Workbook

Sheet Executive Summary
A1: HOTEL BRENDLE LOAN REQUEST
A3: Property: | B3: 601 E Ave A, Robstown, TX 78380
A4: Total Rooms: | B4: 67
A6: LOAN REQUEST:
A7: Total Amount | B7: 850000
A9: USE OF PROCEEDS:
A10: Debt Payoff | B10: 150000
A11: Amenities/Jobsite | B11: 100000
A12: Room Renovation | B12: 600000
A13: Total | B13: =SUM(B10:B12)
A15: TERMS:
A16: Rate | B16: 0.075
A17: Term | B17: 25 years
A18: Monthly P&I | B18: 6281.43
A19: Annual Debt Service | B19: =B18*12

Sheet 10-Year Cash Flow
A1: 10-YEAR MONTHLY CASH FLOW PROJECTION
A3: Year | B3: Month | C3: Rooms | D3: Occ% | E3: Rent | F3: Revenue | G3: Expenses | H3: NOI | I3: Debt Svc | J3: Cash Flow | K3: DSCR
A4: 1 | B4: 1 | C4: 24 | D4: 0.6 | E4: 852 | F4: =C4*D4*E4 | G4: =C4*344.38 | H4: =F4-G4 | I4: 6281.43 | J4: =H4-I4 | K4: =H4/I4
A5: 1 | B5: 2 | C5: 31 | D5: 0.6 | E5: 852 | F5: =C5*D5*E5 | G5: =C5*344.38 | H5: =F5-G5 | I5: 6281.43 | J5: =H5-I5 | K5: =H5/I5
A6: 1 | B6: 3 | C6: 38 | D6: 0.6 | E6: 852 | F6: =C6*D6*E6 | G6: =C6*344.38 | H6: =F6-G6 | I6: 6281.43 | J6: =H6-I6 | K6: =H6/I6
A7: 1 | B7: 4 | C7: 46 | D7: 0.6 | E7: 852 | F7: =C7*D7*E7 | G7: =C7*344.38 | H7: =F7-G7 | I7: 6281.43 | J7: =H7-I7 | K7: =H7/I7
A8: 1 | B8: 5 | C8: 53 | D8: 0.6 | E8: 852 | F8: =C8*D8*E8 | G8: =C8*344.38 | H8: =F8-G8 | I8: 6281.43 | J8: =H8-I8 | K8: =H8/I8
A9: 1 | B9: 6 | C9: 60 | D9: 0.6 | E9: 852 | F9: =C9*D9*E9 | G9: =C9*344.38 | H9: =F9-G9 | I9: 6281.43 | J9: =H9-I9 | K9: =H9/I9
A10: 1 | B10: 7 | C10: 67 | D10: 0.7 | E10: 850 | F10: =C10*D10*E10 | G10: =C10*344.38 | H10: =F10-G10 | I10: 6281.43 | J10: =H10-I10 | K10: =H10/I10
A11: 1 | B11: 8 | C11: 67 | D11: 0.70833333 | E11: 850 | F11: =C11*D11*E11 | G11: =C11*344.38 | H11: =F11-G11 | I11: 6281.43 | J11: =H11-I11 | K11: =H11/I11
A12: 1 | B12: 9 | C12: 67 | D12: 0.71666667 | E12: 850 | F12: =C12*D12*E12 | G12: =C12*344.38 | H12: =F12-G12 | I12: 6281.43 | J12: =H12-I12 | K12: =H12/I12
A13: 1 | B13: 10 | C13: 67 | D13: 0.725 | E13: 850 | F13: =C13*D13*E13 | G13: =C13*344.38 | H13: =F13-G13 | I13: 6281.43 | J13: =H13-I13 | K13: =H13/I13
A14: 1 | B14: 11 | C14: 67 | D14: 0.73333333 | E14: 850 | F14: =C14*D14*E14 | G14: =C14*344.38 | H14: =F14-G14 | I14: 6281.43 | J14: =H14-I14 | K14: =H14/I14
A15: 1 | B15: 12 | C15: 67 | D15: 0.74166667 | E15: 850 | F15: =C15*D15*E15 | G15: =C15*344.38 | H15: =F15-G15 | I15: 6281.43 | J15: =H15-I15 | K15: =H15/I15
... A123: 10 | B123: 12 | C123: 67 | D123: 0.75 | E123: 850 | F123: =C123*D123*E123 | G123: =C123*344.38 | H123: =F123-G123 | I123: 6281.43 | J123: =H123-I123 | K123: =H123/I123

Sheet Annual Summary
A1: ANNUAL SUMMARY
A3: Year | B3: Gross Revenue | C3: Operating Exp | D3: NOI | E3: Debt Service | F3: Cash Flow | G3: DSCR
A4: 1 | B4: =SUM('10-Year Cash Flow'!F4:F15) | C4: =SUM('10-Year Cash Flow'!G4:G15) | D4: =B4-C4 | E4: =SUM('10-Year Cash Flow'!I4:I15) | F4: =D4-E4 | G4: =D4/E4
A5: 2 | B5: =SUM('10-Year Cash Flow'!F16:F27) | C5: =SUM('10-Year Cash Flow'!G16:G27) | D5: =B5-C5 | E5: =SUM('10-Year Cash Flow'!I16:I27) | F5: =D5-E5 | G5: =D5/E5
A6: 3 | B6: =SUM('10-Year Cash Flow'!F28:F39) | C6: =SUM('10-Year Cash Flow'!G28:G39) | D6: =B6-C6 | E6: =SUM('10-Year Cash Flow'!I28:I39) | F6: =D6-E6 | G6: =D6/E6
A7: 4 | B7: =SUM('10-Year Cash Flow'!F40:F51) | C7: =SUM('10-Year Cash Flow'!G40:G51) | D7: =B7-C7 | E7: =SUM('10-Year Cash Flow'!I40:I51) | F7: =D7-E7 | G7: =D7/E7
A8: 5 | B8: =SUM('10-Year Cash Flow'!F52:F63) | C8: =SUM('10-Year Cash Flow'!G52:G63) | D8: =B8-C8 | E8: =SUM('10-Year Cash Flow'!I52:I63) | F8: =D8-E8 | G8: =D8/E8
A9: 6 | B9: =SUM('10-Year Cash Flow'!F64:F75) | C9: =SUM('10-Year Cash Flow'!G64:G75) | D9: =B9-C9 | E9: =SUM('10-Year Cash Flow'!I64:I75) | F9: =D9-E9 | G9: =D9/E9
A10: 7 | B10: =SUM('10-Year Cash Flow'!F76:F87) | C10: =SUM('10-Year Cash Flow'!G76:G87) | D10: =B10-C10 | E10: =SUM('10-Year Cash Flow'!I76:I87) | F10: =D10-E10 | G10: =D10/E10
A11: 8 | B11: =SUM('10-Year Cash Flow'!F88:F99) | C11: =SUM('10-Year Cash Flow'!G88:G99) | D11: =B11-C11 | E11: =SUM('10-Year Cash Flow'!I88:I99) | F11: =D11-E11 | G11: =D11/E11
A12: 9 | B12: =SUM('10-Year Cash Flow'!F100:F111) | C12: =SUM('10-Year Cash Flow'!G100:G111) | D12: =B12-C12 | E12: =SUM('10-Year Cash Flow'!I100:I111) | F12: =D12-E12 | G12: =D12/E12
A13: 10 | B13: =SUM('10-Year Cash Flow'!F112:F123) | C13: =SUM('10-Year Cash Flow'!G112:G123) | D13: =B13-C13 | E13: =SUM('10-Year Cash Flow'!I112:I123) | F13: =D13-E13 | G13: =D13/E13

Sheet Debt Service Schedule
A1: DEBT SERVICE SCHEDULE (25 Years)
A3: Month | B3: Payment | C3: Interest | D3: Principal | E3: Balance
A4: 1 | B4: 6281.43 | C4: 5312.5 | D4: 968.93 | E4: 849031.07
A5: 2 | B5: 6281.43 | C5: 5306.4442 | D5: 974.98581 | E5: 848056.08
A6: 3 | B6: 6281.43 | C6: 5300.3505 | D6: 981.07947 | E6: 847075
A7: 4 | B7: 6281.43 | C7: 5294.2188 | D7: 987.21122 | E7: 846087.79
A8: 5 | B8: 6281.43 | C8: 5288.0487 | D8: 993.38129 | E8: 845094.41
A9: 6 | B9: 6281.43 | C9: 5281.8401 | D9: 999.58992 | E9: 844094.82
A10: 7 | B10: 6281.43 | C10: 5275.5926 | D10: 1005.8374 | E10: 843088.98
A11: 8 | B11: 6281.43 | C11: 5269.3062 | D11: 1012.1238 | E11: 842076.86
A12: 9 | B12: 6281.43 | C12: 5262.9804 | D12: 1018.4496 | E12: 841058.41
A13: 10 | B13: 6281.43 | C13: 5256.6151 | D13: 1024.8149 | E13: 840033.6
A14: 11 | B14: 6281.43 | C14: 5250.21 | D14: 1031.22 | E14: 839002.38
A15: 12 | B15: 6281.43 | C15: 5243.7649 | D15: 1037.6651 | E15: 837964.71
... A303: 300 | B303: 6281.43 | C303: 38.98791 | D303: 6242.4421 | E303: 0

Sheet Sources & Uses
A1: SOURCES & USES OF FUNDS
A3: SOURCES:
A4: New Loan | B4: 850000
A5: Total Sources | B5: =B4
A7: USES:
A8: Existing Debt Payoff | B8: 150000
A9: Amenities & Jobsite | B9: 100000
A10: Room Renovation (40 rooms) | B10: 600000
A11: Total Uses | B11: =SUM(B8:B10)
