Workbook
Name Annual_interest_rate: #REF!
Name Annual_interest_rate: #REF!
Name Beg.Bal: IF(#REF!<>"",#REF!,"")
Name Beg.Bal: IF(#REF!<>"",#REF!,"")
Name buildable: #REF!
Name buildable: #REF!
Name Business_License: #REF!
Name Business_License: #REF!
Name Car_Damages: #REF!
Name Car_Damages: #REF!
Name CITY: [1]OFCPRELM!$B$13
Name Copy_Printing: #REF!
Name Copy_Printing: #REF!
Name Coupon_Sales: #REF!
Name Coupon_Sales: #REF!
Name Credit_Card: #REF!
Name Credit_Card: #REF!
Name Cum.Interest: IF(#REF!<>"",#REF!+#REF!,"")
Name Cum.Interest: IF(#REF!<>"",#REF!+#REF!,"")
Name Customer_Service: #REF!
Name Customer_Service: #REF!
Name ddd: IF(OR(#REF!="",#REF!='Table 1.5'!Total_payments),"",#REF!+1)
Name ddd: IF(OR(#REF!="",#REF!='Table 1A'!Total_payments),"",#REF!+1)
Name ddd: IF(OR(#REF!="",#REF!='Table 3.0'!Total_payments),"",#REF!+1)
Name ddd: IF(OR(#REF!="",#REF!=Total_payments),"",#REF!+1)
Name Degreasing: #REF!
Name Degreasing: #REF!
Name Electricity: #REF!
Name Electricity: #REF!
Name Ending.Balance: IF(#REF!<>"",#REF!-#REF!,"")
Name Ending.Balance: IF(#REF!<>"",#REF!-#REF!,"")
Name Equipment_Repairs: #REF!
Name Equipment_Repairs: #REF!
Name Fire_Protection: #REF!
Name Fire_Protection: #REF!
Name First_payment_due: #REF!
Name First_payment_due: #REF!
Name Incentive_Fee: #REF!
Name Incentive_Fee: #REF!
Name Interest: IF(#REF!<>"",#REF!*'Table 1.1'!Periodic_rate,"")
Name Interest: IF(#REF!<>"",#REF!*'Table 1.2'!Periodic_rate,"")
Name Interest: IF(#REF!<>"",#REF!*'Table 1.5'!Periodic_rate,"")
Name Interest: IF(#REF!<>"",#REF!*'Table 1A'!Periodic_rate,"")
Name Interest: IF(#REF!<>"",#REF!*'Table 3.0'!Periodic_rate,"")
Name Interest: IF(#REF!<>"",#REF!*Periodic_rate,"")
Name Janitorial: #REF!
Name Janitorial: #REF!
Name Key_Card_Sales: #REF!
Name Key_Card_Sales: #REF!
Name Keys: #REF!
Name Keys: #REF!
Name Lamping: #REF!
Name Lamping: #REF!
Name Last_Row: IF(Values_Entered,Header_Row+Number_of_Payments,Header_Row)
Name Liability_Insurance: #REF!
Name Liability_Insurance: #REF!
Name Management_Fee: #REF!
Name Management_Fee: #REF!
Name Mileage: #REF!
Name Mileage: #REF!

Sheet Table 1A
A1: TABLE 1A - INPUT ASSUMPTIONS - | D1: TUCSON AIRPORT CENTER
A3: General Assumptions | E3: Rollover Leasing Assumptions | F3: Standard | G3: Basement | H3: US Orthopedics | I3: Warehouse (24,000 Sq.Ft.)
A4: Analysis Start | C4: 38534 | E4: Renewal Probability | F4: 0.75 | G4: 0.7 | H4: 0.8 | I4: 0.75
A5: Total Net Rentable Area | C5: 129097 | E5: Market Rent New ($ per Sq.Ft./Mos/NNN) | F5: 0.55 | G5: 15 | H5: 27 | I5: 0.4
A6: Market Rent Growth (%) | C6: 0.03 | E6: Market Rent Renewal ($ per Sq.Ft./Mos/NNN) | F6: 0.55 | G6: 17 | H6: 27 | I6: 0.4
A7: Expense Growth | C7: 0.03 | E7: Months Vacant | F7: 6 | G7: 9 | H7: 9 | I7: 9
A8: Operating Expenses ($/Sq. Ft.) | C8: 2.5163482 | E8: Tenant Improvements
A9: Deferred Maintenance | C9: 1000000 | E9: New | F9: 8 | G9: 20 | H9: 20 | I9: 4
A10: Capital Reserves ($/Sq. Ft.) | C10: 0.1545 | E10: Renewal | F10: 2 | G10: 10 | H10: 10 | I10: 0
A11: Closing Costs (B) | C11: =#REF! -> #REF! | E11: Leasing Commissions
A12: Vacancy Loss | C12: 0.1 | E12: New | F12: 0.06 | G12: 0.08 | H12: 0.08 | I12: 0.06
A13: Occupancy | C13: 0.42 | E13: Renewal | F13: 0.03 | G13: 0.03 | H13: 0.03 | I13: 0.03
A14: Leased Up By | C14: 39326 | E14: Rent Abatements | F14: 0 | G14: 3 | H14: 3 | I14: 0
A15: Acquisition Commission (A) | C15: =3%*F20 -> 132000 | E15: Annual Rent Increases | F15: 0.03 | G15: 0 | H15: 0 | I15: 0.03
E16: Lease Term | F16: 5 yrs | G16: 3 | H16: 5 | I16: 5 yrs
A17: Debt Assumptions- Alliance Bank | E17: Lease Type | F17: NNN | G17: Base Year | H17: Base Year | I17: NNN
A18: Loan Amount | C18: 3600000
A19: Cap-Ex, TI & LC Holdback | C19: =450000+475000+125000 -> 1050000 | E19: Pricing
A20: Initial Funding | C20: =C18-C19 -> 2550000 | E20: Asking Price | F20: 4400000
A21: LTV | C21: =C20/F20 -> 0.57954545 | E21: Cap Rate | F21: 0.046780909
A22: Amortization (months) | C22: Interest Only | E22: Table 3.0 | F22: 4400000
A23: Interest Rate- Acquisition | C23: 6.23% Fixed | E23: Cap Rate (on Yr 1 Proforma) | F23: 0.061696364
A24: Interest Rate- Cap-Ex, TI & LC Draws | C24: Prime + 1% (Est. 7.5% Yr 1)
A25: Points and Fees | C25: 36000 | E25: Detailed Closing Costs
A26: Prepayment Penalty | C26: 1% in year 1 then $0 | E26: Commission (Acquisition) | F26: 132000 | H26: 132000
A27: Term (years/mos) | C27: 2 years | E27: Due Diligence and Legal | F27: =F29-F26-F28 -> #REF! | H27: 94730
E28: Loan Fees | F28: 36000
A29: Debt Assumptions- Refinance | E29: Total Est. Closing Costs | F29: =C11 -> #REF! | H29: 250200
A30: Loan Amount | C30: 5500000
A31: TI & LC Holdback | C31: 0
A32: Initial Funding | C32: =C30-C31 -> 5500000 | E32: (A)- Included in Closing Costs
A33: LTV | C33: 0.7 | E33: (B)- See Detailed Closing Costs Above
A34: Amortization (months) | C34: 300
A35: Interest Rate | C35: 0.07
A36: Points and Fees | C36: 0.01
A37: Term (years/mos) | C37: 10

Sheet Table 1.0
A1: TABLE 1.0 - TUCSON AIRPORT CENTER- EXISTING RENT ROLL AS OF MAY 31, 2005
A4: TENANT | B4: SUITE | C4: SF | D4: BASE | E4: $/SF | F4: $/SF | G4: LEASE | H4: EXP. REIMB. | I4: $/YR | J4: TOTAL | K4: $/SF/YR | L4: $/SF/MO | M4: LEASE | N4: LEASE | O4: INCREASES | Q4: NOTES
B5: # | D5: RENT/YR | E5: /YR | F5: /MO | G5: TYPE | H5: SF/YR (B) | J5: REVENUES | M5: START | N5: EXPIRES | O5: ($/SF/YR)
S7: =S11/12 -> 0.95833333
A8: Qantas Airways | B8: 1 | C8: 19204 | D8: 154526 | E8: =D8/C8 -> 8.0465528 | F8: =E8/12 -> 0.67054607 | G8: Net (C) | H8: 2.52 | I8: =H8*C8 -> 48394.08 | J8: =I8+D8 -> 202920.08 | K8: =IF(C8=0,0,J8/C8) -> 10.566553 | L8: =K8/12 -> 0.88054607 | M8: 37653 | N8: 39600 | O8: 2.5% Bumps | Q8: See (C) below. | S8: =E8*1.15 -> 9.2535357 | T8: =S8*1.15 -> 10.641566 | U8: =T8*1.15 -> 12.237801 | V8: =U8*1.15 -> 14.073471
A9: Davis Select | B9: 2 | C9: 12512 | D9: 64562 | E9: =D9/C9 -> 5.1600064 | F9: =E9/12 -> 0.43000053 | G9: Net | H9: 2.52 | I9: =H9*C9 -> 31530.24 | J9: =I9+D9 -> 96092.24 | K9: =IF(C9=0,0,J9/C9) -> 7.6800064 | M9: 37773 | N9: 39692 | O9: 2.5% Bumps
A10: Davis Select (Expansion Space) | B10: 2a | C10: 7488 | D10: 41334 | E10: =D10/C10 -> 5.5200321 | F10: =E10/12 -> 0.46000267 | G10: Net | H10: 2.52 | I10: =H10*C10 -> 18869.76 | J10: =I10+D10 -> 60203.76 | K10: =IF(C10=0,0,J10/C10) -> 8.0400321 | L10: =K10/12 -> 0.67000267 | M10: 38412 | N10: 39692 | O10: 2.5% Bumps | S10: 12.93 | T10: 14.22
A11: APEX | B11: =B35 -> 0 | C11: 15000 | D11: 95400 | E11: =D11/C11 -> 6.36 | F11: =E11/12 -> 0.53 | G11: Net | H11: 2.52 | I11: =H11*C11 -> 37800 | J11: =I11+D11 -> 133200 | K11: =IF(C11=0,0,J11/C11) -> 8.88 | L11: =K11/12 -> 0.74 | M11: 37803 | N11: 39630 | O11: 2.5% Bumps | S11: =10*1.15 -> 11.5
A12: Iron Mountain Temp. Space | B12: 2B | C12: 24000 | D12: =C12*E12 -> 115200 | E12: =F12*12 -> 4.8 | F12: 0.4 | G12: Net | H12: 2.52 | I12: =H12*C12 -> 60480 | J12: =I12+D12 -> 175680 | K12: =IF(C12=0,0,J12/C12) -> 7.32 | M12: 38443 | N12: 38596 | O12: None | Q12: Temp. Lease for Storage
A13: Building C Ste 1 (VACANT) | B13: C1 | C13: 7500
A14: Building C Ste 2 (VACANT) | B14: C2 | C14: 7500
A15: Building A Ste 1 (VACANT) | B15: A1 | C15: 12000
A16: Building A Ste 2 (VACANT) | B16: A2 | C16: 12000
A17: Building A Ste 3 (VACANT) | B17: A3 | C17: 11893
A20: Totals | C20: =SUM(C8:C19) -> 129097 | D20: =SUM(D8:D12) -> 471022 | E20: =D20/(C21) -> 6.0229912 | F20: =ROUND(E20/12,2) -> 0.5 | H20: =I20/C21 -> 2.52 | I20: =SUM(I8:I17) -> 197074.08 | J20: =I20+D20 -> 668096.08 | K20: =J20/C21 -> 8.5429912 | L20: =K20/12 -> 0.71191593
A21: Total Space Occupied | C21: =SUM(C8:C12) -> 78204
A22: % Occupied | C22: =(C21-C12)/C20 -> 0.41987033 | D22: (A)
A23: Avg. Rent of Occupied Space | C23: =(D20-D12)/(C21-C12) -> 6.5644971 | D23: /SF/YR (A)
A25: (A) Excludes Iron Mountain Temporary Space
A26: (B) NNN tenants pay pro-rata share of operating expenses.
A27: (C) QANTAS Airways' actual lease rate is modified gross. Qantas lease rate converted to NNN for comparison purposes. The actual lease rate is $10.56/sq.ft./Yr. with expense reimbursements over 2003 base year.
A54: =A33 -> 0 | B54: 1 | C54: 3600
A55: =A34 -> 0 | B55: 2 | C55: 1200
A56: =A35 -> 0 | B56: 3 | C56: 1200
A57: =A36 -> 0 | B57: 4 | C57: 1500
A58: =A37 -> 0 | B58: 5 | C58: 1500
A59: =A38 -> 0 | B59: 6 | C59: 1500
A60: =A39 -> 0 | B60: 7 | C60: 1500
A61: =A40 -> 0 | B61: 8 | C61: 1200
A62: =A41 -> 0 | B62: 9 | C62: 1200
A63: =A42 -> 0 | B63: 10 | C63: 1200
A64: =A43 -> 0 | B64: 11 | C64: 1200
C66: =SUM(C54:C64) -> 16800

Sheet Table 1.1
A1: TABLE 1.1 -TUCSON AIRPORT CENTER - GROSS POTENTIAL RENT PER SQUARE FOOT (1)
C3: Market Rents | D3: Yr 1 | E3: Yr 2 | F3: Yr 3 | G3: Yr 4 | H3: Yr 5 | I3: Yr 6 | J3: Yr 7 | K3: Yr 8 | L3: Yr 9
C4: Standard | D4: =0.55*12 -> 6.6 | E4: =D4*1.03 -> 6.798 | F4: =E4*1.03 -> 7.00194 | G4: =F4*1.03 -> 7.2119982 | H4: =G4*1.03 -> 7.4283581 | I4: =H4*1.03 -> 7.6512089 | J4: =I4*1.03 -> 7.8807452 | K4: =J4*1.03 -> 8.1171675 | L4: =K4*1.03 -> 8.3606825
C5: Warehouse | D5: =0.4*12 -> 4.8 | E5: =D5*1.03 -> 4.944 | F5: =E5*1.03 -> 5.09232 | G5: =F5*1.03 -> 5.2450896 | H5: =G5*1.03 -> 5.4024423 | I5: =H5*1.03 -> 5.5645156 | J5: =I5*1.03 -> 5.731451 | K5: =J5*1.03 -> 5.9033946 | L5: =K5*1.03 -> 6.0804964
C6: Fiscal Year Ending | D6: 38869 | E6: 39234 | F6: 39600 | G6: 39965 | H6: 40330 | I6: 40695 | J6: 41061 | K6: 41426 | L6: 41791
A7: Rental Rates - $/SF | B7: Suite | C7: SF | D7: Yr 1 | E7: Yr 2 | F7: Yr 3 | G7: Yr 4 | H7: Yr 5 | I7: Yr 6 | J7: Yr 7 | K7: Yr 8 | L7: Yr 9 | N7: TENANT | O7: SUITE
N8: Qantas Airways | O8: 2801 | P8: 203370 | Q8: 210092 | R8: 214317 | S8: 138500 | T8: 142308 | U8: 146577 | V8: 150974 | W8: 155504 | X8: 160169 | Y8: 164573
A9: ='Table 1.0'!A8 -> Qantas Airways | B9: ='Table 1.0'!B8 -> 1 | C9: ='Table 1.0'!C8 -> 19204 | D9: =IF($C9,P8/$C9,0)-P23 -> 8.0736331 | E9: =IF($C9,Q8/$C9,0)-Q23 -> 8.2478973 | F9: =IF($C9,R8/$C9,0)-R23 -> 8.3551511 | G9: =IF($C9,S8/$C9,0) -> 7.2120392 | H9: =IF($C9,T8/$C9,0) -> 7.4103312 | I9: =IF($C9,U8/$C9,0) -> 7.6326286 | J9: =IF($C9,V8/$C9,0) -> 7.8615913 | K9: =IF($C9,W8/$C9,0) -> 8.0974797 | L9: =IF($C9,X8/$C9,0) -> 8.3403978 | N9: Davis Select | O9: 2949A | P9: 69692 | Q9: 71193 | R9: 73320 | S9: 86446 | T9: 92041 | U9: 94802 | V9: 97647 | W9: 100576 | X9: 103593 | Y9: 106440
A10: ='Table 1.0'!A9 -> Davis Select | B10: ='Table 1.0'!B9 -> 2 | C10: ='Table 1.0'!C9 -> 12512 | D10: =IF($C10,P9/$C10,0) -> 5.5700128 | E10: =IF($C10,Q9/$C10,0) -> 5.6899776 | F10: =IF($C10,R9/$C10,0) -> 5.8599744 | G10: =IF($C10,S9/$C10,0) -> 6.9090473 | H10: =IF($C10,T9/$C10,0) -> 7.356218 | I10: =IF($C10,U9/$C10,0) -> 7.5768862 | J10: =IF($C10,V9/$C10,0) -> 7.8042679 | K10: =IF($C10,W9/$C10,0) -> 8.0383632 | L10: =IF($C10,X9/$C10,0) -> 8.2794917 | N10: Davis Expansion Space | O10: 2949 A | P10: 41708 | Q10: 42607 | R10: 43880 | S10: 51734 | T10: 55084 | U10: 56736 | V10: 58438 | W10: 60191 | X10: 61997 | Y10: 63700
A11: ='Table 1.0'!A10 -> Davis Select (Expansion Space) | B11: ='Table 1.0'!B10 -> 2a | C11: ='Table 1.0'!C10 -> 7488 | D11: =IF($C11,P10/$C11,0) -> 5.5699786 | E11: =IF($C11,Q10/$C11,0) -> 5.6900374 | F11: =IF($C11,R10/$C11,0) -> 5.8600427 | G11: =IF($C11,S10/$C11,0) -> 6.9089209 | H11: =IF($C11,T10/$C11,0) -> 7.3563034 | I11: =IF($C11,U10/$C11,0) -> 7.5769231 | J11: =IF($C11,V10/$C11,0) -> 7.8042201 | K11: =IF($C11,W10/$C11,0) -> 8.038328 | L11: =IF($C11,X10/$C11,0) -> 8.2795139 | N11: APEX | O11: 15000 | P11: 95400 | Q11: 99000 | R11: 100800 | S11: 107565 | T11: 110884 | U11: 114211 | V11: 117637 | W11: 121166 | X11: 124802 | Y11: 128232
A12: ='Table 1.0'!A11 -> APEX | B12: ='Table 1.0'!B11 -> 0 | C12: ='Table 1.0'!C11 -> 15000 | D12: =IF($C12,P11/$C12,0) -> 6.36 | E12: =IF($C12,Q11/$C12,0) -> 6.6 | F12: =IF($C12,R11/$C12,0) -> 6.72 | G12: =IF($C12,S11/$C12,0) -> 7.171 | H12: =IF($C12,T11/$C12,0) -> 7.3922667 | I12: =IF($C12,U11/$C12,0) -> 7.6140667 | J12: =IF($C12,V11/$C12,0) -> 7.8424667 | K12: =IF($C12,W11/$C12,0) -> 8.0777333 | L12: =IF($C12,X11/$C12,0) -> 8.3201333 | N12: Iron Mountain | O12: Bldg E | P12: 115200 | Q12: 118656 | R12: 122216 | S12: 125882 | T12: 129659 | U12: 133548 | V12: 137555 | W12: 140994 | X12: 145224 | Y12: 149580
A13: Iron Mountain Temp. Space (A) | B13: ='Table 1.0'!B12 -> 2B | C13: ='Table 1.0'!C12 -> 24000 | D13: =IF($C13,P12/$C13,0) -> 4.8 | E13: =IF($C13,Q12/$C13,0) -> 4.944 | F13: =IF($C13,R12/$C13,0) -> 5.0923333 | G13: =IF($C13,S12/$C13,0) -> 5.2450833 | H13: =IF($C13,T12/$C13,0) -> 5.4024583 | I13: =IF($C13,U12/$C13,0) -> 5.5645 | J13: =IF($C13,V12/$C13,0) -> 5.7314583 | K13: =IF($C13,W12/$C13,0) -> 5.87475 | L13: =IF($C13,X12/$C13,0) -> 6.051 | N13: Building C- Suite 1 | O13: Mo 8 | P13: 49500 | Q13: 49624 | R13: 51112 | S13: 52646 | T13: 54225 | U13: 55852 | V13: 59106 | W13: 60879 | X13: 62705 | Y13: 64586
A14: ='Table 1.0'!A13 -> Building C Ste 1 (VACANT) | B14: ='Table 1.0'!B13 -> C1 | C14: ='Table 1.0'!C13 -> 7500 | D14: =IF($C14,P13/$C14,0) -> 6.6 | E14: =IF($C14,Q13/$C14,0) -> 6.6165333 | F14: =IF($C14,R13/$C14,0) -> 6.8149333 | G14: =IF($C14,S13/$C14,0) -> 7.0194667 | H14: =IF($C14,T13/$C14,0) -> 7.23 | I14: =IF($C14,U13/$C14,0) -> 7.4469333 | J14: =IF($C14,V13/$C14,0) -> 7.8808 | K14: =IF($C14,W13/$C14,0) -> 8.1172 | L14: =IF($C14,X13/$C14,0) -> 8.3606667 | N14: Building C- Suite 2 | O14: Mo 10 | P14: 49500 | Q14: 50119 | R14: 50366 | S14: 51877 | T14: 53434 | U14: 55037 | V14: 57691 | W14: 59992 | X14: 61792 | Y14: 63646
A15: ='Table 1.0'!A14 -> Building C Ste 2 (VACANT) | B15: ='Table 1.0'!B14 -> C2 | C15: ='Table 1.0'!C14 -> 7500 | D15: =IF($C15,P14/$C15,0) -> 6.6 | E15: =IF($C15,Q14/$C15,0) -> 6.6825333 | F15: =IF($C15,R14/$C15,0) -> 6.7154667 | G15: =IF($C15,S14/$C15,0) -> 6.9169333 | H15: =IF($C15,T14/$C15,0) -> 7.1245333 | I15: =IF($C15,U14/$C15,0) -> 7.3382667 | J15: =IF($C15,V14/$C15,0) -> 7.6921333 | K15: =IF($C15,W14/$C15,0) -> 7.9989333 | L15: =IF($C15,X14/$C15,0) -> 8.2389333 | N15: Bldg A Suite 1 | O15: Mo 5 | P15: 64800 | Q15: 65772 | R15: 67745 | S15: 69778 | T15: 71871 | U15: 74027 | V15: 75872 | W15: 78148 | X15: 80493 | Y15: 82908
A16: ='Table 1.0'!A15 -> Building A Ste 1 (VACANT) | B16: ='Table 1.0'!B15 -> A1 | C16: ='Table 1.0'!C15 -> 12000 | D16: =IF($C16,P15/$C16,0) -> 5.4 | E16: =IF($C16,Q15/$C16,0) -> 5.481 | F16: =IF($C16,R15/$C16,0) -> 5.6454167 | G16: =IF($C16,S15/$C16,0) -> 5.8148333 | H16: =IF($C16,T15/$C16,0) -> 5.98925 | I16: =IF($C16,U15/$C16,0) -> 6.1689167 | J16: =IF($C16,V15/$C16,0) -> 6.3226667 | K16: =IF($C16,W15/$C16,0) -> 6.5123333 | L16: =IF($C16,X15/$C16,0) -> 6.70775 | N16: Bldg A Suite 2 | O16: Mo 12 | P16: 79200 | Q16: 80982 | R16: 79794 | S16: 82188 | T16: 84653 | U16: 87193 | V16: 90498 | W16: 95042 | X16: 97893 | Y16: 100830
A17: ='Table 1.0'!A16 -> Building A Ste 2 (VACANT) | B17: ='Table 1.0'!B16 -> A2 | C17: ='Table 1.0'!C16 -> 12000 | D17: =IF($C17,P16/$C17,0) -> 6.6 | E17: =IF($C17,Q16/$C17,0) -> 6.7485 | F17: =IF($C17,R16/$C17,0) -> 6.6495 | G17: =IF($C17,S16/$C17,0) -> 6.849 | H17: =IF($C17,T16/$C17,0) -> 7.0544167 | I17: =IF($C17,U16/$C17,0) -> 7.2660833 | J17: =IF($C17,V16/$C17,0) -> 7.5415 | K17: =IF($C17,W16/$C17,0) -> 7.9201667 | L17: =IF($C17,X16/$C17,0) -> 8.15775 | N17: Bldg A Suite 3 | O17: Mo 17 | P17: 78494 | Q17: 80849 | R17: 79291 | S17: 80456 | T17: 82870 | U17: 85356 | V17: 87917 | W17: 95172 | X17: 98710 | Y17: 101671
A18: ='Table 1.0'!A17 -> Building A Ste 3 (VACANT) | B18: ='Table 1.0'!B17 -> A3 | C18: ='Table 1.0'!C17 -> 11893 | D18: =IF($C18,P17/$C18,0) -> 6.6000168 | E18: =IF($C18,Q17/$C18,0) -> 6.7980325 | F18: =IF($C18,R17/$C18,0) -> 6.667031 | G18: =IF($C18,S17/$C18,0) -> 6.7649878 | H18: =IF($C18,T17/$C18,0) -> 6.9679643 | I18: =IF($C18,U17/$C18,0) -> 7.1769949 | J18: =IF($C18,V17/$C18,0) -> 7.3923316 | K18: =IF($C18,W17/$C18,0) -> 8.0023543 | L18: =IF($C18,X17/$C18,0) -> 8.2998402
C19: =SUM(C9:C18) -> 129097
C20: Average Potential Lease Rate: | D20: =($C$9*D9+$C$10*D10+$C$11*D11+$C$12*D12+$C$13*D13+$C$14*D14+$C$15*D15+$C$16*D16+$C$17*D17+$C$18*D18)/$C$19 -> 6.1855818 | E20: =($C$9*E9+$C$10*E10+$C$11*E11+$C$12*E12+$C$13*E13+$C$14*E14+$C$15*E15+$C$16*E16+$C$17*E17+$C$18*E18)/$C$19 -> 6.3300822 | F20: =($C$9*F9+$C$10*F10+$C$11*F11+$C$12*F12+$C$13*F13+$C$14*F14+$C$15*F15+$C$16*F16+$C$17*F17+$C$18*F18)/$C$19 -> 6.4213446 | G20: =($C$9*G9+$C$10*G10+$C$11*G11+$C$12*G12+$C$13*G13+$C$14*G14+$C$15*G15+$C$16*G16+$C$17*G17+$C$18*G18)/$C$19 -> 6.5615158 | H20: =($C$9*H9+$C$10*H10+$C$11*H11+$C$12*H12+$C$13*H13+$C$14*H14+$C$15*H15+$C$16*H16+$C$17*H17+$C$18*H18)/$C$19 -> 6.7935661 | I20: =($C$9*I9+$C$10*I10+$C$11*I11+$C$12*I12+$C$13*I13+$C$14*I14+$C$15*I15+$C$16*I16+$C$17*I17+$C$18*I18)/$C$19 -> 6.9973663 | J20: =($C$9*J9+$C$10*J10+$C$11*J11+$C$12*J12+$C$13*J13+$C$14*J14+$C$15*J15+$C$16*J16+$C$17*J17+$C$18*J18)/$C$19 -> 7.2297187 | K20: =($C$9*K9+$C$10*K10+$C$11*K11+$C$12*K12+$C$13*K13+$C$14*K14+$C$15*K15+$C$16*K16+$C$17*K17+$C$18*K18)/$C$19 -> 7.4956351 | L20: =($C$9*L9+$C$10*L10+$C$11*L11+$C$12*L12+$C$13*L13+$C$14*L14+$C$15*L15+$C$16*L16+$C$17*L17+$C$18*L18)/$C$19 -> 7.7258031
D21: =(D20-'Table 1.0'!C23)/'Table 1.0'!C23 -> -0.057721911 | E21: =(E20-D20)/D20 -> 0.023360844 | F21: =(F20-E20)/E20 -> 0.014417254 | G21: =(G20-F20)/F20 -> 0.021828945 | H21: =(H20-G20)/G20 -> 0.035365353 | I21: =(I20-H20)/H20 -> 0.029999008 | J21: =(J20-I20)/I20 -> 0.033205696 | K21: =(K20-J20)/J20 -> 0.036781006 | L21: =(L20-K20)/K20 -> 0.03070694 | N21: 129097 | P21: Yr 1 | Q21: Yr 2 | R21: yr 3
N22: Estimated Expenses | P22: 324853 | Q22: 347544 | R22: 362100 | S22: 372239 | T22: 384197 | U22: 395387 | V22: 406751 | W22: 419841 | X22: 431662
A23: Note- Qantas Airways' actual rental rate is modified gross. Rental rate was converted to NNN for purposes of this table by subtracting estimated exspenses/sq.ft. for the remaining term of lease. | N23: Per Sq.Ft. | P23: =P22/$N$21 -> 2.5163482 | Q23: =Q22/$N$21 -> 2.6921152 | R23: =R22/$N$21 -> 2.8048677 | S23: =S22/$N$21 -> 2.8834055 | T23: =T22/$N$21 -> 2.9760335 | U23: =U22/$N$21 -> 3.0627125 | V23: =V22/$N$21 -> 3.1507394 | W23: =W22/$N$21 -> 3.252136 | ... Y23: =Y22/$N$21 -> 0
A24: Subsequent leasing for space reported as NNN.
A26: (A)- Warehouse Space.

Sheet Table 1.2
A1: TABLE 1.2 -TUCSON AIRPORT CENTER- MONTHS VACANT, FREE RENT, & NEW LEASE PROJECTION (1)
C3: Fiscal Year Ending | D3: ='Table 1.1'!D6 -> 38869 | E3: ='Table 1.1'!E6 -> 39234 | F3: ='Table 1.1'!F6 -> 39600 | G3: ='Table 1.1'!G6 -> 39965 | H3: ='Table 1.1'!H6 -> 40330 | I3: ='Table 1.1'!I6 -> 40695 | J3: ='Table 1.1'!J6 -> 41061 | K3: ='Table 1.1'!K6 -> 41426 | L3: ='Table 1.1'!L6 -> 41791
D4: Yr 1 | E4: Yr 2 | F4: Yr 3 | G4: Yr 4 | H4: Yr 5 | I4: Yr 6 | J4: Yr 7 | K4: Yr 8 | L4: Yr 9 | AA4: Yr 1 | AB4: Yr 2 | AC4: Yr 3 | AD4: Yr 4 | AE4: Yr 5 | AF4: Yr 6 | AG4: Yr 7 | AH4: Yr 8 | AI4: Yr 9
B5: SF | C5: Years In
C6: New Lease | D6: Months Vacant per space in year (months/year) 2
A7: ='Table 1.0'!A8 -> Qantas Airways | B7: ='Table 1.0'!C8 -> 19204 | C7: 5 | G7: =AD7 -> 1.9999856 | L7: =AI7 -> 2.009776 | O7: Qantas Airways | P7: 2801 | Q7: 203370 | R7: 210092 | S7: 214317 | T7: 115416 | U7: 141962 | V7: 146221 | W7: 150607 | X7: 155125 | Y7: 133019 | Z7: 163770 | AA7: =12-((Q7/'Table 1.3'!O9)*12) -> 0 | AB7: =12-((R7/'Table 1.3'!P9)*12) -> 0 | AC7: =12-((S7/'Table 1.3'!Q9)*12) -> 0 | AD7: =12-((T7/'Table 1.3'!R9)*12) -> 1.9999856 | AE7: =12-((U7/'Table 1.3'!S9)*12) -> 0 | AF7: =12-((V7/'Table 1.3'!T9)*12) -> 0 | AG7: =12-((W7/'Table 1.3'!U9)*12) -> 0 | AH7: =12-((X7/'Table 1.3'!V9)*12) -> 0 | AI7: =12-((Y7/'Table 1.3'!W9)*12) -> 2.009776
A8: ='Table 1.0'!A9 -> Davis Select | B8: ='Table 1.0'!C9 -> 12512 | C8: 5 | G8: =AD8 -> 2.0876627 | L8: =AI8 -> 2.0245791 | O8: Davis Select | P8: 2949A | Q8: 69692 | R8: 71193 | S8: 73320 | T8: 71406 | U8: 91816 | V8: 94570 | W8: 97407 | X8: 100329 | Y8: 85905 | Z8: 105916 | AA8: =12-((Q8/'Table 1.3'!O10)*12) -> 0 | AB8: =12-((R8/'Table 1.3'!P10)*12) -> 0 | AC8: =12-((S8/'Table 1.3'!Q10)*12) -> 0 | AD8: =12-((T8/'Table 1.3'!R10)*12) -> 2.0876627 | AE8: =12-((U8/'Table 1.3'!S10)*12) -> 0 | AF8: =12-((V8/'Table 1.3'!T10)*12) -> 0 | AG8: =12-((W8/'Table 1.3'!U10)*12) -> 0 | AH8: =12-((X8/'Table 1.3'!V10)*12) -> 0 | AI8: =12-((Y8/'Table 1.3'!W10)*12) -> 2.0245791
A9: ='Table 1.0'!A10 -> Davis Select (Expansion Space) | B9: ='Table 1.0'!C10 -> 7488 | C9: 5 | G9: =AD9 -> 2.0877936 | L9: =AI9 -> 2.0245452 | O9: Davis Expansion Space | P9: 2949 A | Q9: 41708 | R9: 42607 | S9: 43880 | T9: 42734 | U9: 54949 | V9: 56597 | W9: 58295 | X9: 60044 | Y9: 51411 | Z9: 63387 | AA9: =12-((Q9/'Table 1.3'!O11)*12) -> 0 | AB9: =12-((R9/'Table 1.3'!P11)*12) -> 0 | AC9: =12-((S9/'Table 1.3'!Q11)*12) -> 0 | AD9: =12-((T9/'Table 1.3'!R11)*12) -> 2.0877936 | AE9: =12-((U9/'Table 1.3'!S11)*12) -> 0 | AF9: =12-((V9/'Table 1.3'!T11)*12) -> 0 | AG9: =12-((W9/'Table 1.3'!U11)*12) -> 0 | AH9: =12-((X9/'Table 1.3'!V11)*12) -> 0 | AI9: =12-((Y9/'Table 1.3'!W11)*12) -> 2.0245452
A10: ='Table 1.0'!A11 -> APEX | B10: ='Table 1.0'!C11 -> 15000 | C10: 5 | G10: =AD10 -> 2.0114349 | L10: =AI10 -> 2.0146991 | O10: APEX | P10: 15000 | Q10: 95400 | R10: 99000 | S10: 100800 | T10: 89535 | U10: 110614 | V10: 113932 | W10: 117350 | X10: 120871 | Y10: 103595 | Z10: 127605 | AA10: =12-((Q10/'Table 1.3'!O12)*12) -> 0 | AB10: =12-((R10/'Table 1.3'!P12)*12) -> 0 | AC10: =12-((S10/'Table 1.3'!Q12)*12) -> 0 | AD10: =12-((T10/'Table 1.3'!R12)*12) -> 2.0114349 | AE10: =12-((U10/'Table 1.3'!S12)*12) -> 0 | AF10: =12-((V10/'Table 1.3'!T12)*12) -> 0 | AG10: =12-((W10/'Table 1.3'!U12)*12) -> 0 | AH10: =12-((X10/'Table 1.3'!V12)*12) -> 0 | AI10: =12-((Y10/'Table 1.3'!W12)*12) -> 2.0146991
A11: ='Table 1.0'!A12 -> Iron Mountain Temp. Space | B11: ='Table 1.0'!C12 -> 24000 | C11: 5 | D11: =AA11 -> 9 | J11: =AG11 -> 2.0000145 | O11: Iron Mountain | P11: Bldg E | Q11: 28800 | R11: 118656 | S11: 122216 | T11: 125882 | U11: 129659 | V11: 133548 | W11: 114629 | X11: 140994 | Y11: 145224 | Z11: 149580 | AA11: =12-((Q11/'Table 1.3'!O13)*12) -> 9 | AB11: =12-((R11/'Table 1.3'!P13)*12) -> 0 | AC11: =12-((S11/'Table 1.3'!Q13)*12) -> 0 | AD11: =12-((T11/'Table 1.3'!R13)*12) -> 0 | AE11: =12-((U11/'Table 1.3'!S13)*12) -> 0 | AF11: =12-((V11/'Table 1.3'!T13)*12) -> 0 | AG11: =12-((W11/'Table 1.3'!U13)*12) -> 2.0000145 | AH11: =12-((X11/'Table 1.3'!V13)*12) -> 0 | AI11: =12-((Y11/'Table 1.3'!W13)*12) -> 0
A12: ='Table 1.0'!A13 -> Building C Ste 1 (VACANT) | B12: ='Table 1.0'!C13 -> 7500 | C12: 5 | D12: =AA12 -> 11 | I12: =AF12 -> 1.0274296 | J12: =AG12 -> 0.9999154 | O12: Building C- Suite 1 | P12: Mo 8 | Q12: 4125 | R12: 49624 | S12: 51112 | T12: 52646 | U12: 54225 | V12: 51070 | W12: 54180 | X12: 60731 | Y12: 62553 | Z12: 64430 | AA12: =12-((Q12/'Table 1.3'!O14)*12) -> 11 | AB12: =12-((R12/'Table 1.3'!P14)*12) -> 0 | AC12: =12-((S12/'Table 1.3'!Q14)*12) -> 0 | AD12: =12-((T12/'Table 1.3'!R14)*12) -> 0 | AE12: =12-((U12/'Table 1.3'!S14)*12) -> 0 | AF12: =12-((V12/'Table 1.3'!T14)*12) -> 1.0274296 | AG12: =12-((W12/'Table 1.3'!U14)*12) -> 0.9999154 | AH12: =12-((X12/'Table 1.3'!V14)*12) -> 0 | AI12: =12-((Y12/'Table 1.3'!W14)*12) -> 0
A13: ='Table 1.0'!A14 -> Building C Ste 2 (VACANT) | B13: ='Table 1.0'!C14 -> 7500 | C13: 5 | D13: =AA13 -> 12 | E13: =AB13 -> 5.0864542 | J13: =AG13 -> 2.0490189 | O13: Building C- Suite 2 | P13: Mo 10 | Q13: 0 | R13: 28875 | S13: 50366 | T13: 51877 | U13: 53434 | V13: 55037 | W13: 47841 | X13: 59844 | Y13: 61640 | Z13: 63489 | AA13: =12-((Q13/'Table 1.3'!O15)*12) -> 12 | AB13: =12-((R13/'Table 1.3'!P15)*12) -> 5.0864542 | AC13: =12-((S13/'Table 1.3'!Q15)*12) -> 0 | AD13: =12-((T13/'Table 1.3'!R15)*12) -> 0 | AE13: =12-((U13/'Table 1.3'!S15)*12) -> 0 | AF13: =12-((V13/'Table 1.3'!T15)*12) -> 0 | AG13: =12-((W13/'Table 1.3'!U15)*12) -> 2.0490189 | AH13: =12-((X13/'Table 1.3'!V15)*12) -> 0 | AI13: =12-((Y13/'Table 1.3'!W15)*12) -> 0
A14: ='Table 1.0'!A15 -> Building A Ste 1 (VACANT) | B14: ='Table 1.0'!C15 -> 12000 | C14: 5 | D14: =AA14 -> 6 | I14: =AF14 -> 2.0295298 | O14: Bldg A Suite 1 | P14: Mo 5 | Q14: 32400 | R14: 65772 | S14: 67745 | T14: 69778 | U14: 71871 | V14: 61507 | W14: 75872 | X14: 78148 | Y14: 80493 | Z14: 82908 | AA14: =12-((Q14/'Table 1.3'!O16)*12) -> 6 | AB14: =12-((R14/'Table 1.3'!P16)*12) -> 0 | AC14: =12-((S14/'Table 1.3'!Q16)*12) -> 0 | AD14: =12-((T14/'Table 1.3'!R16)*12) -> 0 | AE14: =12-((U14/'Table 1.3'!S16)*12) -> 0 | AF14: =12-((V14/'Table 1.3'!T16)*12) -> 2.0295298 | AG14: =12-((W14/'Table 1.3'!U16)*12) -> 0 | AH14: =12-((X14/'Table 1.3'!V16)*12) -> 0 | AI14: =12-((Y14/'Table 1.3'!W16)*12) -> 0
A15: ='Table 1.0'!A16 -> Building A Ste 2 (VACANT) | B15: ='Table 1.0'!C16 -> 12000 | C15: 5 | D15: =AA15 -> 12 | E15: =AB15 -> 9.0660147 | J15: =AG15 -> 2.0899256 | O15: Bldg A Suite 2 | P15: Mo 12 | Q15: 0 | R15: 19800 | S15: 79794 | T15: 82188 | U15: 84653 | V15: 87193 | W15: 74736 | X15: 94805 | Y15: 97650 | Z15: 100579 | AA15: =12-((Q15/'Table 1.3'!O17)*12) -> 12 | AB15: =12-((R15/'Table 1.3'!P17)*12) -> 9.0660147 | AC15: =12-((S15/'Table 1.3'!Q17)*12) -> 0 | AD15: =12-((T15/'Table 1.3'!R17)*12) -> 0 | AE15: =12-((U15/'Table 1.3'!S17)*12) -> 0 | AF15: =12-((V15/'Table 1.3'!T17)*12) -> 0 | AG15: =12-((W15/'Table 1.3'!U17)*12) -> 2.0899256 | AH15: =12-((X15/'Table 1.3'!V17)*12) -> 0 | AI15: =12-((Y15/'Table 1.3'!W17)*12) -> 0
A16: ='Table 1.0'!A17 -> Building A Ste 3 (VACANT) | B16: ='Table 1.0'!C17 -> 11893 | C16: 5 | D16: =AA16 -> 12 | E16: =AB16 -> 12 | F16: =AC16 -> 2.1004654 | K16: =AH16 -> 2.0287266 | O16: Bldg A Suite 3 | P16: Mo 17 | Q16: 0 | R16: 0 | S16: 65412 | T16: 80456 | U16: 82870 | V16: 85356 | W16: 87917 | X16: 79083 | Y16: 98468 | Z16: 101422 | AA16: =12-((Q16/'Table 1.3'!O18)*12) -> 12 | AB16: =12-((R16/'Table 1.3'!P18)*12) -> 12 | AC16: =12-((S16/'Table 1.3'!Q18)*12) -> 2.1004654 | AD16: =12-((T16/'Table 1.3'!R18)*12) -> 0 | AE16: =12-((U16/'Table 1.3'!S18)*12) -> 0 | AF16: =12-((V16/'Table 1.3'!T18)*12) -> 0 | AG16: =12-((W16/'Table 1.3'!U18)*12) -> 0 | AH16: =12-((X16/'Table 1.3'!V18)*12) -> 2.0287266 | AI16: =12-((Y16/'Table 1.3'!W18)*12) -> 0
B17: =SUM(B7:B16) -> 129097
A20: First Term Lease Expirations | D20: 24000 | E20: 0 | F20: 19204 | G20: 35000 | H20: 0 | I20: 19500 | J20: 19500 | K20: 11893 | L20: 0
A21: Lease Expirations after First Term | D21: 0 | E21: =E22-E20 -> 0 | F21: 0 | G21: 0 | H21: =H22-H20 -> 0 | I21: 24000 | J21: 0 | K21: 0 | L21: 54204
A22: Total | D22: =D20+D21 -> 24000 | E22: 0 | F22: =F20+F21 -> 19204 | G22: =G20+G21 -> 35000 | H22: 0 | I22: =I20+I21 -> 43500 | J22: =J20+J21 -> 19500 | K22: =K20+K21 -> 11893 | L22: 54204
A23: % of Building | D23: =D22/$B$17 -> 0.18590672 | E23: =E22/$B$17 -> 0 | F23: =F22/$B$17 -> 0.14875636 | G23: =G22/$B$17 -> 0.27111397 | H23: =H22/$B$17 -> 0 | I23: =I22/$B$17 -> 0.33695593 | J23: =J22/$B$17 -> 0.15104921 | K23: =K22/$B$17 -> 0.092124527 | L23: =L22/$B$17 -> 0.41987033
A25: (1) Months vacant calculation for vacant space shows the blended downtime (1 month) between leases.
A26: The 1 month blended downtime between leases is based on a 25% probability that a tenant vacates and it takes 6 months to find a new tenant.

Sheet Table 1.3
A1: TABLE 1.3 -TUCSON AIRPORT CENTER - BASE RENT REVENUES
D3: Fiscal Year Ending | E3: ='Table 1.1'!D6 -> 38869 | F3: ='Table 1.1'!E6 -> 39234 | G3: ='Table 1.1'!F6 -> 39600 | H3: ='Table 1.1'!G6 -> 39965 | I3: ='Table 1.1'!H6 -> 40330 | J3: ='Table 1.1'!I6 -> 40695 | K3: ='Table 1.1'!J6 -> 41061 | L3: ='Table 1.1'!K6 -> 41426 | M3: ='Table 1.1'!L6 -> 41791
E4: Yr 1 | F4: Yr 2 | G4: Yr 3 | H4: Yr 4 | I4: Yr 5 | J4: Yr 6 | K4: Yr 7 | L4: Yr 8 | M4: Yr 9
D6: OCCUPANCY BEFORE VACANCY LOSS: | E6: =E22/(E20) -> #REF! | F6: =F22/(F20) -> #REF! | G6: =G22/(G20) -> #REF! | H6: =H22/(H20) -> #REF! | I6: =I22/(I20) -> #REF! | J6: =J22/(J20) -> #REF! | K6: =K22/(K20) -> #REF! | L6: =L22/(L20) -> #REF! | M6: =M22/(M20) -> #REF!
D7: OCCUPANCY AFTER VACANCY LOSS: | E7: =IF(E6<0.92,E6,0.92) -> #REF! | F7: =IF(F6<0.92,F6,0.92) -> #REF! | G7: =IF(G6<0.9,G6,0.9) -> #REF! | H7: =IF(H6<0.9,H6,0.9) -> #REF! | I7: =IF(I6<0.9,I6,0.9) -> #REF! | J7: =IF(J6<0.9,J6,0.9) -> #REF! | K7: =IF(K6<0.9,K6,0.9) -> #REF! | L7: =IF(L6<0.9,L6,0.9) -> #REF! | M7: =IF(M6<0.9,M6,0.9) -> #REF!
C8: Suite | D8: SF
A9: ='Table 1.0'!A8 -> Qantas Airways | C9: ='Table 1.0'!B8 -> 1 | D9: ='Table 1.0'!C8 -> 19204 | E9: =O9 -> 203370 | F9: =P9 -> 210092 | G9: =Q9 -> 214317 | H9: =R9 -> 138499 | I9: =S9 -> 141962 | J9: =T9 -> 146221 | K9: =U9 -> 150607 | L9: =V9 -> 155125 | M9: =W9 -> 159779 | O9: 203370 | P9: 210092 | Q9: 214317 | R9: 138499 | S9: 141962 | T9: 146221 | U9: 150607 | V9: 155125 | W9: 159779 | X9: 163770
A10: ='Table 1.0'!A9 -> Davis Select | C10: ='Table 1.0'!B9 -> 2 | D10: ='Table 1.0'!C9 -> 12512 | E10: =O10 -> 69692 | F10: =P10 -> 71193 | G10: =Q10 -> 73320 | H10: =R10 -> 86445 | I10: =S10 -> 91816 | J10: =T10 -> 94570 | K10: =U10 -> 97407 | L10: =V10 -> 100329 | M10: =W10 -> 103340 | O10: 69692 | P10: 71193 | Q10: 73320 | R10: 86445 | S10: 91816 | T10: 94570 | U10: 97407 | V10: 100329 | W10: 103340 | X10: 105916
A11: ='Table 1.0'!A10 -> Davis Select (Expansion Space) | C11: ='Table 1.0'!B10 -> 2a | D11: ='Table 1.0'!C10 -> 7488 | E11: =O11 -> 41708 | F11: =P11 -> 42607 | G11: =Q11 -> 43880 | H11: =R11 -> 51735 | I11: =S11 -> 54949 | J11: =T11 -> 56597 | K11: =U11 -> 58295 | L11: =V11 -> 60044 | M11: =W11 -> 61845 | O11: 41708 | P11: 42607 | Q11: 43880 | R11: 51735 | S11: 54949 | T11: 56597 | U11: 58295 | V11: 60044 | W11: 61845 | X11: 63387
A12: ='Table 1.0'!A11 -> APEX | C12: ='Table 1.0'!B11 -> 0 | D12: ='Table 1.0'!C11 -> 15000 | E12: =O12 -> 95400 | F12: =P12 -> 99000 | G12: =Q12 -> 100800 | H12: =R12 -> 107565 | I12: =S12 -> 110614 | J12: =T12 -> 113932 | K12: =U12 -> 117350 | L12: =V12 -> 120871 | M12: =W12 -> 124497 | O12: 95400 | P12: 99000 | Q12: 100800 | R12: 107565 | S12: 110614 | T12: 113932 | U12: 117350 | V12: 120871 | W12: 124497 | X12: 127605
A13: ='Table 1.0'!A12 -> Iron Mountain Temp. Space | C13: ='Table 1.0'!B12 -> 2B | D13: ='Table 1.0'!C12 -> 24000 | E13: =O13 -> 115200 | F13: =P13 -> 118656 | G13: =Q13 -> 122216 | H13: =R13 -> 125882 | I13: =S13 -> 129659 | J13: =T13 -> 133548 | K13: =U13 -> 137555 | L13: =V13 -> 140994 | M13: =W13 -> 145224 | O13: 115200 | P13: 118656 | Q13: 122216 | R13: 125882 | S13: 129659 | T13: 133548 | U13: 137555 | V13: 140994 | W13: 145224 | X13: 149580
A14: ='Table 1.0'!A13 -> Building C Ste 1 (VACANT) | C14: ='Table 1.0'!B13 -> C1 | D14: ='Table 1.0'!C13 -> 7500 | E14: =O14 -> 49500 | F14: =P14 -> 49624 | G14: =Q14 -> 51112 | H14: =R14 -> 52646 | I14: =S14 -> 54225 | J14: =T14 -> 55852 | K14: =U14 -> 59105 | L14: =V14 -> 60731 | M14: =W14 -> 62553 | O14: 49500 | P14: 49624 | Q14: 51112 | R14: 52646 | S14: 54225 | T14: 55852 | U14: 59105 | V14: 60731 | W14: 62553 | X14: 64430
A15: ='Table 1.0'!A14 -> Building C Ste 2 (VACANT) | C15: ='Table 1.0'!B14 -> C2 | D15: ='Table 1.0'!C14 -> 7500 | E15: =O15 -> 49500 | F15: =P15 -> 50119 | G15: =Q15 -> 50366 | H15: =R15 -> 51877 | I15: =S15 -> 53434 | J15: =T15 -> 55037 | K15: =U15 -> 57692 | L15: =V15 -> 59844 | M15: =W15 -> 61640 | O15: 49500 | P15: 50119 | Q15: 50366 | R15: 51877 | S15: 53434 | T15: 55037 | U15: 57692 | V15: 59844 | W15: 61640 | X15: 63489
A16: ='Table 1.0'!A15 -> Building A Ste 1 (VACANT) | C16: ='Table 1.0'!B15 -> A1 | D16: ='Table 1.0'!C15 -> 12000 | E16: =O16 -> 64800 | F16: =P16 -> 65772 | G16: =Q16 -> 67745 | H16: =R16 -> 69778 | I16: =S16 -> 71871 | J16: =T16 -> 74027 | K16: =U16 -> 75872 | L16: =V16 -> 78148 | M16: =W16 -> 80493 | O16: 64800 | P16: 65772 | Q16: 67745 | R16: 69778 | S16: 71871 | T16: 74027 | U16: 75872 | V16: 78148 | W16: 80493 | X16: 82908
A17: ='Table 1.0'!A16 -> Building A Ste 2 (VACANT) | C17: ='Table 1.0'!B16 -> A2 | D17: ='Table 1.0'!C16 -> 12000 | E17: =O17 -> 79200 | F17: =P17 -> 80982 | G17: =Q17 -> 79794 | H17: =R17 -> 82188 | I17: =S17 -> 84653 | J17: =T17 -> 87193 | K17: =U17 -> 90497 | L17: =V17 -> 94805 | M17: =W17 -> 97650 | O17: 79200 | P17: 80982 | Q17: 79794 | R17: 82188 | S17: 84653 | T17: 87193 | U17: 90497 | V17: 94805 | W17: 97650 | X17: 100579
A18: ='Table 1.0'!A17 -> Building A Ste 3 (VACANT) | C18: ='Table 1.0'!B17 -> A3 | D18: ='Table 1.0'!C17 -> 11893 | E18: =O18 -> 78494 | F18: =P18 -> 80849 | G18: =Q18 -> 79291 | H18: =R18 -> 80456 | I18: =S18 -> 82870 | J18: =T18 -> 85356 | K18: =U18 -> 87917 | L18: =V18 -> 95173 | M18: =W18 -> 98468 | O18: 78494 | P18: 80849 | Q18: 79291 | R18: 80456 | S18: 82870 | T18: 85356 | U18: 87917 | V18: 95173 | W18: 98468 | X18: 101422
D19: =SUM(D9:D18) -> 129097
D20: POTENTIAL RENTAL INCOME: | E20: =SUM(E9:E18) -> 846864 | F20: =SUM(F9:F18) -> 868894 | G20: =SUM(G9:G18) -> 882841 | H20: =SUM(H9:H18) -> 847071 | I20: =SUM(I9:I18) -> 876053 | J20: =SUM(J9:J18) -> 902333 | K20: =SUM(K9:K18) -> 932297 | L20: =SUM(L9:L18) -> 966064 | M20: =SUM(M9:M18) -> 995489
D21: ABSORPTION & TURNOVER VACANCY1: | E21: =E22-E20 -> #REF! | F21: =F22-F20 -> #REF! | G21: =G22-G20 -> #REF! | H21: =H22-H20 -> #REF! | I21: =I22-I20 -> #REF! | J21: =J22-J20 -> #REF! | K21: =K22-K20 -> #REF! | L21: =L22-L20 -> #REF! | M21: =M22-M20 -> #REF!
D22: RENTAL INCOME BEFORE VACANCY LOSS: | E22: =#REF! -> #REF! | F22: =#REF! -> #REF! | G22: =#REF! -> #REF! | H22: =#REF! -> #REF! | I22: =#REF! -> #REF! | J22: =#REF! -> #REF! | K22: =#REF! -> #REF! | L22: =#REF! -> #REF! | M22: =#REF! -> #REF!
A25: 1Absorption & Turnover Vacancy: The amount of revenue lost during the initial lease up of vacant space and downtime between leases.

Sheet Table 1.4
A1: TABLE 1.4 - TUCSON AIRPORT CENTER - LEASE COMMISSIONS
C3: Fiscal Year Ending | D3: ='Table 1.3'!E3 -> 38869 | E3: ='Table 1.3'!F3 -> 39234 | F3: ='Table 1.3'!G3 -> 39600 | G3: ='Table 1.3'!H3 -> 39965 | H3: ='Table 1.3'!I3 -> 40330 | I3: ='Table 1.3'!J3 -> 40695 | J3: ='Table 1.3'!K3 -> 41061 | K3: ='Table 1.3'!L3 -> 41426 | L3: ='Table 1.3'!M3 -> 41791
D4: Yr 1 | E4: Yr 2 | F4: Yr 3 | G4: Yr 4 | H4: Yr 5 | I4: Yr 6 | J4: Yr 7 | K4: Yr 8 | L4: Yr 9
B6: Suite | C6: SF
A7: ='Table 1.0'!A8 -> Qantas Airways | B7: ='Table 1.0'!B8 -> 1 | C7: ='Table 1.0'!C8 -> 19204 | G7: 27574 | L7: 31966
A8: ='Table 1.0'!A9 -> Davis Select | B8: ='Table 1.0'!B9 -> 2 | C8: ='Table 1.0'!C9 -> 12512 | G8: 17965 | L8: 20827
A9: ='Table 1.0'!A10 -> Davis Select (Expansion Space) | B9: ='Table 1.0'!B10 -> 2a | C9: ='Table 1.0'!C10 -> 7488 | G9: 10752 | L9: 12464
A10: ='Table 1.0'!A11 -> APEX | B10: ='Table 1.0'!B11 -> 0 | C10: ='Table 1.0'!C11 -> 15000 | G10: 21538 | L10: 24968
A11: ='Table 1.0'!A12 -> Iron Mountain Temp. Space | B11: ='Table 1.0'!B12 -> 2B | C11: ='Table 1.0'!C12 -> 24000 | E11: 37798 | J11: 27386
A12: ='Table 1.0'!A13 -> Building C Ste 1 (VACANT) | B12: ='Table 1.0'!B13 -> C1 | C12: ='Table 1.0'!C13 -> 7500 | D12: 15768 | J12: 11767
A13: ='Table 1.0'!A14 -> Building C Ste 2 (VACANT) | B13: ='Table 1.0'!B14 -> C2 | C13: ='Table 1.0'!C14 -> 7500 | E13: 15768 | J13: 11767
A14: ='Table 1.0'!A15 -> Building A Ste 1 (VACANT) | B14: ='Table 1.0'!B15 -> A1 | C14: ='Table 1.0'!C15 -> 12000 | D14: 20642 | I14: 14956
A15: ='Table 1.0'!A16 -> Building A Ste 2 (VACANT) | B15: ='Table 1.0'!B16 -> A2 | C15: ='Table 1.0'!C16 -> 12000 | E15: 25229 | J15: 18828
A16: ='Table 1.0'!A17 -> Building A Ste 3 (VACANT) | B16: ='Table 1.0'!B17 -> A3 | C16: ='Table 1.0'!C17 -> 11893 | F16: 25004 | K16: 19220
A17: TOTAL | C17: =SUM(C7:C16) -> 129097
A19: New Lease Commission % | D19: 0.06 | E19: =D19 -> 0.06 | F19: =E19 -> 0.06 | G19: =F19 -> 0.06 | H19: =G19 -> 0.06 | I19: =H19 -> 0.06 | J19: =I19 -> 0.06 | K19: =J19 -> 0.06 | L19: =K19 -> 0.06
A20: Renewal Commission % | D20: 0.03 | E20: =D20 -> 0.03 | F20: =E20 -> 0.03 | G20: =F20 -> 0.03 | H20: =G20 -> 0.03 | I20: =H20 -> 0.03 | J20: =I20 -> 0.03 | K20: =J20 -> 0.03 | L20: =K20 -> 0.03
A21: TOTAL LEASE COMMISSIONS | D21: =SUM(D7:D16) -> 36410 | E21: =SUM(E7:E16) -> 78795 | F21: =SUM(F7:F16) -> 25004 | G21: =SUM(G7:G16) -> 77829 | H21: =SUM(H7:H16) -> 0 | I21: =SUM(I7:I16) -> 14956 | J21: =SUM(J7:J16) -> 69748 | K21: =SUM(K7:K16) -> 19220 | L21: =SUM(L7:L16) -> 90225
C23: 7

Sheet Table 1.5
A1: TABLE 1.5 - TUCSON AIRPORT CENTER - TENANT IMPROVEMENTS (A)
C3: Fiscal Year Ending | D3: 38869 | E3: 39234 | F3: 39600 | G3: 39965 | H3: 40330 | I3: 40695 | J3: 41061 | K3: 41426 | L3: 41791
A4: Total Amount | D4: Yr 1 | E4: Yr 2 | F4: Yr 3 | G4: Yr 4 | H4: Yr 5 | I4: Yr 6 | J4: Yr 7 | K4: Yr 8 | L4: Yr 9
B6: Suite | C6: SF
A7: Qantas Airways | B7: 1 | C7: 19204 | D7: =P7 | E7: =Q7 | F7: =R7 | G7: =S7 -> 94431 | H7: =T7 | I7: =U7 | J7: =V7 | K7: =W7 | L7: =X7 -> 109472 | N7: Qantas Airways | O7: 2801 | S7: 94431 | X7: 109472
A8: Davis Select | B8: 2 | C8: 12512 | D8: =P8 | E8: =Q8 | F8: =R8 | G8: =S8 -> 61525 | H8: =T8 | I8: =U8 | J8: =V8 | K8: =W8 | L8: =X8 -> 71324 | N8: Davis Select | O8: 2949A | S8: 61525 | X8: 71324
A9: Davis Select (Expansion Space) | B9: 2a | C9: 7488 | D9: =P9 | E9: =Q9 | F9: =R9 | G9: =S9 -> 36821 | H9: =T9 | I9: =U9 | J9: =V9 | K9: =W9 | L9: =X9 -> 42685 | N9: Davis Expansion Space | O9: 2949 A | S9: 36821 | X9: 42685
A10: APEX | B10: 0 | C10: 15000 | D10: =P10 | E10: =Q10 | F10: =R10 | G10: =S10 -> 73759 | H10: =T10 | I10: =U10 | J10: =V10 | K10: =W10 | L10: =X10 -> 85507 | N10: APEX | O10: 15000 | S10: 73759 | X10: 85507
A11: Iron Mountain Temp. Space (B) | B11: 2B | C11: 24000 | D11: =P11 | E11: =Q11 -> 98880 | F11: =R11 | G11: =S11 | H11: =T11 | I11: =U11 | J11: =V11 -> 28657 | K11: =W11 | L11: =X11 | N11: Iron Mountain | O11: Bldg E | Q11: 98880 | V11: 28657
A12: Building C Ste 1 (VACANT) | B12: C1 | C12: 7500 | D12: =P12 -> 90000 | E12: =Q12 | F12: =R12 | G12: =S12 | H12: =T12 | I12: =U12 | J12: =V12 -> 40299 | K12: =W12 | L12: =X12 | N12: Building C- Suite 1 | O12: Mo 12 | P12: 90000 | V12: 40299
A13: Building C Ste 2 (VACANT) | B13: C2 | C13: 7500 | D13: =P13 | E13: =Q13 -> 92700 | F13: =R13 | G13: =S13 | H13: =T13 | I13: =U13 | J13: =V13 -> 40299 | K13: =W13 | L13: =X13 | N13: Building C- Suite 2 | O13: Mo 18 | Q13: 92700 | V13: 40299
A14: Building A Ste 1 (VACANT) | B14: A1 | C14: 12000 | D14: =P14 -> 144000 | E14: =Q14 | F14: =R14 | G14: =S14 | H14: =T14 | I14: =U14 -> 62601 | J14: =V14 | K14: =W14 | L14: =X14 | N14: Bldg A Suite 1 | O14: Mo 7 | P14: 144000 | U14: 62601
A15: Building A Ste 2 (VACANT) | B15: A2 | C15: 12000 | D15: =P15 | E15: =Q15 -> 148320 | F15: =R15 | G15: =S15 | H15: =T15 | I15: =U15 | J15: =V15 -> 64479 | K15: =W15 | L15: =X15 | N15: Bldg A Suite 2 | O15: Mo 22 | Q15: 148320 | V15: 64479
A16: Building A Ste 3 (VACANT) | B16: A3 | C16: 11893 | D16: =P16 | E16: =Q16 | F16: =R16 -> 151407 | G16: =S16 | H16: =T16 | I16: =U16 | J16: =V16 | K16: =W16 -> 65821 | L16: =X16 | N16: Bldg A Suite 3 | O16: Mo 27 | R16: 151407 | W16: 65821
C17: =SUM(C7:C16) -> 129097 | P17: __________ | Q17: __________ | R17: __________ | S17: __________ | T17: __________ | U17: __________ | V17: __________ | W17: __________ | X17: __________ | Y17: __________
A18: TOTAL TI'S | D18: =SUM(D7:D16) -> 234000 | E18: =SUM(E7:E16) -> 339900 | F18: =SUM(F7:F16) -> 151407 | G18: =SUM(G7:G16) -> 266536 | H18: =SUM(H7:H16) -> 0 | I18: =SUM(I7:I16) -> 62601 | J18: =SUM(J7:J16) -> 173734 | K18: =SUM(K7:K16) -> 65821 | L18: =SUM(L7:L16) -> 308988
C19: New Tenant TI: | D19: 12 | E19: =D19*1.03 -> 12.36 | F19: =E19*1.03 -> 12.7308 | G19: =F19*1.03 -> 13.112724 | H19: =G19*1.03 -> 13.506106 | I19: =H19*1.03 -> 13.911289 | J19: =I19*1.03 -> 14.328628 | K19: =J19*1.03 -> 14.758486 | L19: =K19*1.03 -> 15.201241
C20: Renewal Tenant TI: | D20: 2 | E20: =D20*1.03 -> 2.06 | F20: =E20*1.03 -> 2.1218 | G20: =F20*1.03 -> 2.185454 | H20: =G20*1.03 -> 2.2510176 | I20: =H20*1.03 -> 2.3185481 | J20: =I20*1.03 -> 2.3881046 | K20: =J20*1.03 -> 2.4597477 | L20: =K20*1.03 -> 2.5335402
C21: Fiscal Year Ending | D21: =D3 -> 38869 | E21: =E3 -> 39234 | F21: =F3 -> 39600 | G21: =G3 -> 39965 | H21: =H3 -> 40330 | I21: =I3 -> 40695 | J21: =J3 -> 41061 | K21: =K3 -> 41426 | L21: =L3 -> 41791
A22: $/SF Amount | D22: Yr 1 | E22: Yr 2 | F22: Yr 3 | G22: Yr 4 | H22: Yr 5 | I22: Yr 6 | J22: Yr 7 | K22: Yr 8 | L22: Yr 9
B23: Suite | C23: SF
A24: =A7 -> Qantas Airways | B24: =B7 -> 1 | C24: =C7 -> 19204 | G24: =G7/$C24 -> 4.9172568 | L24: =L7/$C24 -> 5.7004791
A25: =A8 -> Davis Select | B25: =B8 -> 2 | C25: =C8 -> 12512 | G25: =G8/$C25 -> 4.9172794 | L25: =L8/$C25 -> 5.7004476
A26: =A9 -> Davis Select (Expansion Space) | B26: =B9 -> 2a | C26: =C9 -> 7488 | G26: =G9/$C26 -> 4.9173344 | L26: =L9/$C26 -> 5.7004541
A27: =A10 -> APEX | B27: =B10 -> 0 | C27: =C10 -> 15000 | G27: =G10/$C27 -> 4.9172667 | L27: =L10/$C27 -> 5.7004667
A28: =A11 -> Iron Mountain Temp. Space (B) | B28: =B11 -> 2B | C28: =C11 -> 24000 | E28: =E11/$C28 -> 4.12 | J28: =J11/$C28 -> 1.1940417
A29: =A12 -> Building C Ste 1 (VACANT) | B29: =B12 -> C1 | C29: =C12 -> 7500 | D29: =D12/$C29 -> 12 | J29: =J12/$C29 -> 5.3732
A30: =A13 -> Building C Ste 2 (VACANT) | B30: =B13 -> C2 | C30: =C13 -> 7500 | E30: =E13/$C30 -> 12.36 | J30: =J13/$C30 -> 5.3732
A31: =A14 -> Building A Ste 1 (VACANT) | B31: =B14 -> A1 | C31: =C14 -> 12000 | D31: =D14/$C31 -> 12 | I31: =I14/$C31 -> 5.21675
A32: =A15 -> Building A Ste 2 (VACANT) | B32: =B15 -> A2 | C32: =C15 -> 12000 | E32: =E15/$C32 -> 12.36 | J32: =J15/$C32 -> 5.37325
A33: =A16 -> Building A Ste 3 (VACANT) | B33: =B16 -> A3 | C33: =C16 -> 11893 | F33: =F16/$C33 -> 12.730766 | K33: =K16/$C33 -> 5.534432
C34: =SUM(C24:C33) -> 129097
A35: Total SF Expiring/ New Leases | D35: =C12+C14 -> 19500 | E35: =C11+C13+C15 -> 43500 | F35: =C16 -> 11893 | G35: =C7+C8+C9+C10 -> 54204 | H35: =0 -> 0 | I35: =C14 -> 12000 | J35: =C15+C13+C12+C11 -> 51000 | K35: =C16 -> 11893 | L35: =C7+C8+C9+C10 -> 54204
A36: TOTAL TI'S ($/SF Expiring-New Leases) | D36: =IF(D35=0,0,D18/D35) -> 12 | E36: =IF(E35=0,0,E18/E35) -> 7.8137931 | F36: =IF(F35=0,0,F18/F35) -> 12.730766 | G36: =IF(G35=0,0,G18/G35) -> 4.9172755 | H36: =IF(H35=0,0,H18/H35) -> 0 | I36: =IF(I35=0,0,I18/I35) -> 5.21675 | J36: =IF(J35=0,0,J18/J35) -> 3.406549 | K36: =IF(K35=0,0,K18/K35) -> 5.534432 | L36: =IF(L35=0,0,L18/L35) -> 5.7004649
A37: (A)- Tenant Improvement amounts calculated based on a 75% probability that tenants will renew.
A38: (B)- Assumes New Tenant Improvement allowance of $4.00/sq.ft. and Renewal Tenant Allowance of $2.00/sq.ft. as the space is 100% warehouse.

Sheet Table 2
A1: =+'Table 1A'!D1 -> TUCSON AIRPORT CENTER
A2: TABLE 2.0 : HISTORICAL EXPENSE & 1ST YEAR PROJECTION
A4: Net Rentable: | B4: 129097
A5: Leased Square Footage: | B5: 54204
A6: % Occupied as of March 1, 2005: | B6: =B5/B4 -> 0.41987033
B7: 2002 | C7: $/SF | D7: 2003 | E7: $/SF | F7: 2004 | G7: $/SF | H7: Year 1 | I7: $/SF
B8: Actual | D8: Actual | F8: Actual | H8: Estimated
A9: 12-Month Average Occupancy
A10: Base Rent | B10: 488318.57 | C10: =B10/$B$4 -> 3.782571 | D10: 466546.99 | E10: =D10/$B$4 -> 3.6139259 | F10: 381265 | G10: =F10/$B$4 -> 2.9533219 | H10: 538926 | I10: =H10/$B$4 -> 4.1745819
A11: Cam Reimbursement | B11: 52865.28 | C11: =B11/$B$4 -> 0.40950045 | D11: 44348.69 | E11: =D11/$B$4 -> 0.34352998 | F11: 29564 | G11: =F11/$B$4 -> 0.2290061 | H11: 75478 | I11: =H11/$B$4 -> 0.58466115
A12: Insurance Reimbursement | B12: 2591.04 | C12: =B12/$B$4 -> 0.02007049 | D12: 2080.7 | E12: =D12/$B$4 -> 0.016117338 | F12: 822 | G12: =F12/$B$4 -> 0.0063673052 | H12: 11472 | I12: =H12/$B$4 -> 0.088863413
A13: RE Taxes Reimbursed | B13: 63202.08 | C13: =B13/$B$4 -> 0.48957048 | D13: 51029.98 | E13: =D13/$B$4 -> 0.39528401 | F13: 30199 | G13: =F13/$B$4 -> 0.23392488 | H13: 64245 | I13: =H13/$B$4 -> 0.49764905
A14: Maintenance Tenant | B14: 5347.36 | C14: =B14/$B$4 -> 0.041421257 | D14: 4623.11 | E14: =D14/$B$4 -> 0.035811134 | F14: 4500 | G14: =F14/$B$4 -> 0.03485751 | H14: 0 | I14: =H14/$B$4 -> 0
A15: Other Income Tenant | B15: 8224.62 | C15: =B15/$B$4 -> 0.063708839 | D15: 0 | E15: =D15/$B$4 -> 0 | F15: 74175 | G15: =F15/$B$4 -> 0.57456796 | H15: 0 | I15: =H15/$B$4 -> 0
A16: Interest Income Other | B16: 15.49 | C16: =B16/$B$4 -> 0.0001199873 | D16: 0 | E16: =D16/$B$4 -> 0 | F16: 11375.68 | G16: =F16/$B$4 -> 0.088117307 | H16: 0 | I16: =H16/$B$4 -> 0
A17: Dividends | B17: 50 | C17: =B17/$B$4 -> 0.00038730567 | D17: 63.33 | E17: =D17/$B$4 -> 0.00049056136 | F17: 32.01 | G17: =F17/$B$4 -> 0.00024795309 | H17: 0 | I17: =H17/$B$4 -> 0
A18: GROSS INCOME | B18: =SUM(B10:B17) -> 620614.44 | C18: =B18/$B$4 -> 4.8073498 | D18: =SUM(D10:D17) -> 568692.8 | E18: =D18/$B$4 -> 4.4051589 | F18: =SUM(F10:F17) -> 531932.69 | G18: =F18/$B$4 -> 4.1204109 | H18: =SUM(H10:H17) -> 690121 | I18: =H18/$B$4 -> 5.3457555
A20: Operating Expenses
A21: Property Management | B21: 35679.7 | C21: =B21/$B$4 -> 0.276379 | D21: 39392.69 | E21: =D21/$B$4 -> 0.30514024 | F21: 31876.43 | G21: =F21/$B$4 -> 0.24691844 | H21: 23853 | I21: =H21/$B$4 -> 0.18476804
A22: RE Taxes | B22: 136597.95 | C22: =B22/$B$4 -> 1.0581032 | D22: =66884.09 -> 66884.09 | E22: =D22/$B$4 -> 0.51809174 | F22: 191101.73 | G22: =F22/$B$4 -> 1.4802957 | H22: 140000 | I22: =H22/$B$4 -> 1.0844559
A23: Insurance | B23: 14827.5 | C23: =B23/$B$4 -> 0.1148555 | D23: 5404.99 | E23: =D23/$B$4 -> 0.041867665 | F23: 12541.7 | G23: =F23/$B$4 -> 0.09714943 | H23: 25000 | I23: =H23/$B$4 -> 0.19365283
A24: Utilities | B24: 37981.75 | C24: =B24/$B$4 -> 0.29421094 | D24: 34202.97 | E24: =D24/$B$4 -> 0.26494008 | F24: 27327.58 | G24: =F24/$B$4 -> 0.21168253 | H24: 40000 | I24: =H24/$B$4 -> 0.30984454
A25: HVAC | B25: 120 | C25: =B25/$B$4 -> 0.00092953361 | D25: 5888.33 | E25: =D25/$B$4 -> 0.045611672 | F25: 2487.33 | G25: =F25/$B$4 -> 0.01926714 | H25: 25000 | I25: =H25/$B$4 -> 0.19365283
A26: Repairs & Maint. | B26: 740.55 | C26: =B26/$B$4 -> 0.0057363843 | D26: 40523.98 | E26: =D26/$B$4 -> 0.31390334 | F26: 3709.32 | G26: =F26/$B$4 -> 0.028732813 | H26: 46000 | I26: =H26/$B$4 -> 0.35632122
A27: Landscaping | B27: 19663 | C27: =B27/$B$4 -> 0.15231183 | D27: 11825.5 | E27: =D27/$B$4 -> 0.091601664 | F27: 12669 | G27: =F27/$B$4 -> 0.098135511 | H27: 15000 | I27: =H27/$B$4 -> 0.1161917
A28: Misc. Bldg | B28: 256.42 | C28: =B28/$B$4 -> 0.0019862584 | D28: 313.99 | E28: =D28/$B$4 -> 0.0024322021 | F28: 3382.84 | G28: =F28/$B$4 -> 0.026203862 | H28: 10000 | I28: =H28/$B$4 -> 0.077461134
A29: Misc. Other | B29: 439.13 | C29: =B29/$B$4 -> 0.0034015508 | D29: 343.52 | E29: =D29/$B$4 -> 0.0026609449 | F29: 400 | G29: =F29/$B$4 -> 0.0030984454 | H29: 0 | I29: =H29/$B$4 -> 0
A30: Office Exp | B30: 1370.9 | C30: =B30/$B$4 -> 0.010619147 | D30: 1228.93 | E30: =D30/$B$4 -> 0.0095194311 | F30: 3173 | G30: =F30/$B$4 -> 0.024578418 | H30: 0 | I30: =H30/$B$4 -> 0
A31: Total Operating Expenses | B31: =SUM(B21:B30) -> 247676.9 | C31: =B31/$B$4 -> 1.9185334 | D31: =SUM(D21:D30) -> 206008.99 | E31: =D31/$B$4 -> 1.595769 | F31: =SUM(F21:F30) -> 288668.93 | G31: =F31/$B$4 -> 2.2360623 | H31: =SUM(H21:H30) -> 324853 | I31: =H31/$B$4 -> 2.5163482
A32: Non-Reimbursable Expenses | H32: (A)
A33: Leasing | B33: 20098.75 | C33: =B33/$B$4 -> 0.1556872 | D33: 28378.03 | E33: =D33/$B$4 -> 0.21981944 | F33: 18816.2 | G33: =F33/$B$4 -> 0.14575242 | H33: 0 | I33: =H33/$B$4 -> 0
A34: Accounting | B34: 5821 | C34: =B34/$B$4 -> 0.045090126 | D34: 5513 | E34: =D34/$B$4 -> 0.042704323 | F34: 5306 | G34: =F34/$B$4 -> 0.041100878 | H34: 0 | I34: =H34/$B$4 -> 0
A35: Legal | B35: 504 | C35: =B35/$B$4 -> 0.0039040411 | D35: 1890.6 | E35: =D35/$B$4 -> 0.014644802 | F35: 4103.8 | G35: =F35/$B$4 -> 0.0317885 | H35: 0 | I35: =H35/$B$4 -> 0
A36: Professional Services | B36: 4381.34 | C36: =B36/$B$4 -> 0.033938356 | D36: 0 | E36: =D36/$B$4 -> 0 | F36: 19265.25 | G36: =F36/$B$4 -> 0.14923081 | H36: 0 | I36: =H36/$B$4 -> 0
A37: Total Non-Reimbursable Expenses | B37: =SUM(B33:B36) -> 30805.09 | C37: =B37/$B$4 -> 0.23861972 | D37: =SUM(D33:D36) -> 35781.63 | E37: =D37/$B$4 -> 0.27716856 | F37: =SUM(F33:F36) -> 47491.25 | G37: =F37/$B$4 -> 0.36787261 | H37: =SUM(H33:H36) -> 0 | I37: =H37/$B$4 -> 0
A38: NET OPERATING INCOME | B38: =B18-B31-B37 -> 342132.45 | C38: =B38/$B$4 -> 2.6501968 | D38: =D18-D31-D37 -> 326902.18 | E38: =D38/$B$4 -> 2.5322214 | F38: =F18-F31-F37 -> 195772.51 | G38: =F38/$B$4 -> 1.5164761 | H38: =H18-H31-H37 -> 365268 | I38: =H38/$B$4 -> 2.8294073
A40: (A)- We account for these expenses below the NOI line.

Sheet Table 3.0
C3: CAPITALIZATION | J3: PROJECT STATISTICS | O3: UNIT COSTS
C4: Property Purchases | J4: Land (sf) | K4: Land (Ac.) | L4: Amenity Center | M4: Square Footage | Q4: Total | R4: $ Unit | S4: $ per SF
E5: 1950 Hoffman | G5: ='Purchase Price'!O5 -> 1334287.3 | J5: 589933 | K5: =J5/43560 -> 13.542998 | L5: (y/n) | M5: =Clubhouse!C4 -> 2120 | O5: Land & Sunk Costs | Q5: =G5 -> 1334287.3 | R5: =Q5/K$7 -> 18531.768 | S5: =Q5/K$8 -> 20.590853
E6: Plus: | G6: 0 | L6: y | O6: Hard Costs - Buildings | Q6: 0 | R6: =Q6/K$7 -> 0 | S6: =Q6/K$8 -> 0
D7: Less: Acquisition Loan | G7: =-K22 -> -1175000 | H7: =-G7/SUM(G5:G6) -> 0.88061995 | J7: # Pads | K7: ='Rent Roll'!C3 -> 72 | O7: Hard Costs - Sitework | Q7: =Infrastructure!D34 -> 1368706 | R7: =Q7/K$7 -> 19009.806 | S7: =Q7/K$8 -> 21.122006
D8: Less: Seller Carryback | G8: =-K23 -> 0 | J8: Total sf: | K8: =K7*900 -> 64800 | L8: Golf Cart Usage | M8: Glamping Occup. | O8: Hard Costs - Amenities | Q8: ='Cost Curves'!F22 -> 631000 | R8: =Q8/K$7 -> 8763.8889 | S8: =Q8/K$8 -> 9.7376543
D9: Plus: Org. & Closing Costs | G9: ='Org. & Closing Costs'!G28 -> 17000 | J9: # Laundry Vending | K9: 2 | L9: 0.7 | M9: 0.5 | O9: Soft Costs | Q9: ='Cost Curves'!F35 -> 498000 | R9: =Q9/K$7 -> 6916.6667 | S9: =Q9/K$8 -> 7.6851852
D10: Plus: Loan Fees | G10: =(K22*Q22+R22)+(K24*Q24+R24) -> 37745 | J10: # Soda Vending | K10: 2 | O10: Contractor Fee | Q10: =S127 -> 120000 | R10: =Q10/K$7 -> 1666.6667 | S10: =Q10/K$8 -> 1.8518519
D11: Plus: Start-Up Mgmt. Fee (% of Purchase Price) | G11: 0 | O11: Contingency | P11: =G133 -> 0.075 | Q11: =S133 -> 204000 | R11: =Q11/K$7 -> 2833.3333 | S11: =Q11/K$8 -> 3.1481481
D12: Plus: Working Capital | G12: 1241134 | J12: CAPITAL CONSTRAINTS | O12: Sub-Total | Q12: =SUM(Q5:Q11) -> 4155993.3 | R12: =Q12/K$7 -> 57722.129 | S12: =Q12/K$8 -> 64.135699
D13: Plus: | J13: Cash Raised | K13: Cash Used | L13: Debt. Avail. | M13: Peak Debt
C14: Initial Equity Investment | G14: =SUM(G5:G13) -> 1455166.3 | J14: ='Members Capital'!I14 -> 1127750.1 | K14: =Worksheet!D23 -> 1127750.1 | L14: =K22+K24 -> 3675000 | M14: =Worksheet!D34 -> 3358369.6 | O14: FF&E | Q14: ='FF&E'!L49 -> 222000 | R14: =Q14/K7 -> 3083.3333 | S14: =Q14/$K$8 -> 3.4259259
D16: Less: Acq. Fee Reinvested | G16: =-G11 -> 0 | J16: ='Members Capital'!G8 -> 281774.22 | K16: + LOC Converted | O16: Financing Expenses | Q16: =SUM(S111:S113)+G10 -> 1282364.9 | R16: =Q16/$K$7 -> 17810.623 | S16: =Q16/$K$8 -> 19.789582
D17: Less: Initial Equity + Ph II Capital | G17: =-'Members Capital'!G7-'Members Capital'!G8-'Members Capital'!G16-'Members Capital'!G17-'Members Capital'!G18 -> -1428416.2 | J17: ='Members Capital'!G7 -> 45642 | K17: + Acq. Fee Converted | O17: Total | Q17: =SUM(Q12:Q16) -> 5660358.2 | R17: =Q17/$K$7 -> 78616.086 | S17: =Q17/$K$8 -> 87.351206
C18: Add'l. Acquisition Equity Required | G18: =SUM(G14:G17) -> 26750.06 | J18: =SUM(J14:J17) -> 1455166.3 | K18: Total Capital
D20: Add: New Capital ("Mezz") | G20: 0 | J20: PROJECT FINANCING
C21: Total Cash Raised from Investors | G21: =G18+G20 -> 26750.06 | K21: Loan Amount | L21: LTC (1) | M21: Int. Rate | N21: Loan Type | O21: Term - Yrs. | P21: Amort. - Mo's. | Q21: Pts. & Fees | R21: Legal Fees | S21: Mo. Initiated
C22: Total Equity & Mezz. | G22: =G14+G20 -> 1455166.3 | J22: Acq. & Const. | K22: 1175000 | L22: =K22/SUM(G5:G6) -> 0.88061995 | M22: 0.095 | N22: Int. Only | O22: 1 | P22: N/A | Q22: 0.01 | R22: 995
J23: Seller Carryback | K23: 0 | M23: 0 | N23: Int. Only | O23: 1 | P23: N/A | Q23: 0 | R23: See Org. Costs
C24: TOTAL CAPITAL COMMITMENTS | J24: Const. Loan | K24: 2500000 | M24: =M22 -> 0.095 | N24: Int. Only | O24: 1 | P24: N/A | Q24: =Q22 -> 0.01 | R24: 0 | S24: 36
G25: Investment | H25: Prorata Share | J25: Total | K25: =SUM(K22:K24) -> 3675000 | L25: =MAX(Balances!I37:AR37) -> 0.56761111
E26: Dabdoub Acquisitions | G26: ='Members Capital'!G17 -> 1000000 | H26: =G26/G31 -> 0.65443228
E27: Nexus Management | G27: ='Members Capital'!G8+'Members Capital'!G18 -> 357774.22 | H27: =G27/G31 -> 0.234139 | K27: Peak Loan Amt. | L27: DCR | M27: Interest Rate | N27: Loan Type | O27: Term (Years) | P27: Amort. Mo's | Q27: Pts. & Fees | R27: Legal Fees | S27: Notes
E28: Mark | G28: ='Members Capital'!H22 -> 99625.77 | H28: =G28/G31 -> 0.06519832 | J28: Perm. Loan | K28: ='Perm Loan'!BX12 -> 2230000 | L28: 1.25 | M28: 0.06 | N28: Amort. | O28: 30 | P28: 360 | Q28: 0.011 | R28: 5000 | S28: (2)
E29: Manager | G29: ='Members Capital'!G7 -> 45642 | H29: =G29/G31 -> 0.029869598 | J29: (1) LTC excludes financing costs
E30: Cort | G30: ='Members Capital'!G16 -> 25000 | H30: =G30/G31 -> 0.016360807 | J30: (2) Phased loan with issuance at end of years 2-8
G31: =SUM(G26:G30) -> 1528042 | H31: =SUM(H26:H30) -> 1
J33: Year 1 | K33: Year 2 | L33: Year 3 | M33: Year 4 | N33: Year 5 | O33: Year 6 | P33: Year 7 | Q33: Year 8 | R33: Year 9 | S33: Cumulative
C35: RV RENTAL INCOME
D36: Short-Term RV Rental Income | J36: =SUM(Monthly!K8:V8) -> 0 | K36: =SUM(Monthly!W8:AH8) -> 151200 | L36: =SUM(Monthly!AI8:AT8) -> 163800 | M36: =SUM(Monthly!AU8:BF8) -> 176400 | N36: =SUM(Monthly!BG8:BR8) -> 189000 | O36: =SUM(Monthly!BS8:CD8) -> 201600 | P36: =SUM(Monthly!CE8:CP8) -> 214200 | Q36: =SUM(Monthly!CQ8:DB8) -> 226800 | R36: =SUM(Monthly!DC8:DN8) -> 239400 | S36: =SUM(J36:R36) -> 1562400
D37: Long-Term RV Rental Income | J37: =SUM(Monthly!K9:V9) -> 0 | K37: =SUM(Monthly!W9:AH9) -> 322422 | L37: =SUM(Monthly!AI9:AT9) -> 331905 | M37: =SUM(Monthly!AU9:BF9) -> 341388 | N37: =SUM(Monthly!BG9:BR9) -> 350871 | O37: =SUM(Monthly!BS9:CD9) -> 360354 | P37: =SUM(Monthly!CE9:CP9) -> 369837 | Q37: =SUM(Monthly!CQ9:DB9) -> 379320 | R37: =SUM(Monthly!DC9:DN9) -> 388803 | S37: =SUM(J37:R37) -> 2844900
C38: SUB-TOTAL | J38: =SUM(J36:J37) -> 0 | K38: =SUM(K36:K37) -> 473622 | L38: =SUM(L36:L37) -> 495705 | M38: =SUM(M36:M37) -> 517788 | N38: =SUM(N36:N37) -> 539871 | O38: =SUM(O36:O37) -> 561954 | P38: =SUM(P36:P37) -> 584037 | Q38: =SUM(Q36:Q37) -> 606120 | R38: =SUM(R36:R37) -> 628203 | S38: =SUM(J38:R38) -> 4407300
C40: Golf Cart Rentals ($/day) (# carts) | G40: 75 | H40: 4 | J40: =SUM(Monthly!K12:V12) -> 0 | K40: =SUM(Monthly!W12:AH12) -> 76650 | L40: =SUM(Monthly!AI12:AT12) -> 76650 | M40: =SUM(Monthly!AU12:BF12) -> 76860 | N40: =SUM(Monthly!BG12:BR12) -> 76650 | O40: =SUM(Monthly!BS12:CD12) -> 76650 | P40: =SUM(Monthly!CE12:CP12) -> 76650 | Q40: =SUM(Monthly!CQ12:DB12) -> 76650 | R40: =SUM(Monthly!DC12:DN12) -> 76650 | S40: =SUM(I40:R40) -> 613410
C41: Glamping Rentals ($/night) (# spaces) | G41: 40 | H41: 10 | J41: =SUM(Monthly!K13:V13) -> 0 | K41: =SUM(Monthly!W13:AH13) -> 73000 | L41: =SUM(Monthly!AI13:AT13) -> 73000 | M41: =SUM(Monthly!AU13:BF13) -> 73200 | N41: =SUM(Monthly!BG13:BR13) -> 73000 | O41: =SUM(Monthly!BS13:CD13) -> 73000 | P41: =SUM(Monthly!CE13:CP13) -> 73000 | Q41: =SUM(Monthly!CQ13:DB13) -> 73000 | R41: =SUM(Monthly!DC13:DN13) -> 73000 | S41: =SUM(I41:R41) -> 584200
C42: SUB-TOTAL | J42: =J40+J41 -> 0 | K42: =K40+K41 -> 149650 | L42: =L40+L41 -> 149650 | M42: =M40+M41 -> 150060 | N42: =N40+N41 -> 149650 | O42: =O40+O41 -> 149650 | P42: =P40+P41 -> 149650 | Q42: =Q40+Q41 -> 149650 | R42: =R40+R41 -> 149650 | S42: =SUM(J42:R42) -> 1197610
C44: TOTAL RENTAL INCOME | J44: =J38+J42 -> 0 | K44: =K38+K42 -> 623272 | L44: =L38+L42 -> 645355 | M44: =M38+M42 -> 667848 | N44: =N38+N42 -> 689521 | O44: =O38+O42 -> 711604 | P44: =P38+P42 -> 733687 | Q44: =Q38+Q42 -> 755770 | R44: =R38+R42 -> 777853 | S44: =SUM(J44:R44) -> 5604910
C46: OTHER INCOME
D47: Laundry ($/unit/month) | G47: 20 | J47: =SUM(Monthly!K19:V19) -> 0 | K47: =SUM(Monthly!W19:AH19) -> 9396 | L47: =SUM(Monthly!AI19:AT19) -> 9396 | M47: =SUM(Monthly!AU19:BF19) -> 9396 | N47: =SUM(Monthly!BG19:BR19) -> 9396 | O47: =SUM(Monthly!BS19:CD19) -> 9396 | P47: =SUM(Monthly!CE19:CP19) -> 9396 | Q47: =SUM(Monthly!CQ19:DB19) -> 9396 | R47: =SUM(Monthly!DC19:DN19) -> 9396 | S47: =SUM(J47:R47) -> 75168
D48: Convenience Store Sales (gross revenue per day) | G48: 150 | J48: =SUM(Monthly!K20:V20) -> 0 | K48: =SUM(Monthly!W20:AH20) -> 54750 | L48: =SUM(Monthly!AI20:AT20) -> 54750 | M48: =SUM(Monthly!AU20:BF20) -> 54900 | N48: =SUM(Monthly!BG20:BR20) -> 54750 | O48: =SUM(Monthly!BS20:CD20) -> 54750 | P48: =SUM(Monthly!CE20:CP20) -> 54750 | Q48: =SUM(Monthly!CQ20:DB20) -> 54750 | R48: =SUM(Monthly!DC20:DN20) -> 54750 | S48: =SUM(J48:R48) -> 438150
D49: Laundry Vending ($/unit/month) | G49: 10 | J49: =SUM(Monthly!K21:V21) -> 0 | K49: =SUM(Monthly!W21:AH21) -> 4698 | L49: =SUM(Monthly!AI21:AT21) -> 4698 | M49: =SUM(Monthly!AU21:BF21) -> 4698 | N49: =SUM(Monthly!BG21:BR21) -> 4698 | O49: =SUM(Monthly!BS21:CD21) -> 4698 | P49: =SUM(Monthly!CE21:CP21) -> 4698 | Q49: =SUM(Monthly!CQ21:DB21) -> 4698 | R49: =SUM(Monthly!DC21:DN21) -> 4698 | S49: =SUM(J49:R49) -> 37584
D50: Candy/Soda Vending ($/machine/month) | G50: 250 | J50: =SUM(Monthly!K22:V22) -> 0 | K50: =SUM(Monthly!W22:AH22) -> 6000 | L50: =SUM(Monthly!AI22:AT22) -> 6000 | M50: =SUM(Monthly!AU22:BF22) -> 6000 | N50: =SUM(Monthly!BG22:BR22) -> 6000 | O50: =SUM(Monthly!BS22:CD22) -> 6000 | P50: =SUM(Monthly!CE22:CP22) -> 6000 | Q50: =SUM(Monthly!CQ22:DB22) -> 6000 | R50: =SUM(Monthly!DC22:DN22) -> 6000 | S50: =SUM(J50:R50) -> 48000
D51: Elec. Reimbursement (Reimb. per LT unit) | G51: 60 | J51: =SUM(Monthly!K23:V23) -> 0 | K51: =SUM(Monthly!W23:AH23) -> 28188 | L51: =SUM(Monthly!AI23:AT23) -> 28188 | M51: =SUM(Monthly!AU23:BF23) -> 28188 | N51: =SUM(Monthly!BG23:BR23) -> 28188 | O51: =SUM(Monthly!BS23:CD23) -> 28188 | P51: =SUM(Monthly!CE23:CP23) -> 28188 | Q51: =SUM(Monthly!CQ23:DB23) -> 28188 | R51: =SUM(Monthly!DC23:DN23) -> 28188 | S51: =SUM(J51:R51) -> 225504
C52: SUB-TOTAL | J52: =SUM(J47:J51) -> 0 | K52: =SUM(K47:K51) -> 103032 | L52: =SUM(L47:L51) -> 103032 | M52: =SUM(M47:M51) -> 103182 | N52: =SUM(N47:N51) -> 103032 | O52: =SUM(O47:O51) -> 103032 | P52: =SUM(P47:P51) -> 103032 | Q52: =SUM(Q47:Q51) -> 103032 | R52: =SUM(R47:R51) -> 103032 | S52: =SUM(J52:R52) -> 824406
C54: EFFECTIVE GROSS REVENUE | J54: =J44+J52 -> 0 | K54: =K44+K52 -> 726304 | L54: =L44+L52 -> 748387 | M54: =M44+M52 -> 771030 | N54: =N44+N52 -> 792553 | O54: =O44+O52 -> 814636 | P54: =P44+P52 -> 836719 | Q54: =Q44+Q52 -> 858802 | R54: =R44+R52 -> 880885 | S54: =SUM(I54:R54) -> 6429316
C56: DEPARTMENTAL EXPENSES
D57: Labor
E58: Salaries & Wages
F59: Community Manager | G59: 0.03 | H59: YoY Growth | J59: =SUM(Monthly!K31:V31) -> 0 | K59: =SUM(Monthly!W31:AH31) -> 65000 | L59: =SUM(Monthly!AI31:AT31) -> 66950 | M59: =SUM(Monthly!AU31:BF31) -> 68958.5 | N59: =SUM(Monthly!BG31:BR31) -> 71027.255 | O59: =SUM(Monthly!BS31:CD31) -> 73158.073 | P59: =SUM(Monthly!CE31:CP31) -> 75352.815 | Q59: =SUM(Monthly!CQ31:DB31) -> 77613.399 | R59: =SUM(Monthly!DC31:DN31) -> 79941.801 | S59: =SUM(J59:R59) -> 578001.84
F60: Maintenance | G60: =G59 -> 0.03 | H60: YoY Growth | J60: =SUM(Monthly!K32:V32) -> 0 | K60: =SUM(Monthly!W32:AH32) -> 60000 | L60: =SUM(Monthly!AI32:AT32) -> 61800 | M60: =SUM(Monthly!AU32:BF32) -> 63654 | N60: =SUM(Monthly!BG32:BR32) -> 65563.62 | O60: =SUM(Monthly!BS32:CD32) -> 67530.529 | P60: =SUM(Monthly!CE32:CP32) -> 69556.444 | Q60: =SUM(Monthly!CQ32:DB32) -> 71643.138 | R60: =SUM(Monthly!DC32:DN32) -> 73792.432 | S60: =SUM(J60:R60) -> 533540.16
F61: Clubhouse Staff | G61: =G60 -> 0.03 | H61: YoY Growth | J61: =SUM(Monthly!K33:V33) -> 0 | K61: =SUM(Monthly!W33:AH33) -> 60000 | L61: =SUM(Monthly!AI33:AT33) -> 61800 | M61: =SUM(Monthly!AU33:BF33) -> 63654 | N61: =SUM(Monthly!BG33:BR33) -> 65563.62 | O61: =SUM(Monthly!BS33:CD33) -> 67530.529 | P61: =SUM(Monthly!CE33:CP33) -> 69556.444 | Q61: =SUM(Monthly!CQ33:DB33) -> 71643.138 | R61: =SUM(Monthly!DC33:DN33) -> 73792.432 | S61: =SUM(J61:R61) -> 533540.16
E62: Payroll Taxes & Incentives
F63: Payroll Taxes | G63: 0.1 | H63: of Salaries and Wages | J63: =SUM(Monthly!K35:V35) -> 0 | K63: =SUM(Monthly!W35:AH35) -> 18500 | L63: =SUM(Monthly!AI35:AT35) -> 19055 | M63: =SUM(Monthly!AU35:BF35) -> 19626.65 | N63: =SUM(Monthly!BG35:BR35) -> 20215.45 | O63: =SUM(Monthly!BS35:CD35) -> 20821.913 | P63: =SUM(Monthly!CE35:CP35) -> 21446.57 | Q63: =SUM(Monthly!CQ35:DB35) -> 22089.967 | R63: =SUM(Monthly!DC35:DN35) -> 22752.667 | S63: =SUM(J63:R63) -> 164508.22
F64: Payroll Processing Fees | G64: 0.01 | H64: of Salaries and Wages | J64: =SUM(Monthly!K36:V36) -> 0 | K64: =SUM(Monthly!W36:AH36) -> 1850 | L64: =SUM(Monthly!AI36:AT36) -> 1905.5 | M64: =SUM(Monthly!AU36:BF36) -> 1962.665 | N64: =SUM(Monthly!BG36:BR36) -> 2021.5449 | O64: =SUM(Monthly!BS36:CD36) -> 2082.1913 | P64: =SUM(Monthly!CE36:CP36) -> 2144.657 | Q64: =SUM(Monthly!CQ36:DB36) -> 2208.9967 | R64: =SUM(Monthly!DC36:DN36) -> 2275.2667 | S64: =SUM(J64:R64) -> 16450.822
F65: Benefits | G65: 0.01 | H65: of Salaries and Wages | J65: =SUM(Monthly!K37:V37) -> 0 | K65: =SUM(Monthly!W37:AH37) -> 1850 | L65: =SUM(Monthly!AI37:AT37) -> 1905.5 | M65: =SUM(Monthly!AU37:BF37) -> 1962.665 | N65: =SUM(Monthly!BG37:BR37) -> 2021.5449 | O65: =SUM(Monthly!BS37:CD37) -> 2082.1913 | P65: =SUM(Monthly!CE37:CP37) -> 2144.657 | Q65: =SUM(Monthly!CQ37:DB37) -> 2208.9967 | R65: =SUM(Monthly!DC37:DN37) -> 2275.2667 | S65: =SUM(J65:R65) -> 16450.822
D66: Laundry Expenses
E67: Laundry Machine Related Exp. | G67: 0.03 | H67: YoY Growth | J67: =SUM(Monthly!K39:V39) -> 0 | K67: =SUM(Monthly!W39:AH39) -> 3000 | L67: =SUM(Monthly!AI39:AT39) -> 3090 | M67: =SUM(Monthly!AU39:BF39) -> 3182.7 | N67: =SUM(Monthly!BG39:BR39) -> 3278.181 | O67: =SUM(Monthly!BS39:CD39) -> 3376.5264 | P67: =SUM(Monthly!CE39:CP39) -> 3477.8222 | Q67: =SUM(Monthly!CQ39:DB39) -> 3582.1569 | R67: =SUM(Monthly!DC39:DN39) -> 3689.6216 | S67: =SUM(J67:R67) -> 26677.008
E68: Laundry Vending Machine Supplies | G68: 0.03 | H68: YoY Growth | J68: =SUM(Monthly!K40:V40) -> 0 | K68: =SUM(Monthly!W40:AH40) -> 42000 | L68: =SUM(Monthly!AI40:AT40) -> 43260 | M68: =SUM(Monthly!AU40:BF40) -> 44557.8 | N68: =SUM(Monthly!BG40:BR40) -> 45894.534 | O68: =SUM(Monthly!BS40:CD40) -> 47271.37 | P68: =SUM(Monthly!CE40:CP40) -> 48689.511 | Q68: =SUM(Monthly!CQ40:DB40) -> 50150.196 | R68: =SUM(Monthly!DC40:DN40) -> 51654.702 | S68: =SUM(J68:R68) -> 373478.11
D69: Retail Expenses
E70: Convenience Store/Vending Supplies | G70: 0.03 | H70: YoY Growth | J70: =SUM(Monthly!K42:V42) -> 0 | K70: =SUM(Monthly!W42:AH42) -> 42000 | L70: =SUM(Monthly!AI42:AT42) -> 43260 | M70: =SUM(Monthly!AU42:BF42) -> 44557.8 | N70: =SUM(Monthly!BG42:BR42) -> 45894.534 | O70: =SUM(Monthly!BS42:CD42) -> 47271.37 | P70: =SUM(Monthly!CE42:CP42) -> 48689.511 | Q70: =SUM(Monthly!CQ42:DB42) -> 50150.196 | R70: =SUM(Monthly!DC42:DN42) -> 51654.702 | S70: =SUM(J70:R70) -> 373478.11
D71: Total Departmental Expenses | J71: =SUM(J57:J70) -> 0 | K71: =SUM(K57:K70) -> 294200 | L71: =SUM(L57:L70) -> 303026 | M71: =SUM(M57:M70) -> 312116.78 | N71: =SUM(N57:N70) -> 321480.28 | O71: =SUM(O57:O70) -> 331124.69 | P71: =SUM(P57:P70) -> 341058.43 | Q71: =SUM(Q57:Q70) -> 351290.19 | ... S71: =SUM(S57:S70) -> 2616125.3
C73: UNDISTRIBUTED OPERATING EXPENSES
D74: Administrative & General
E75: Accounting | G75: 0.03 | H75: YoY Growth | J75: =SUM(Monthly!K47:V47) -> 0 | K75: =SUM(Monthly!W47:AH47) -> 3000 | L75: =SUM(Monthly!AI47:AT47) -> 3090 | M75: =SUM(Monthly!AU47:BF47) -> 3182.7 | N75: =SUM(Monthly!BG47:BR47) -> 3278.181 | O75: =SUM(Monthly!BS47:CD47) -> 3376.5264 | P75: =SUM(Monthly!CE47:CP47) -> 3477.8222 | Q75: =SUM(Monthly!CQ47:DB47) -> 3582.1569 | R75: =SUM(Monthly!DC47:DN47) -> 3689.6216 | S75: =SUM(J75:R75) -> 26677.008
E76: Legal | G76: 0.03 | H76: YoY Growth | J76: =SUM(Monthly!K48:V48) -> 0 | K76: =SUM(Monthly!W48:AH48) -> 3000 | L76: =SUM(Monthly!AI48:AT48) -> 3090 | M76: =SUM(Monthly!AU48:BF48) -> 3182.7 | N76: =SUM(Monthly!BG48:BR48) -> 3278.181 | O76: =SUM(Monthly!BS48:CD48) -> 3376.5264 | P76: =SUM(Monthly!CE48:CP48) -> 3477.8222 | Q76: =SUM(Monthly!CQ48:DB48) -> 3582.1569 | R76: =SUM(Monthly!DC48:DN48) -> 3689.6216 | S76: =SUM(J76:R76) -> 26677.008
E77: Misc. | G77: 0.03 | H77: YoY Growth | J77: =SUM(Monthly!K49:V49) -> 0 | K77: =SUM(Monthly!W49:AH49) -> 3000 | L77: =SUM(Monthly!AI49:AT49) -> 3090 | M77: =SUM(Monthly!AU49:BF49) -> 3182.7 | N77: =SUM(Monthly!BG49:BR49) -> 3278.181 | O77: =SUM(Monthly!BS49:CD49) -> 3376.5264 | P77: =SUM(Monthly!CE49:CP49) -> 3477.8222 | Q77: =SUM(Monthly!CQ49:DB49) -> 3582.1569 | R77: =SUM(Monthly!DC49:DN49) -> 3689.6216 | S77: =SUM(J77:R77) -> 26677.008
E78: Bank Fees | G78: 0.03 | H78: YoY Growth | J78: =SUM(Monthly!K50:V50) -> 0 | K78: =SUM(Monthly!W50:AH50) -> 6000 | L78: =SUM(Monthly!AI50:AT50) -> 6180 | M78: =SUM(Monthly!AU50:BF50) -> 6365.4 | N78: =SUM(Monthly!BG50:BR50) -> 6556.362 | O78: =SUM(Monthly!BS50:CD50) -> 6753.0529 | P78: =SUM(Monthly!CE50:CP50) -> 6955.6444 | Q78: =SUM(Monthly!CQ50:DB50) -> 7164.3138 | R78: =SUM(Monthly!DC50:DN50) -> 7379.2432 | S78: =SUM(J78:R78) -> 53354.016
E79: CC Processing | G79: 0.03 | H79: of Revenue | J79: =SUM(Monthly!K51:V51) -> 0 | K79: =SUM(Monthly!W51:AH51) -> 21789.12 | L79: =SUM(Monthly!AI51:AT51) -> 22451.61 | M79: =SUM(Monthly!AU51:BF51) -> 23130.9 | N79: =SUM(Monthly!BG51:BR51) -> 23776.59 | O79: =SUM(Monthly!BS51:CD51) -> 24439.08 | P79: =SUM(Monthly!CE51:CP51) -> 25101.57 | Q79: =SUM(Monthly!CQ51:DB51) -> 25764.06 | R79: =SUM(Monthly!DC51:DN51) -> 26426.55 | S79: =SUM(J79:R79) -> 192879.48
D80: Office & Software
E81: Software Expense | G81: 0.03 | H81: YoY Growth | J81: =SUM(Monthly!K53:V53) -> 0 | K81: =SUM(Monthly!W53:AH53) -> 2520 | L81: =SUM(Monthly!AI53:AT53) -> 2595.6 | M81: =SUM(Monthly!AU53:BF53) -> 2673.468 | N81: =SUM(Monthly!BG53:BR53) -> 2753.672 | O81: =SUM(Monthly!BS53:CD53) -> 2836.2822 | P81: =SUM(Monthly!CE53:CP53) -> 2921.3707 | Q81: =SUM(Monthly!CQ53:DB53) -> 3009.0118 | R81: =SUM(Monthly!DC53:DN53) -> 3099.2821 | S81: =SUM(J81:R81) -> 22408.687
D82: Sales & Marketing
E83: Digital Marketing | G83: 0.03 | H83: YoY Growth | J83: =SUM(Monthly!K55:V55) -> 5500 | K83: =SUM(Monthly!W55:AH55) -> 3000 | L83: =SUM(Monthly!AI55:AT55) -> 3090 | M83: =SUM(Monthly!AU55:BF55) -> 3182.7 | N83: =SUM(Monthly!BG55:BR55) -> 3278.181 | O83: =SUM(Monthly!BS55:CD55) -> 3376.5264 | P83: =SUM(Monthly!CE55:CP55) -> 3477.8222 | Q83: =SUM(Monthly!CQ55:DB55) -> 3582.1569 | R83: =SUM(Monthly!DC55:DN55) -> 3689.6216 | S83: =SUM(J83:R83) -> 32177.008
D84: Property Operating & Maintenance
E85: R&M Groundskeeping/Landscaping | G85: 0.03 | H85: YoY Growth | J85: =SUM(Monthly!K57:V57) -> 0 | K85: =SUM(Monthly!W57:AH57) -> 34560 | L85: =SUM(Monthly!AI57:AT57) -> 35596.8 | M85: =SUM(Monthly!AU57:BF57) -> 36664.704 | N85: =SUM(Monthly!BG57:BR57) -> 37764.645 | O85: =SUM(Monthly!BS57:CD57) -> 38897.584 | P85: =SUM(Monthly!CE57:CP57) -> 40064.512 | Q85: =SUM(Monthly!CQ57:DB57) -> 41266.447 | R85: =SUM(Monthly!DC57:DN57) -> 42504.441 | S85: =SUM(J85:R85) -> 307319.13
E86: R&M Pool | G86: 0.03 | H86: YoY Growth | J86: =SUM(Monthly!K58:V58) -> 0 | K86: =SUM(Monthly!W58:AH58) -> 6000 | L86: =SUM(Monthly!AI58:AT58) -> 6180 | M86: =SUM(Monthly!AU58:BF58) -> 6365.4 | N86: =SUM(Monthly!BG58:BR58) -> 6556.362 | O86: =SUM(Monthly!BS58:CD58) -> 6753.0529 | P86: =SUM(Monthly!CE58:CP58) -> 6955.6444 | Q86: =SUM(Monthly!CQ58:DB58) -> 7164.3138 | R86: =SUM(Monthly!DC58:DN58) -> 7379.2432 | S86: =SUM(J86:R86) -> 53354.016
E87: R&M Plumbing & Septic | G87: 0.03 | H87: YoY Growth | J87: =SUM(Monthly!K59:V59) -> 0 | K87: =SUM(Monthly!W59:AH59) -> 6000 | L87: =SUM(Monthly!AI59:AT59) -> 6180 | M87: =SUM(Monthly!AU59:BF59) -> 6365.4 | N87: =SUM(Monthly!BG59:BR59) -> 6556.362 | O87: =SUM(Monthly!BS59:CD59) -> 6753.0529 | P87: =SUM(Monthly!CE59:CP59) -> 6955.6444 | Q87: =SUM(Monthly!CQ59:DB59) -> 7164.3138 | R87: =SUM(Monthly!DC59:DN59) -> 7379.2432 | S87: =SUM(J87:R87) -> 53354.016
E88: R&M Tools & Supplies | G88: 0.03 | H88: YoY Growth | J88: =SUM(Monthly!K60:V60) -> 0 | K88: =SUM(Monthly!W60:AH60) -> 6000 | L88: =SUM(Monthly!AI60:AT60) -> 6180 | M88: =SUM(Monthly!AU60:BF60) -> 6365.4 | N88: =SUM(Monthly!BG60:BR60) -> 6556.362 | O88: =SUM(Monthly!BS60:CD60) -> 6753.0529 | P88: =SUM(Monthly!CE60:CP60) -> 6955.6444 | Q88: =SUM(Monthly!CQ60:DB60) -> 7164.3138 | R88: =SUM(Monthly!DC60:DN60) -> 7379.2432 | S88: =SUM(J88:R88) -> 53354.016
D89: Utilities
E90: Water | G90: 0.03 | H90: YoY Growth | J90: =SUM(Monthly!K62:V62) -> 0 | K90: =SUM(Monthly!W62:AH62) -> 13800 | L90: =SUM(Monthly!AI62:AT62) -> 14214 | M90: =SUM(Monthly!AU62:BF62) -> 14640.42 | N90: =SUM(Monthly!BG62:BR62) -> 15079.633 | O90: =SUM(Monthly!BS62:CD62) -> 15532.022 | P90: =SUM(Monthly!CE62:CP62) -> 15997.982 | Q90: =SUM(Monthly!CQ62:DB62) -> 16477.922 | R90: =SUM(Monthly!DC62:DN62) -> 16972.259 | S90: =SUM(J90:R90) -> 122714.24
E91: Telephone | G91: 0.03 | H91: YoY Growth | J91: =SUM(Monthly!K63:V63) -> 0 | K91: =SUM(Monthly!W63:AH63) -> 3000 | L91: =SUM(Monthly!AI63:AT63) -> 3090 | M91: =SUM(Monthly!AU63:BF63) -> 3182.7 | N91: =SUM(Monthly!BG63:BR63) -> 3278.181 | O91: =SUM(Monthly!BS63:CD63) -> 3376.5264 | P91: =SUM(Monthly!CE63:CP63) -> 3477.8222 | Q91: =SUM(Monthly!CQ63:DB63) -> 3582.1569 | R91: =SUM(Monthly!DC63:DN63) -> 3689.6216 | S91: =SUM(J91:R91) -> 26677.008
E92: Cable/Internet | G92: 0.03 | H92: YoY Growth | J92: =SUM(Monthly!K64:V64) -> 0 | K92: =SUM(Monthly!W64:AH64) -> 14400 | L92: =SUM(Monthly!AI64:AT64) -> 14832 | M92: =SUM(Monthly!AU64:BF64) -> 15276.96 | N92: =SUM(Monthly!BG64:BR64) -> 15735.269 | O92: =SUM(Monthly!BS64:CD64) -> 16207.327 | P92: =SUM(Monthly!CE64:CP64) -> 16693.547 | Q92: =SUM(Monthly!CQ64:DB64) -> 17194.353 | R92: =SUM(Monthly!DC64:DN64) -> 17710.184 | S92: =SUM(J92:R92) -> 128049.64
E93: Electric | G93: 0.03 | H93: YoY Growth | J93: =SUM(Monthly!K65:V65) -> 0 | K93: =SUM(Monthly!W65:AH65) -> 18000 | L93: =SUM(Monthly!AI65:AT65) -> 18540 | M93: =SUM(Monthly!AU65:BF65) -> 19096.2 | N93: =SUM(Monthly!BG65:BR65) -> 19669.086 | O93: =SUM(Monthly!BS65:CD65) -> 20259.159 | P93: =SUM(Monthly!CE65:CP65) -> 20866.933 | Q93: =SUM(Monthly!CQ65:DB65) -> 21492.941 | R93: =SUM(Monthly!DC65:DN65) -> 22137.73 | S93: =SUM(J93:R93) -> 160062.05
E94: Gas | G94: 0.03 | H94: YoY Growth | J94: =SUM(Monthly!K66:V66) -> 0 | K94: =SUM(Monthly!W66:AH66) -> 12000 | L94: =SUM(Monthly!AI66:AT66) -> 12360 | M94: =SUM(Monthly!AU66:BF66) -> 12730.8 | N94: =SUM(Monthly!BG66:BR66) -> 13112.724 | O94: =SUM(Monthly!BS66:CD66) -> 13506.106 | P94: =SUM(Monthly!CE66:CP66) -> 13911.289 | Q94: =SUM(Monthly!CQ66:DB66) -> 14328.628 | R94: =SUM(Monthly!DC66:DN66) -> 14758.486 | S94: =SUM(J94:R94) -> 106708.03
E95: Pest Control | G95: 0.03 | H95: YoY Growth | J95: =SUM(Monthly!K67:V67) -> 0 | K95: =SUM(Monthly!W67:AH67) -> 6000 | L95: =SUM(Monthly!AI67:AT67) -> 6180 | M95: =SUM(Monthly!AU67:BF67) -> 6365.4 | N95: =SUM(Monthly!BG67:BR67) -> 6556.362 | O95: =SUM(Monthly!BS67:CD67) -> 6753.0529 | P95: =SUM(Monthly!CE67:CP67) -> 6955.6444 | Q95: =SUM(Monthly!CQ67:DB67) -> 7164.3138 | R95: =SUM(Monthly!DC67:DN67) -> 7379.2432 | S95: =SUM(J95:R95) -> 53354.016
E96: Fire Prevention | G96: 0.03 | H96: YoY Growth | J96: =SUM(Monthly!K68:V68) -> 0 | K96: =SUM(Monthly!W68:AH68) -> 3000 | L96: =SUM(Monthly!AI68:AT68) -> 3090 | M96: =SUM(Monthly!AU68:BF68) -> 3182.7 | N96: =SUM(Monthly!BG68:BR68) -> 3278.181 | O96: =SUM(Monthly!BS68:CD68) -> 3376.5264 | P96: =SUM(Monthly!CE68:CP68) -> 3477.8222 | Q96: =SUM(Monthly!CQ68:DB68) -> 3582.1569 | R96: =SUM(Monthly!DC68:DN68) -> 3689.6216 | S96: =SUM(J96:R96) -> 26677.008
E97: Waste Disposal | G97: 0.03 | H97: YoY Growth | J97: =SUM(Monthly!K69:V69) -> 0 | K97: =SUM(Monthly!W69:AH69) -> 3000 | L97: =SUM(Monthly!AI69:AT69) -> 3090 | M97: =SUM(Monthly!AU69:BF69) -> 3182.7 | N97: =SUM(Monthly!BG69:BR69) -> 3278.181 | O97: =SUM(Monthly!BS69:CD69) -> 3376.5264 | P97: =SUM(Monthly!CE69:CP69) -> 3477.8222 | Q97: =SUM(Monthly!CQ69:DB69) -> 3582.1569 | R97: =SUM(Monthly!DC69:DN69) -> 3689.6216 | S97: =SUM(J97:R97) -> 26677.008
D98: Property Taxes | G98: 0.12 | H98: YoY Growth | J98: =SUM(Monthly!K70:V70) -> 40000 | K98: =SUM(Monthly!W70:AH70) -> 44800 | L98: =SUM(Monthly!AI70:AT70) -> 50176 | M98: =SUM(Monthly!AU70:BF70) -> 56197.12 | N98: =SUM(Monthly!BG70:BR70) -> 62940.774 | O98: =SUM(Monthly!BS70:CD70) -> 70493.667 | P98: =SUM(Monthly!CE70:CP70) -> 78952.907 | Q98: =SUM(Monthly!CQ70:DB70) -> 88427.256 | R98: =SUM(Monthly!DC70:DN70) -> 99038.527 | S98: =SUM(J98:R98) -> 591026.25
D99: Insurance
E100: General Liability | G100: 0.1 | H100: YoY Growth | J100: =SUM(Monthly!K72:V72) -> 5300 | K100: =SUM(Monthly!W72:AH72) -> 5830 | L100: =SUM(Monthly!AI72:AT72) -> 6413 | M100: =SUM(Monthly!AU72:BF72) -> 7054.3 | N100: =SUM(Monthly!BG72:BR72) -> 7759.73 | O100: =SUM(Monthly!BS72:CD72) -> 8535.703 | P100: =SUM(Monthly!CE72:CP72) -> 9389.2733 | Q100: =SUM(Monthly!CQ72:DB72) -> 10328.201 | R100: =SUM(Monthly!DC72:DN72) -> 11361.021 | S100: =SUM(J100:R100) -> 71971.228
E101: Builders Risk | J101: =SUM(Monthly!K73:V73) -> 3000 | K101: =SUM(Monthly!W73:AH73) -> 0 | L101: =SUM(Monthly!AI73:AT73) -> 0 | M101: =SUM(Monthly!AU73:BF73) -> 0 | N101: =SUM(Monthly!BG73:BR73) -> 0 | O101: =SUM(Monthly!BS73:CD73) -> 0 | P101: =SUM(Monthly!CE73:CP73) -> 0 | Q101: =SUM(Monthly!CQ73:DB73) -> 0 | R101: =SUM(Monthly!DC73:DN73) -> 0 | S101: =SUM(J101:R101) -> 3000
E102: Other | J102: =SUM(Monthly!K74:V74) -> 0 | K102: =SUM(Monthly!W74:AH74) -> 0 | L102: =SUM(Monthly!AI74:AT74) -> 0 | M102: =SUM(Monthly!AU74:BF74) -> 0 | N102: =SUM(Monthly!BG74:BR74) -> 0 | O102: =SUM(Monthly!BS74:CD74) -> 0 | P102: =SUM(Monthly!CE74:CP74) -> 0 | Q102: =SUM(Monthly!CQ74:DB74) -> 0 | R102: =SUM(Monthly!DC74:DN74) -> 0 | S102: =SUM(J102:R102) -> 0
D103: Total Undistributed Expenses | J103: =SUM(J74:J102) -> 53800 | K103: =SUM(K74:K102) -> 218699.12 | L103: =SUM(L74:L102) -> 229709.01 | M103: =SUM(M74:M102) -> 241570.77 | N103: =SUM(N74:N102) -> 254321.2 | O103: =SUM(O74:O102) -> 268107.88 | P103: =SUM(P74:P102) -> 283022.36 | Q103: =SUM(Q74:Q102) -> 299185.49 | ... S103: =SUM(S74:S102) -> 2165147.9
C105: TOTAL OPERATING EXPENSES | J105: =J103+J71 -> 53800 | K105: =K103+K71 -> 512899.12 | L105: =L103+L71 -> 532735.01 | M105: =M103+M71 -> 553687.55 | N105: =N103+N71 -> 575801.48 | O105: =O103+O71 -> 599232.57 | P105: =P103+P71 -> 624080.79 | Q105: =Q103+Q71 -> 650475.67 | ... S105: =S103+S71 -> 4781273.1
C107: NET OPERATING INCOME (NOI) | J107: =J54-J105 -> -53800 | K107: =K54-K105 -> 213404.88 | L107: =L54-L105 -> 215651.99 | M107: =M54-M105 -> 217342.45 | N107: =N54-N105 -> 216751.52 | O107: =O54-O105 -> 215403.43 | P107: =P54-P105 -> 212638.21 | Q107: =Q54-Q105 -> 208326.33 | ... S107: =S54-S105 -> 1648042.9
C109: NON-OPERATING EXPENSES
D110: Debt Service - Interest
E111: Acquisition Loan (Int. Rate) | G111: =M22 -> 0.095 | J111: =SUM(Monthly!K83:V83) -> 111625 | K111: =SUM(Monthly!W83:AH83) -> 111625 | L111: =SUM(Monthly!AI83:AT83) -> 89993.15 | M111: =SUM(Monthly!AU83:BF83) -> 89133.749 | N111: =SUM(Monthly!BG83:BR83) -> 89133.749 | O111: =SUM(Monthly!BS83:CD83) -> 89133.749 | P111: =SUM(Monthly!CE83:CP83) -> 89133.749 | Q111: =SUM(Monthly!CQ83:DB83) -> 89133.749 | R111: =SUM(Monthly!DC83:DN83) -> 89133.749 | S111: =SUM(J111:R111) -> 848045.65
E112: Seller Carryback (Int. Rate) | G112: =IF(M23=0,"N/A",0) -> N/A | J112: =SUM(Monthly!K84:V84) -> 0 | K112: =SUM(Monthly!W84:AH84) -> 0 | L112: =SUM(Monthly!AI84:AT84) -> 0 | M112: =SUM(Monthly!AU84:BF84) -> 0 | N112: =SUM(Monthly!BG84:BR84) -> 0 | O112: =SUM(Monthly!BS84:CD84) -> 0 | P112: =SUM(Monthly!CE84:CP84) -> 0 | Q112: =SUM(Monthly!CQ84:DB84) -> 0 | R112: =SUM(Monthly!DC84:DN84) -> 0 | S112: =SUM(J112:R112) -> 0
E113: Construction Loan (Int. Rate) | G113: =M24 -> 0.095 | J113: =SUM(Monthly!K85:V85) -> 62899.524 | K113: =SUM(Monthly!W85:AH85) -> 195474.95 | L113: =SUM(Monthly!AI85:AT85) -> 1644.5104 | M113: =SUM(Monthly!AU85:BF85) -> 5492.7966 | N113: =SUM(Monthly!BG85:BR85) -> 10208.906 | O113: =SUM(Monthly!BS85:CD85) -> 16055.124 | P113: =SUM(Monthly!CE85:CP85) -> 24139.697 | Q113: =SUM(Monthly!CQ85:DB85) -> 34364.568 | R113: =SUM(Monthly!DC85:DN85) -> 46294.164 | S113: =SUM(J113:R113) -> 396574.24
E114: Permanent Loan (Int. Rate) | G114: =M28 -> 0.06 | J114: =SUM(Monthly!K86:V86) -> 0 | K114: =SUM(Monthly!W86:AH86) -> 0 | L114: =SUM(Monthly!AI86:AT86) -> 141408.29 | M114: =SUM(Monthly!AU86:BF86) -> 140804.87 | N114: =SUM(Monthly!BG86:BR86) -> 138883.01 | O114: =SUM(Monthly!BS86:CD86) -> 135652.03 | P114: =SUM(Monthly!CE86:CP86) -> 131718.91 | Q114: =SUM(Monthly!CQ86:DB86) -> 126493.71 | R114: =SUM(Monthly!DC86:DN86) -> 120587.98 | S114: =SUM(J114:R114) -> 935548.81
D115: Total Debt Service | J115: =SUM(J111:J114) -> 174524.52 | K115: =SUM(K111:K114) -> 307099.95 | L115: =SUM(L111:L114) -> 233045.95 | M115: =SUM(M111:M114) -> 235431.42 | N115: =SUM(N111:N114) -> 238225.67 | O115: =SUM(O111:O114) -> 240840.9 | P115: =SUM(P111:P114) -> 244992.36 | Q115: =SUM(Q111:Q114) -> 249992.03 | ... S115: =SUM(S111:S114) -> 2180168.7
...

Sheet CF0
B3: Current Basis: | E3: 1888209.9
B5: Ph II Capital Raised | E5: ='Members Capital'!H15 -> 1101000
B6: Accumulated Pref
B7: Sub-Total | E7: =E5+E6 -> 1101000
B9: New Equity Required

Sheet Distributions
D2: Year 1 | P2: Year 2 | AB2: Year 3 | AN2: Year 4 | AZ2: Year 5 | BL2: Year 6 | BX2: Year 7 | CJ2: Year 8 | CV2: Year 9
D3: =Monthly!K4 -> 45413 | E3: =Monthly!L4 -> 45444 | F3: =Monthly!M4 -> 45474 | G3: =Monthly!N4 -> 45505 | H3: =Monthly!O4 -> 45536 | I3: =Monthly!P4 -> 45566 | J3: =Monthly!Q4 -> 45597 | K3: =Monthly!R4 -> 45627 | ... DG3: =Monthly!DN4 -> 48670
D4: May | E4: June | F4: July | G4: August | H4: September | I4: October | J4: November | K4: December | L4: January | M4: February | N4: March | O4: April | P4: May | Q4: June | R4: July | S4: August | T4: September | U4: October | V4: November | W4: December | X4: January | Y4: February | Z4: March | AA4: April | AB4: May | AC4: June | AD4: July | AE4: August | AF4: September | AG4: October | AH4: November | AI4: December | AJ4: January | AK4: February | AL4: March | AM4: April | AN4: May | AO4: June | AP4: July | AQ4: August | AR4: September | AS4: October | AT4: November | AU4: December | AV4: January | AW4: February | AX4: March | AY4: April | AZ4: May | BA4: June | BB4: July | BC4: August | BD4: September | BE4: October | BF4: November | BG4: December | BH4: January | BI4: February | BJ4: March | BK4: April | BL4: May | BM4: June | BN4: July | BO4: August | BP4: September | BQ4: October | BR4: November | BS4: December | BT4: January | BU4: February | BV4: March | BW4: April | BX4: May | BY4: June | BZ4: July | CA4: August | CB4: September | CC4: October | CD4: November | CE4: December | CF4: January | CG4: February | CH4: March | CI4: April | CJ4: May | CK4: June | CL4: July | CM4: August | CN4: September | CO4: October | CP4: November | CQ4: December | CR4: January | CS4: February | CT4: March | CU4: April | CV4: May | CW4: June | CX4: July | CY4: August | CZ4: September | DA4: October | DB4: November | DC4: December | DD4: January | DE4: February | DF4: March | DG4: April | DI4: Total
B5: Monthly Distributions | D5: 1 | E5: 2 | F5: 3 | G5: 4 | H5: 5 | I5: 6 | J5: 7 | K5: 8 | L5: 9 | M5: 10 | N5: 11 | O5: 12 | P5: 13 | Q5: 14 | R5: 15 | S5: 16 | T5: 17 | U5: 18 | V5: 19 | W5: 20 | X5: 21 | Y5: 22 | Z5: 23 | AA5: 24 | AB5: 25 | AC5: 26 | AD5: 27 | AE5: 28 | AF5: 29 | AG5: 30 | AH5: 31 | AI5: 32 | AJ5: 33 | AK5: 34 | AL5: 35 | AM5: 36 | AN5: 37 | AO5: 38 | AP5: 39 | AQ5: 40 | AR5: 41 | AS5: 42 | AT5: 43 | AU5: 44 | AV5: 45 | AW5: 46 | AX5: 47 | AY5: 48 | AZ5: 49 | BA5: 50 | BB5: 51 | BC5: 52 | BD5: 53 | BE5: 54 | BF5: 55 | BG5: 56 | BH5: 57 | BI5: 58 | BJ5: 59 | BK5: 60 | BL5: 61 | BM5: 62 | BN5: 63 | BO5: 64 | BP5: 65 | BQ5: 66 | BR5: 67 | BS5: 68 | BT5: 69 | BU5: 70 | BV5: 71 | BW5: 72 | BX5: 73 | BY5: 74 | BZ5: 75 | CA5: 76 | CB5: 77 | CC5: 78 | CD5: 79 | CE5: 80 | CF5: 81 | CG5: 82 | CH5: 83 | CI5: 84 | CJ5: 85 | CK5: 86 | CL5: 87 | CM5: 88 | CN5: 89 | CO5: 90 | CP5: 91 | CQ5: 92 | CR5: 93 | CS5: 94 | CT5: 95 | CU5: 96 | CV5: 97 | CW5: 98 | CX5: 99 | CY5: 100 | CZ5: 101 | DA5: 102 | DB5: 103 | DC5: 104 | DD5: 105 | DE5: 106 | DF5: 107 | DG5: 108
B6: PH II Capital | D6: =Balances!I93+Balances!I99+Balances!I102 -> 0 | E6: =Balances!J93+Balances!J99+Balances!J102 -> 0 | F6: =Balances!K93+Balances!K99+Balances!K102 -> 0 | G6: =Balances!L93+Balances!L99+Balances!L102 -> 0 | H6: =Balances!M93+Balances!M99+Balances!M102 -> 0 | I6: =Balances!N93+Balances!N99+Balances!N102 -> 0 | J6: =Balances!O93+Balances!O99+Balances!O102 -> 0 | K6: =Balances!P93+Balances!P99+Balances!P102 -> 0 | ... DG6: =Balances!DL93+Balances!DL99+Balances!DL102 -> 0 | DI6: =SUM(D6:DG6) -> 0
B7: Initial Equity | D7: =Balances!I78 -> 0 | E7: =Balances!J78 -> 0 | F7: =Balances!K78 -> 0 | G7: =Balances!L78 -> 0 | H7: =Balances!M78 -> 0 | I7: =Balances!N78 -> 0 | J7: =Balances!O78 -> 0 | K7: =Balances!P78 -> 0 | ... DG7: =Balances!DL78 -> 0 | DI7: =SUM(D7:DG7) -> 0
B8: Mark | D8: =Balances!I114 -> 0 | E8: =Balances!J114 -> 0 | F8: =Balances!K114 -> 0 | G8: =Balances!L114 -> 0 | H8: =Balances!M114 -> 0 | I8: =Balances!N114 -> 0 | J8: =Balances!O114 -> 0 | K8: =Balances!P114 -> 0 | ... DG8: =Balances!DL114 -> 0 | DI8: =SUM(D8:DG8) -> 0
B9: Sub-Total | D9: =SUM(D6:D8) -> 0 | E9: =SUM(E6:E8) -> 0 | F9: =SUM(F6:F8) -> 0 | G9: =SUM(G6:G8) -> 0 | H9: =SUM(H6:H8) -> 0 | I9: =SUM(I6:I8) -> 0 | J9: =SUM(J6:J8) -> 0 | K9: =SUM(K6:K8) -> 0 | ... DG9: =SUM(DG6:DG8) -> 0 | DI9: =SUM(DI6:DI8) -> 0
B11: Carried Interest | D11: =Balances!I127 -> 0 | E11: =Balances!J127 -> 0 | F11: =Balances!K127 -> 0 | G11: =Balances!L127 -> 0 | H11: =Balances!M127 -> 0 | I11: =Balances!N127 -> 0 | J11: =Balances!O127 -> 0 | K11: =Balances!P127 -> 0 | ... DG11: =Balances!DL127 -> 0 | DI11: =SUM(D11:DG11) -> 0
B12: Total | D12: =D9+D11 -> 0 | E12: =E9+E11 -> 0 | F12: =F9+F11 -> 0 | G12: =G9+G11 -> 0 | H12: =H9+H11 -> 0 | I12: =I9+I11 -> 0 | J12: =J9+J11 -> 0 | K12: =K9+K11 -> 0 | ... DG12: =DG9+DG11 -> 0 | DI12: =DI9+DI11 -> 0
B15: Annual Distributions | D15: Year 1 | E15: Year 2 | F15: Year 3 | G15: Year 4 | H15: Year 5 | I15: Year 6 | J15: Year 7 | K15: Year 8 | L15: Year 9 | M15: Total
B16: =B6 -> PH II Capital | D16: =SUM(D6:O6) -> 0 | E16: =SUM(P6:AA6) -> 0 | F16: =SUM(AB6:AM6) -> 0 | G16: =SUM(AN6:AY6) -> 0 | H16: =SUM(AZ6:BK6) -> 0 | I16: =SUM(BL6:BW6) -> 0 | J16: =SUM(BX6:CI6) -> 0 | K16: =SUM(CJ6:CU6) -> 0 | L16: =SUM(CV6:DG6) -> 0 | M16: =SUM(C16:L16) -> 0
B17: =B7 -> Initial Equity | D17: =SUM(D7:O7) -> 0 | E17: =SUM(P7:AA7) -> 0 | F17: =SUM(AB7:AM7) -> 0 | G17: =SUM(AN7:AY7) -> 0 | H17: =SUM(AZ7:BK7) -> 0 | I17: =SUM(BL7:BW7) -> 0 | J17: =SUM(BX7:CI7) -> 0 | K17: =SUM(CJ7:CU7) -> 0 | L17: =SUM(CV7:DG7) -> 0 | M17: =SUM(C17:L17) -> 0
B18: =B8 -> Mark | D18: =SUM(D8:O8) -> 0 | E18: =SUM(P8:AA8) -> 0 | F18: =SUM(AB8:AM8) -> 0 | G18: =SUM(AN8:AY8) -> 0 | H18: =SUM(AZ8:BK8) -> 0 | I18: =SUM(BL8:BW8) -> 0 | J18: =SUM(BX8:CI8) -> 0 | K18: =SUM(CJ8:CU8) -> 0 | L18: =SUM(CV8:DG8) -> 0 | M18: =SUM(C18:L18) -> 0
B19: Sub-Total | D19: =SUM(D16:D18) -> 0 | E19: =SUM(E16:E18) -> 0 | F19: =SUM(F16:F18) -> 0 | G19: =SUM(G16:G18) -> 0 | H19: =SUM(H16:H18) -> 0 | I19: =SUM(I16:I18) -> 0 | J19: =SUM(J16:J18) -> 0 | K19: =SUM(K16:K18) -> 0 | ... M19: =SUM(M16:M18) -> 0
B21: Carried Interest | D21: =SUM(D11:O11) -> 0 | E21: =SUM(P11:AA11) -> 0 | F21: =SUM(AB11:AM11) -> 0 | G21: =SUM(AN11:AY11) -> 0 | H21: =SUM(AZ11:BK11) -> 0 | I21: =SUM(BL11:BW11) -> 0 | J21: =SUM(BX11:CI11) -> 0 | K21: =SUM(CJ11:CU11) -> 0 | L21: =SUM(CV11:DG11) -> 0 | M21: =SUM(C21:L21) -> 0
B22: Total | D22: =D19+D21 -> 0 | E22: =E19+E21 -> 0 | F22: =F19+F21 -> 0 | G22: =G19+G21 -> 0 | H22: =H19+H21 -> 0 | I22: =I19+I21 -> 0 | J22: =J19+J21 -> 0 | K22: =K19+K21 -> 0 | ... M22: =M19+M21 -> 0

Sheet Monthly
H2: # Days: | J2: 30 | K2: 31 | L2: 30 | M2: 31 | N2: 31 | O2: 30 | P2: 31 | Q2: 30 | R2: 31 | S2: 31 | T2: 28 | U2: 31 | V2: 30 | W2: 31 | X2: 30 | Y2: 31 | Z2: 31 | AA2: 30 | AB2: 31 | AC2: 30 | AD2: 31 | AE2: 31 | AF2: 28 | AG2: 31 | AH2: 30 | AI2: 31 | AJ2: 30 | AK2: 31 | AL2: 31 | AM2: 30 | AN2: 31 | AO2: 30 | AP2: 31 | AQ2: 31 | AR2: 28 | AS2: 31 | AT2: 30 | AU2: 31 | AV2: 30 | AW2: 31 | AX2: 31 | AY2: 30 | AZ2: 31 | BA2: 30 | BB2: 31 | BC2: 31 | BD2: 29 | BE2: 31 | BF2: 30 | BG2: 31 | BH2: 30 | BI2: 31 | BJ2: 31 | BK2: 30 | BL2: 31 | BM2: 30 | BN2: 31 | BO2: 31 | BP2: 28 | BQ2: 31 | BR2: 30 | BS2: 31 | BT2: 30 | BU2: 31 | BV2: 31 | BW2: 30 | BX2: 31 | BY2: 30 | BZ2: 31 | CA2: 31 | CB2: 28 | CC2: 31 | CD2: 30 | CE2: 31 | CF2: 30 | CG2: 31 | CH2: 31 | CI2: 30 | CJ2: 31 | CK2: 30 | CL2: 31 | CM2: 31 | CN2: 28 | CO2: 31 | CP2: 30 | CQ2: 31 | CR2: 30 | CS2: 31 | CT2: 31 | CU2: 30 | CV2: 31 | CW2: 30 | CX2: 31 | CY2: 31 | CZ2: 28 | DA2: 31 | DB2: 30 | DC2: 31 | DD2: 30 | DE2: 31 | DF2: 31 | DG2: 30 | DH2: 31 | DI2: 30 | DJ2: 31 | DK2: 31 | DL2: 28 | DM2: 31 | DN2: 30
J3: CF0 | K3: Year 1 | W3: Year 2 | AI3: Year 3 | AU3: Year 4 | BG3: Year 5 | BS3: Year 6 | CE3: Year 7 | CQ3: Year 8 | DC3: Year 9
J4: 45383 | K4: 45413 | L4: 45444 | M4: 45474 | N4: 45505 | O4: 45536 | P4: 45566 | Q4: 45597 | R4: 45627 | S4: 45658 | T4: 45689 | U4: 45717 | V4: 45748 | W4: 45778 | X4: 45809 | Y4: 45839 | Z4: 45870 | AA4: 45901 | AB4: 45931 | AC4: 45962 | AD4: 45992 | AE4: 46023 | AF4: 46054 | AG4: 46082 | AH4: 46113 | AI4: 46143 | AJ4: 46174 | AK4: 46204 | AL4: 46235 | AM4: 46266 | AN4: 46296 | AO4: 46327 | AP4: 46357 | AQ4: 46388 | AR4: 46419 | AS4: 46447 | AT4: 46478 | AU4: 46508 | AV4: 46539 | AW4: 46569 | AX4: 46600 | AY4: 46631 | AZ4: 46661 | BA4: 46692 | BB4: 46722 | BC4: 46753 | BD4: 46784 | BE4: 46813 | BF4: 46844 | BG4: 46874 | BH4: 46905 | BI4: 46935 | BJ4: 46966 | BK4: 46997 | BL4: 47027 | BM4: 47058 | BN4: 47088 | BO4: 47119 | BP4: 47150 | BQ4: 47178 | BR4: 47209 | BS4: 47239 | BT4: 47270 | BU4: 47300 | BV4: 47331 | BW4: 47362 | BX4: 47392 | BY4: 47423 | BZ4: 47453 | CA4: 47484 | CB4: 47515 | CC4: 47543 | CD4: 47574 | CE4: 47604 | CF4: 47635 | CG4: 47665 | CH4: 47696 | CI4: 47727 | CJ4: 47757 | CK4: 47788 | CL4: 47818 | CM4: 47849 | CN4: 47880 | CO4: 47908 | CP4: 47939 | CQ4: 47969 | CR4: 48000 | CS4: 48030 | CT4: 48061 | CU4: 48092 | CV4: 48122 | CW4: 48153 | CX4: 48183 | CY4: 48214 | CZ4: 48245 | DA4: 48274 | DB4: 48305 | DC4: 48335 | DD4: 48366 | DE4: 48396 | DF4: 48427 | DG4: 48458 | DH4: 48488 | DI4: 48519 | DJ4: 48549 | DK4: 48580 | DL4: 48611 | DM4: 48639 | DN4: 48670 | DP4: Total
J5: 0 | K5: =J5+1 -> 1 | L5: =K5+1 -> 2 | M5: =L5+1 -> 3 | N5: =M5+1 -> 4 | O5: =N5+1 -> 5 | P5: =O5+1 -> 6 | Q5: =P5+1 -> 7 | R5: =Q5+1 -> 8 | ... DN5: =DM5+1 -> 108
C7: ='Table 3.0'!C35 -> RV RENTAL INCOME
D8: ='Table 3.0'!D36 -> Short-Term RV Rental Income | K8: ='Rent Roll'!C12 -> 0 | L8: =K8 -> 0 | M8: =L8 -> 0 | N8: =M8 -> 0 | O8: =N8 -> 0 | P8: =O8 -> 0 | Q8: =P8 -> 0 | R8: =Q8 -> 0 | S8: =R8 -> 0 | ... V8: =U8 -> 0 | W8: ='Rent Roll'!H12 -> 12600 | X8: =W8 -> 12600 | Y8: =X8 -> 12600 | Z8: =Y8 -> 12600 | AA8: =Z8 -> 12600 | AB8: =AA8 -> 12600 | AC8: =AB8 -> 12600 | AD8: =AC8 -> 12600 | AE8: =AD8 -> 12600 | ... AH8: =AG8 -> 12600 | AI8: ='Rent Roll'!M12 -> 13650 | AJ8: =AI8 -> 13650 | AK8: =AJ8 -> 13650 | AL8: =AK8 -> 13650 | AM8: =AL8 -> 13650 | AN8: =AM8 -> 13650 | AO8: =AN8 -> 13650 | AP8: =AO8 -> 13650 | AQ8: =AP8 -> 13650 | ... AT8: =AS8 -> 13650 | AU8: ='Rent Roll'!R12 -> 14700 | AV8: =AU8 -> 14700 | AW8: =AV8 -> 14700 | AX8: =AW8 -> 14700 | AY8: =AX8 -> 14700 | AZ8: =AY8 -> 14700 | BA8: =AZ8 -> 14700 | BB8: =BA8 -> 14700 | BC8: =BB8 -> 14700 | ... BF8: =BE8 -> 14700 | BG8: ='Rent Roll'!W12 -> 15750 | BH8: =BG8 -> 15750 | BI8: =BH8 -> 15750 | BJ8: =BI8 -> 15750 | BK8: =BJ8 -> 15750 | BL8: =BK8 -> 15750 | BM8: =BL8 -> 15750 | BN8: =BM8 -> 15750 | BO8: =BN8 -> 15750 | ... BR8: =BQ8 -> 15750 | BS8: ='Rent Roll'!C43 -> 16800 | BT8: =BS8 -> 16800 | BU8: =BT8 -> 16800 | BV8: =BU8 -> 16800 | BW8: =BV8 -> 16800 | BX8: =BW8 -> 16800 | BY8: =BX8 -> 16800 | BZ8: =BY8 -> 16800 | CA8: =BZ8 -> 16800 | ... CD8: =CC8 -> 16800 | CE8: ='Rent Roll'!H43 -> 17850 | CF8: =CE8 -> 17850 | CG8: =CF8 -> 17850 | CH8: =CG8 -> 17850 | CI8: =CH8 -> 17850 | CJ8: =CI8 -> 17850 | CK8: =CJ8 -> 17850 | CL8: =CK8 -> 17850 | CM8: =CL8 -> 17850 | ... CP8: =CO8 -> 17850 | CQ8: ='Rent Roll'!M43 -> 18900 | CR8: =CQ8 -> 18900 | CS8: =CR8 -> 18900 | CT8: =CS8 -> 18900 | CU8: =CT8 -> 18900 | CV8: =CU8 -> 18900 | CW8: =CV8 -> 18900 | CX8: =CW8 -> 18900 | CY8: =CX8 -> 18900 | ... DB8: =DA8 -> 18900 | DC8: ='Rent Roll'!R43 -> 19950 | DD8: =DC8 -> 19950 | DE8: =DD8 -> 19950 | DF8: =DE8 -> 19950 | DG8: =DF8 -> 19950 | DH8: =DG8 -> 19950 | DI8: =DH8 -> 19950 | DJ8: =DI8 -> 19950 | DK8: =DJ8 -> 19950 | ... DN8: =DM8 -> 19950 | DP8: =SUM(J8:DN8) -> 1562400
D9: ='Table 3.0'!D37 -> Long-Term RV Rental Income | K9: ='Rent Roll'!D17 -> 0 | L9: ='Rent Roll'!D18 -> 0 | M9: ='Rent Roll'!D19 -> 0 | N9: ='Rent Roll'!D20 -> 0 | O9: ='Rent Roll'!D21 -> 0 | P9: ='Rent Roll'!D22 -> 0 | Q9: ='Rent Roll'!D23 -> 0 | R9: ='Rent Roll'!D24 -> 0 | S9: ='Rent Roll'!D25 -> 0 | T9: ='Rent Roll'!D26 -> 0 | U9: ='Rent Roll'!D27 -> 0 | V9: ='Rent Roll'!D28 -> 0 | W9: ='Rent Roll'!I17 -> 26622 | X9: ='Rent Roll'!I18 -> 29580 | Y9: ='Rent Roll'!I19 -> 32538 | Z9: ='Rent Roll'!I20 -> 32538 | AA9: ='Rent Roll'!I21 -> 31059 | AB9: ='Rent Roll'!I22 -> 29580 | AC9: ='Rent Roll'!I23 -> 26622 | AD9: ='Rent Roll'!I24 -> 23664 | AE9: ='Rent Roll'!I25 -> 20706 | AF9: ='Rent Roll'!I26 -> 20706 | AG9: ='Rent Roll'!I27 -> 23664 | AH9: ='Rent Roll'!I28 -> 25143 | AI9: ='Rent Roll'!N17 -> 27405 | AJ9: ='Rent Roll'!N18 -> 30450 | AK9: ='Rent Roll'!N19 -> 33495 | AL9: ='Rent Roll'!N20 -> 33495 | AM9: ='Rent Roll'!N21 -> 31972.5 | AN9: ='Rent Roll'!N22 -> 30450 | AO9: ='Rent Roll'!N23 -> 27405 | AP9: ='Rent Roll'!N24 -> 24360 | AQ9: ='Rent Roll'!N25 -> 21315 | AR9: ='Rent Roll'!N26 -> 21315 | AS9: ='Rent Roll'!N27 -> 24360 | AT9: ='Rent Roll'!N28 -> 25882.5 | AU9: ='Rent Roll'!S17 -> 28188 | AV9: ='Rent Roll'!S18 -> 31320 | AW9: ='Rent Roll'!S19 -> 34452 | AX9: ='Rent Roll'!S20 -> 34452 | AY9: ='Rent Roll'!S21 -> 32886 | AZ9: ='Rent Roll'!S22 -> 31320 | BA9: ='Rent Roll'!S23 -> 28188 | BB9: ='Rent Roll'!S24 -> 25056 | BC9: ='Rent Roll'!S25 -> 21924 | BD9: ='Rent Roll'!S26 -> 21924 | BE9: ='Rent Roll'!S27 -> 25056 | BF9: ='Rent Roll'!S28 -> 26622 | BG9: ='Rent Roll'!X17 -> 28971 | BH9: ='Rent Roll'!X18 -> 32190 | BI9: ='Rent Roll'!X19 -> 35409 | BJ9: ='Rent Roll'!X20 -> 35409 | BK9: ='Rent Roll'!X21 -> 33799.5 | BL9: ='Rent Roll'!X22 -> 32190 | BM9: ='Rent Roll'!X23 -> 28971 | BN9: ='Rent Roll'!X24 -> 25752 | BO9: ='Rent Roll'!X25 -> 22533 | BP9: ='Rent Roll'!X26 -> 22533 | BQ9: ='Rent Roll'!X27 -> 25752 | BR9: ='Rent Roll'!X28 -> 27361.5 | BS9: ='Rent Roll'!D48 -> 29754 | BT9: ='Rent Roll'!D49 -> 33060 | BU9: ='Rent Roll'!D50 -> 36366 | BV9: ='Rent Roll'!D51 -> 36366 | BW9: ='Rent Roll'!D52 -> 34713 | BX9: ='Rent Roll'!D53 -> 33060 | BY9: ='Rent Roll'!D54 -> 29754 | BZ9: ='Rent Roll'!D55 -> 26448 | CA9: ='Rent Roll'!D56 -> 23142 | CB9: ='Rent Roll'!D57 -> 23142 | CC9: ='Rent Roll'!D58 -> 26448 | CD9: ='Rent Roll'!D59 -> 28101 | CE9: ='Rent Roll'!I48 -> 30537 | CF9: ='Rent Roll'!I49 -> 33930 | CG9: ='Rent Roll'!I50 -> 37323 | CH9: ='Rent Roll'!I51 -> 37323 | CI9: ='Rent Roll'!I52 -> 35626.5 | CJ9: ='Rent Roll'!I53 -> 33930 | CK9: ='Rent Roll'!I54 -> 30537 | CL9: ='Rent Roll'!I55 -> 27144 | CM9: ='Rent Roll'!I56 -> 23751 | CN9: ='Rent Roll'!I57 -> 23751 | CO9: ='Rent Roll'!I58 -> 27144 | CP9: ='Rent Roll'!I59 -> 28840.5 | CQ9: ='Rent Roll'!N48 -> 31320 | CR9: ='Rent Roll'!N49 -> 34800 | CS9: ='Rent Roll'!N50 -> 38280 | CT9: ='Rent Roll'!N51 -> 38280 | CU9: ='Rent Roll'!N52 -> 36540 | CV9: ='Rent Roll'!N53 -> 34800 | CW9: ='Rent Roll'!N54 -> 31320 | CX9: ='Rent Roll'!N55 -> 27840 | CY9: ='Rent Roll'!N56 -> 24360 | CZ9: ='Rent Roll'!N57 -> 24360 | DA9: ='Rent Roll'!N58 -> 27840 | DB9: ='Rent Roll'!N59 -> 29580 | DC9: ='Rent Roll'!S48 -> 32103 | DD9: ='Rent Roll'!S49 -> 35670 | DE9: ='Rent Roll'!S50 -> 39237 | DF9: ='Rent Roll'!S51 -> 39237 | DG9: ='Rent Roll'!S52 -> 37453.5 | DH9: ='Rent Roll'!S53 -> 35670 | DI9: ='Rent Roll'!S54 -> 32103 | DJ9: ='Rent Roll'!S55 -> 28536 | DK9: ='Rent Roll'!S56 -> 24969 | DL9: ='Rent Roll'!S57 -> 24969 | DM9: ='Rent Roll'!S58 -> 28536 | DN9: ='Rent Roll'!S59 -> 30319.5 | DP9: =SUM(J9:DN9) -> 2844900
C10: ='Table 3.0'!C38 -> SUB-TOTAL | K10: =SUM(K8:K9) -> 0 | L10: =SUM(L8:L9) -> 0 | M10: =SUM(M8:M9) -> 0 | N10: =SUM(N8:N9) -> 0 | O10: =SUM(O8:O9) -> 0 | P10: =SUM(P8:P9) -> 0 | Q10: =SUM(Q8:Q9) -> 0 | R10: =SUM(R8:R9) -> 0 | ... DN10: =SUM(DN8:DN9) -> 50269.5 | DP10: =SUM(J10:DN10) -> 4407300
C12: ='Table 3.0'!C40 -> Golf Cart Rentals ($/day) (# carts) | G12: ='Table 3.0'!G40 -> 75 | H12: ='Table 3.0'!H40 -> 4 | K12: =IF(K10=0,0,$G$12*$H$12*'Table 3.0'!$L$9*K2) -> 0 | L12: =IF(L10=0,0,$G$12*$H$12*'Table 3.0'!$L$9*L2) -> 0 | M12: =IF(M10=0,0,$G$12*$H$12*'Table 3.0'!$L$9*M2) -> 0 | N12: =IF(N10=0,0,$G$12*$H$12*'Table 3.0'!$L$9*N2) -> 0 | O12: =IF(O10=0,0,$G$12*$H$12*'Table 3.0'!$L$9*O2) -> 0 | P12: =IF(P10=0,0,$G$12*$H$12*'Table 3.0'!$L$9*P2) -> 0 | Q12: =IF(Q10=0,0,$G$12*$H$12*'Table 3.0'!$L$9*Q2) -> 0 | R12: =IF(R10=0,0,$G$12*$H$12*'Table 3.0'!$L$9*R2) -> 0 | ... DN12: =IF(DN10=0,0,$G$12*$H$12*'Table 3.0'!$L$9*DN2) -> 6300 | DP12: =SUM(J12:DN12) -> 613410
C13: ='Table 3.0'!C41 -> Glamping Rentals ($/night) (# spaces) | G13: ='Table 3.0'!G41 -> 40 | H13: ='Table 3.0'!H41 -> 10 | K13: =IF(K10=0,0,$G$13*$H$13*'Table 3.0'!$M$9*Monthly!K2) -> 0 | L13: =IF(L10=0,0,$G$13*$H$13*'Table 3.0'!$M$9*Monthly!L2) -> 0 | M13: =IF(M10=0,0,$G$13*$H$13*'Table 3.0'!$M$9*Monthly!M2) -> 0 | N13: =IF(N10=0,0,$G$13*$H$13*'Table 3.0'!$M$9*Monthly!N2) -> 0 | O13: =IF(O10=0,0,$G$13*$H$13*'Table 3.0'!$M$9*Monthly!O2) -> 0 | P13: =IF(P10=0,0,$G$13*$H$13*'Table 3.0'!$M$9*Monthly!P2) -> 0 | Q13: =IF(Q10=0,0,$G$13*$H$13*'Table 3.0'!$M$9*Monthly!Q2) -> 0 | R13: =IF(R10=0,0,$G$13*$H$13*'Table 3.0'!$M$9*Monthly!R2) -> 0 | ... DN13: =IF(DN10=0,0,$G$13*$H$13*'Table 3.0'!$M$9*Monthly!DN2) -> 6000 | DP13: =SUM(J13:DN13) -> 584200
C14: ='Table 3.0'!C42 -> SUB-TOTAL | K14: =SUM(K12:K13) -> 0 | L14: =SUM(L12:L13) -> 0 | M14: =SUM(M12:M13) -> 0 | N14: =SUM(N12:N13) -> 0 | O14: =SUM(O12:O13) -> 0 | P14: =SUM(P12:P13) -> 0 | Q14: =SUM(Q12:Q13) -> 0 | R14: =SUM(R12:R13) -> 0 | ... DN14: =SUM(DN12:DN13) -> 12300 | DP14: =SUM(J14:DN14) -> 1197610
C16: ='Table 3.0'!C44 -> TOTAL RENTAL INCOME | K16: =K10+K14 -> 0 | L16: =L10+L14 -> 0 | M16: =M10+M14 -> 0 | N16: =N10+N14 -> 0 | O16: =O10+O14 -> 0 | P16: =P10+P14 -> 0 | Q16: =Q10+Q14 -> 0 | R16: =R10+R14 -> 0 | ... DN16: =DN10+DN14 -> 62569.5 | DP16: =SUM(J16:DN16) -> 5604910
C18: ='Table 3.0'!C46 -> OTHER INCOME
D19: ='Table 3.0'!D47 -> Laundry ($/unit/month) | G19: ='Table 3.0'!G47 -> 20 | K19: =IF(K10=0,0,$G$19*'Rent Roll'!$E$7*'Rent Roll'!$C$11*'Rent Roll'!$C$17) -> 0 | L19: =IF(L10=0,0,$G$19*'Rent Roll'!$E$7*'Rent Roll'!$C$11*'Rent Roll'!$C$17) -> 0 | M19: =IF(M10=0,0,$G$19*'Rent Roll'!$E$7*'Rent Roll'!$C$11*'Rent Roll'!$C$17) -> 0 | N19: =IF(N10=0,0,$G$19*'Rent Roll'!$E$7*'Rent Roll'!$C$11*'Rent Roll'!$C$17) -> 0 | O19: =IF(O10=0,0,$G$19*'Rent Roll'!$E$7*'Rent Roll'!$C$11*'Rent Roll'!$C$17) -> 0 | P19: =IF(P10=0,0,$G$19*'Rent Roll'!$E$7*'Rent Roll'!$C$11*'Rent Roll'!$C$17) -> 0 | Q19: =IF(Q10=0,0,$G$19*'Rent Roll'!$E$7*'Rent Roll'!$C$11*'Rent Roll'!$C$17) -> 0 | R19: =IF(R10=0,0,$G$19*'Rent Roll'!$E$7*'Rent Roll'!$C$11*'Rent Roll'!$C$17) -> 0 | ... DN19: =IF(DN10=0,0,$G$19*'Rent Roll'!$E$7*'Rent Roll'!$C$11*'Rent Roll'!$C$17) -> 783 | DP19: =SUM(J19:DN19) -> 75168
D20: ='Table 3.0'!D48 -> Convenience Store Sales (gross revenue per day) | G20: ='Table 3.0'!G48 -> 150 | K20: =IF(K10=0,0,$G$20*K2) -> 0 | L20: =IF(L10=0,0,$G$20*L2) -> 0 | M20: =IF(M10=0,0,$G$20*M2) -> 0 | N20: =IF(N10=0,0,$G$20*N2) -> 0 | O20: =IF(O10=0,0,$G$20*O2) -> 0 | P20: =IF(P10=0,0,$G$20*P2) -> 0 | Q20: =IF(Q10=0,0,$G$20*Q2) -> 0 | R20: =IF(R10=0,0,$G$20*R2) -> 0 | ... DN20: =IF(DN10=0,0,$G$20*DN2) -> 4500 | DP20: =SUM(J20:DN20) -> 438150
D21: ='Table 3.0'!D49 -> Laundry Vending ($/unit/month) | G21: ='Table 3.0'!G49 -> 10 | K21: =IF(K10=0,0,$G$21*'Rent Roll'!$E$7*'Rent Roll'!$C$11*'Rent Roll'!$C$17) -> 0 | L21: =IF(L10=0,0,$G$21*'Rent Roll'!$E$7*'Rent Roll'!$C$11*'Rent Roll'!$C$17) -> 0 | M21: =IF(M10=0,0,$G$21*'Rent Roll'!$E$7*'Rent Roll'!$C$11*'Rent Roll'!$C$17) -> 0 | N21: =IF(N10=0,0,$G$21*'Rent Roll'!$E$7*'Rent Roll'!$C$11*'Rent Roll'!$C$17) -> 0 | O21: =IF(O10=0,0,$G$21*'Rent Roll'!$E$7*'Rent Roll'!$C$11*'Rent Roll'!$C$17) -> 0 | P21: =IF(P10=0,0,$G$21*'Rent Roll'!$E$7*'Rent Roll'!$C$11*'Rent Roll'!$C$17) -> 0 | Q21: =IF(Q10=0,0,$G$21*'Rent Roll'!$E$7*'Rent Roll'!$C$11*'Rent Roll'!$C$17) -> 0 | R21: =IF(R10=0,0,$G$21*'Rent Roll'!$E$7*'Rent Roll'!$C$11*'Rent Roll'!$C$17) -> 0 | ... DN21: =IF(DN10=0,0,$G$21*'Rent Roll'!$E$7*'Rent Roll'!$C$11*'Rent Roll'!$C$17) -> 391.5 | DP21: =SUM(J21:DN21) -> 37584
D22: ='Table 3.0'!D50 -> Candy/Soda Vending ($/machine/month) | G22: ='Table 3.0'!G50 -> 250 | K22: =IF(K10=0,0,$G$22*'Table 3.0'!$K$10) -> 0 | L22: =IF(L10=0,0,$G$22*'Table 3.0'!$K$10) -> 0 | M22: =IF(M10=0,0,$G$22*'Table 3.0'!$K$10) -> 0 | N22: =IF(N10=0,0,$G$22*'Table 3.0'!$K$10) -> 0 | O22: =IF(O10=0,0,$G$22*'Table 3.0'!$K$10) -> 0 | P22: =IF(P10=0,0,$G$22*'Table 3.0'!$K$10) -> 0 | Q22: =IF(Q10=0,0,$G$22*'Table 3.0'!$K$10) -> 0 | R22: =IF(R10=0,0,$G$22*'Table 3.0'!$K$10) -> 0 | ... DN22: =IF(DN10=0,0,$G$22*'Table 3.0'!$K$10) -> 500 | DP22: =SUM(J22:DN22) -> 48000
D23: ='Table 3.0'!D51 -> Elec. Reimbursement (Reimb. per LT unit) | G23: ='Table 3.0'!G51 -> 60 | K23: =IF(K10=0,0,$G$23*'Rent Roll'!$E$7*'Rent Roll'!$C$11*'Rent Roll'!$C$17) -> 0 | L23: =IF(L10=0,0,$G$23*'Rent Roll'!$E$7*'Rent Roll'!$C$11*'Rent Roll'!$C$17) -> 0 | M23: =IF(M10=0,0,$G$23*'Rent Roll'!$E$7*'Rent Roll'!$C$11*'Rent Roll'!$C$17) -> 0 | N23: =IF(N10=0,0,$G$23*'Rent Roll'!$E$7*'Rent Roll'!$C$11*'Rent Roll'!$C$17) -> 0 | O23: =IF(O10=0,0,$G$23*'Rent Roll'!$E$7*'Rent Roll'!$C$11*'Rent Roll'!$C$17) -> 0 | P23: =IF(P10=0,0,$G$23*'Rent Roll'!$E$7*'Rent Roll'!$C$11*'Rent Roll'!$C$17) -> 0 | Q23: =IF(Q10=0,0,$G$23*'Rent Roll'!$E$7*'Rent Roll'!$C$11*'Rent Roll'!$C$17) -> 0 | R23: =IF(R10=0,0,$G$23*'Rent Roll'!$E$7*'Rent Roll'!$C$11*'Rent Roll'!$C$17) -> 0 | ... DN23: =IF(DN10=0,0,$G$23*'Rent Roll'!$E$7*'Rent Roll'!$C$11*'Rent Roll'!$C$17) -> 2349 | DP23: =SUM(J23:DN23) -> 225504
C24: ='Table 3.0'!C52 -> SUB-TOTAL | K24: =SUM(K19:K23) -> 0 | L24: =SUM(L19:L23) -> 0 | M24: =SUM(M19:M23) -> 0 | N24: =SUM(N19:N23) -> 0 | O24: =SUM(O19:O23) -> 0 | P24: =SUM(P19:P23) -> 0 | Q24: =SUM(Q19:Q23) -> 0 | R24: =SUM(R19:R23) -> 0 | ... DN24: =SUM(DN19:DN23) -> 8523.5 | DP24: =SUM(J24:DN24) -> 824406
C26: ='Table 3.0'!C54 -> EFFECTIVE GROSS REVENUE | K26: =K24+K16 -> 0 | L26: =L24+L16 -> 0 | M26: =M24+M16 -> 0 | N26: =N24+N16 -> 0 | O26: =O24+O16 -> 0 | P26: =P24+P16 -> 0 | Q26: =Q24+Q16 -> 0 | R26: =R24+R16 -> 0 | ... DN26: =DN24+DN16 -> 71093 | DP26: =SUM(J26:DJ26) -> 6157428.5
C28: ='Table 3.0'!C56 -> DEPARTMENTAL EXPENSES
D29: ='Table 3.0'!D57 -> Labor
E30: ='Table 3.0'!E58 -> Salaries & Wages
F31: ='Table 3.0'!F59 -> Community Manager | G31: ='Table 3.0'!G59 -> 0.03 | H31: ='Table 3.0'!H59 -> YoY Growth | W31: =Labor!$H$18/12 -> 5416.6667 | X31: =Labor!$H$18/12 -> 5416.6667 | Y31: =Labor!$H$18/12 -> 5416.6667 | Z31: =Labor!$H$18/12 -> 5416.6667 | AA31: =Labor!$H$18/12 -> 5416.6667 | AB31: =Labor!$H$18/12 -> 5416.6667 | AC31: =Labor!$H$18/12 -> 5416.6667 | AD31: =Labor!$H$18/12 -> 5416.6667 | ... AH31: =Labor!$H$18/12 -> 5416.6667 | AI31: =Labor!$H$18/12*(1+$G$31) -> 5579.1667 | AJ31: =Labor!$H$18/12*(1+$G$31) -> 5579.1667 | AK31: =Labor!$H$18/12*(1+$G$31) -> 5579.1667 | AL31: =Labor!$H$18/12*(1+$G$31) -> 5579.1667 | AM31: =Labor!$H$18/12*(1+$G$31) -> 5579.1667 | AN31: =Labor!$H$18/12*(1+$G$31) -> 5579.1667 | AO31: =Labor!$H$18/12*(1+$G$31) -> 5579.1667 | AP31: =Labor!$H$18/12*(1+$G$31) -> 5579.1667 | ... AT31: =Labor!$H$18/12*(1+$G$31) -> 5579.1667 | AU31: =Labor!$H$18/12*(1+$G$31)^2 -> 5746.5417 | AV31: =Labor!$H$18/12*(1+$G$31)^2 -> 5746.5417 | AW31: =Labor!$H$18/12*(1+$G$31)^2 -> 5746.5417 | AX31: =Labor!$H$18/12*(1+$G$31)^2 -> 5746.5417 | AY31: =Labor!$H$18/12*(1+$G$31)^2 -> 5746.5417 | AZ31: =Labor!$H$18/12*(1+$G$31)^2 -> 5746.5417 | BA31: =Labor!$H$18/12*(1+$G$31)^2 -> 5746.5417 | BB31: =Labor!$H$18/12*(1+$G$31)^2 -> 5746.5417 | ... BF31: =Labor!$H$18/12*(1+$G$31)^2 -> 5746.5417 | BG31: =Labor!$H$18/12*(1+$G$31)^3 -> 5918.9379 | BH31: =Labor!$H$18/12*(1+$G$31)^3 -> 5918.9379 | BI31: =Labor!$H$18/12*(1+$G$31)^3 -> 5918.9379 | BJ31: =Labor!$H$18/12*(1+$G$31)^3 -> 5918.9379 | BK31: =Labor!$H$18/12*(1+$G$31)^3 -> 5918.9379 | BL31: =Labor!$H$18/12*(1+$G$31)^3 -> 5918.9379 | BM31: =Labor!$H$18/12*(1+$G$31)^3 -> 5918.9379 | BN31: =Labor!$H$18/12*(1+$G$31)^3 -> 5918.9379 | ... BR31: =Labor!$H$18/12*(1+$G$31)^3 -> 5918.9379 | BS31: =Labor!$H$18/12*(1+$G$31)^4 -> 6096.5061 | BT31: =Labor!$H$18/12*(1+$G$31)^4 -> 6096.5061 | BU31: =Labor!$H$18/12*(1+$G$31)^4 -> 6096.5061 | BV31: =Labor!$H$18/12*(1+$G$31)^4 -> 6096.5061 | BW31: =Labor!$H$18/12*(1+$G$31)^4 -> 6096.5061 | BX31: =Labor!$H$18/12*(1+$G$31)^4 -> 6096.5061 | BY31: =Labor!$H$18/12*(1+$G$31)^4 -> 6096.5061 | BZ31: =Labor!$H$18/12*(1+$G$31)^4 -> 6096.5061 | ... CD31: =Labor!$H$18/12*(1+$G$31)^4 -> 6096.5061 | CE31: =Labor!$H$18/12*(1+$G$31)^5 -> 6279.4012 | CF31: =Labor!$H$18/12*(1+$G$31)^5 -> 6279.4012 | CG31: =Labor!$H$18/12*(1+$G$31)^5 -> 6279.4012 | CH31: =Labor!$H$18/12*(1+$G$31)^5 -> 6279.4012 | CI31: =Labor!$H$18/12*(1+$G$31)^5 -> 6279.4012 | CJ31: =Labor!$H$18/12*(1+$G$31)^5 -> 6279.4012 | CK31: =Labor!$H$18/12*(1+$G$31)^5 -> 6279.4012 | CL31: =Labor!$H$18/12*(1+$G$31)^5 -> 6279.4012 | ... CP31: =Labor!$H$18/12*(1+$G$31)^5 -> 6279.4012 | CQ31: =Labor!$H$18/12*(1+$G$31)^6 -> 6467.7833 | CR31: =Labor!$H$18/12*(1+$G$31)^6 -> 6467.7833 | CS31: =Labor!$H$18/12*(1+$G$31)^6 -> 6467.7833 | CT31: =Labor!$H$18/12*(1+$G$31)^6 -> 6467.7833 | CU31: =Labor!$H$18/12*(1+$G$31)^6 -> 6467.7833 | CV31: =Labor!$H$18/12*(1+$G$31)^6 -> 6467.7833 | CW31: =Labor!$H$18/12*(1+$G$31)^6 -> 6467.7833 | CX31: =Labor!$H$18/12*(1+$G$31)^6 -> 6467.7833 | ... DB31: =Labor!$H$18/12*(1+$G$31)^6 -> 6467.7833 | DC31: =Labor!$H$18/12*(1+$G$31)^7 -> 6661.8168 | DD31: =Labor!$H$18/12*(1+$G$31)^7 -> 6661.8168 | DE31: =Labor!$H$18/12*(1+$G$31)^7 -> 6661.8168 | DF31: =Labor!$H$18/12*(1+$G$31)^7 -> 6661.8168 | DG31: =Labor!$H$18/12*(1+$G$31)^7 -> 6661.8168 | DH31: =Labor!$H$18/12*(1+$G$31)^7 -> 6661.8168 | DI31: =Labor!$H$18/12*(1+$G$31)^7 -> 6661.8168 | DJ31: =Labor!$H$18/12*(1+$G$31)^7 -> 6661.8168 | ... DN31: =Labor!$H$18/12*(1+$G$31)^7 -> 6661.8168 | DP31: =SUM(J31:DN31) -> 578001.84
F32: ='Table 3.0'!F60 -> Maintenance | G32: ='Table 3.0'!G60 -> 0.03 | H32: ='Table 3.0'!H60 -> YoY Growth | W32: =Labor!$H$19/12 -> 5000 | X32: =Labor!$H$19/12 -> 5000 | Y32: =Labor!$H$19/12 -> 5000 | Z32: =Labor!$H$19/12 -> 5000 | AA32: =Labor!$H$19/12 -> 5000 | AB32: =Labor!$H$19/12 -> 5000 | AC32: =Labor!$H$19/12 -> 5000 | AD32: =Labor!$H$19/12 -> 5000 | ... AH32: =Labor!$H$19/12 -> 5000 | AI32: =(Labor!$H$19/12)*(1+$G$32) -> 5150 | AJ32: =(Labor!$H$19/12)*(1+$G$32) -> 5150 | AK32: =(Labor!$H$19/12)*(1+$G$32) -> 5150 | AL32: =(Labor!$H$19/12)*(1+$G$32) -> 5150 | AM32: =(Labor!$H$19/12)*(1+$G$32) -> 5150 | AN32: =(Labor!$H$19/12)*(1+$G$32) -> 5150 | AO32: =(Labor!$H$19/12)*(1+$G$32) -> 5150 | AP32: =(Labor!$H$19/12)*(1+$G$32) -> 5150 | ... AT32: =(Labor!$H$19/12)*(1+$G$32) -> 5150 | AU32: =(Labor!$H$19/12)*(1+$G$32)^2 -> 5304.5 | AV32: =(Labor!$H$19/12)*(1+$G$32)^2 -> 5304.5 | AW32: =(Labor!$H$19/12)*(1+$G$32)^2 -> 5304.5 | AX32: =(Labor!$H$19/12)*(1+$G$32)^2 -> 5304.5 | AY32: =(Labor!$H$19/12)*(1+$G$32)^2 -> 5304.5 | AZ32: =(Labor!$H$19/12)*(1+$G$32)^2 -> 5304.5 | BA32: =(Labor!$H$19/12)*(1+$G$32)^2 -> 5304.5 | BB32: =(Labor!$H$19/12)*(1+$G$32)^2 -> 5304.5 | ... BF32: =(Labor!$H$19/12)*(1+$G$32)^2 -> 5304.5 | BG32: =(Labor!$H$19/12)*(1+$G$32)^3 -> 5463.635 | BH32: =(Labor!$H$19/12)*(1+$G$32)^3 -> 5463.635 | BI32: =(Labor!$H$19/12)*(1+$G$32)^3 -> 5463.635 | BJ32: =(Labor!$H$19/12)*(1+$G$32)^3 -> 5463.635 | BK32: =(Labor!$H$19/12)*(1+$G$32)^3 -> 5463.635 | BL32: =(Labor!$H$19/12)*(1+$G$32)^3 -> 5463.635 | BM32: =(Labor!$H$19/12)*(1+$G$32)^3 -> 5463.635 | BN32: =(Labor!$H$19/12)*(1+$G$32)^3 -> 5463.635 | ... BR32: =(Labor!$H$19/12)*(1+$G$32)^3 -> 5463.635 | BS32: =(Labor!$H$19/12)*(1+$G$32)^4 -> 5627.544 | BT32: =(Labor!$H$19/12)*(1+$G$32)^4 -> 5627.544 | BU32: =(Labor!$H$19/12)*(1+$G$32)^4 -> 5627.544 | BV32: =(Labor!$H$19/12)*(1+$G$32)^4 -> 5627.544 | BW32: =(Labor!$H$19/12)*(1+$G$32)^4 -> 5627.544 | BX32: =(Labor!$H$19/12)*(1+$G$32)^4 -> 5627.544 | BY32: =(Labor!$H$19/12)*(1+$G$32)^4 -> 5627.544 | BZ32: =(Labor!$H$19/12)*(1+$G$32)^4 -> 5627.544 | ... CD32: =(Labor!$H$19/12)*(1+$G$32)^4 -> 5627.544 | CE32: =(Labor!$H$19/12)*(1+$G$32)^5 -> 5796.3704 | CF32: =(Labor!$H$19/12)*(1+$G$32)^5 -> 5796.3704 | CG32: =(Labor!$H$19/12)*(1+$G$32)^5 -> 5796.3704 | CH32: =(Labor!$H$19/12)*(1+$G$32)^5 -> 5796.3704 | CI32: =(Labor!$H$19/12)*(1+$G$32)^5 -> 5796.3704 | CJ32: =(Labor!$H$19/12)*(1+$G$32)^5 -> 5796.3704 | CK32: =(Labor!$H$19/12)*(1+$G$32)^5 -> 5796.3704 | CL32: =(Labor!$H$19/12)*(1+$G$32)^5 -> 5796.3704 | ... CP32: =(Labor!$H$19/12)*(1+$G$32)^5 -> 5796.3704 | CQ32: =(Labor!$H$19/12)*(1+$G$32)^6 -> 5970.2615 | CR32: =(Labor!$H$19/12)*(1+$G$32)^6 -> 5970.2615 | CS32: =(Labor!$H$19/12)*(1+$G$32)^6 -> 5970.2615 | CT32: =(Labor!$H$19/12)*(1+$G$32)^6 -> 5970.2615 | CU32: =(Labor!$H$19/12)*(1+$G$32)^6 -> 5970.2615 | CV32: =(Labor!$H$19/12)*(1+$G$32)^6 -> 5970.2615 | CW32: =(Labor!$H$19/12)*(1+$G$32)^6 -> 5970.2615 | CX32: =(Labor!$H$19/12)*(1+$G$32)^6 -> 5970.2615 | ... DB32: =(Labor!$H$19/12)*(1+$G$32)^6 -> 5970.2615 | DC32: =(Labor!$H$19/12)*(1+$G$32)^7 -> 6149.3693 | DD32: =(Labor!$H$19/12)*(1+$G$32)^7 -> 6149.3693 | DE32: =(Labor!$H$19/12)*(1+$G$32)^7 -> 6149.3693 | DF32: =(Labor!$H$19/12)*(1+$G$32)^7 -> 6149.3693 | DG32: =(Labor!$H$19/12)*(1+$G$32)^7 -> 6149.3693 | DH32: =(Labor!$H$19/12)*(1+$G$32)^7 -> 6149.3693 | DI32: =(Labor!$H$19/12)*(1+$G$32)^7 -> 6149.3693 | DJ32: =(Labor!$H$19/12)*(1+$G$32)^7 -> 6149.3693 | ... DN32: =(Labor!$H$19/12)*(1+$G$32)^7 -> 6149.3693 | DP32: =SUM(J32:DN32) -> 533540.16
F33: ='Table 3.0'!F61 -> Clubhouse Staff | G33: ='Table 3.0'!G61 -> 0.03 | H33: ='Table 3.0'!H61 -> YoY Growth | W33: =(Labor!$H$20/12)+(Labor!$H$21/12) -> 5000 | X33: =(Labor!$H$20/12)+(Labor!$H$21/12) -> 5000 | Y33: =(Labor!$H$20/12)+(Labor!$H$21/12) -> 5000 | Z33: =(Labor!$H$20/12)+(Labor!$H$21/12) -> 5000 | AA33: =(Labor!$H$20/12)+(Labor!$H$21/12) -> 5000 | AB33: =(Labor!$H$20/12)+(Labor!$H$21/12) -> 5000 | AC33: =(Labor!$H$20/12)+(Labor!$H$21/12) -> 5000 | AD33: =(Labor!$H$20/12)+(Labor!$H$21/12) -> 5000 | ... AH33: =(Labor!$H$20/12)+(Labor!$H$21/12) -> 5000 | AI33: =((Labor!$H$20/12)+(Labor!$H$21/12))*(1+$G$33) -> 5150 | AJ33: =((Labor!$H$20/12)+(Labor!$H$21/12))*(1+$G$33) -> 5150 | AK33: =((Labor!$H$20/12)+(Labor!$H$21/12))*(1+$G$33) -> 5150 | AL33: =((Labor!$H$20/12)+(Labor!$H$21/12))*(1+$G$33) -> 5150 | AM33: =((Labor!$H$20/12)+(Labor!$H$21/12))*(1+$G$33) -> 5150 | AN33: =((Labor!$H$20/12)+(Labor!$H$21/12))*(1+$G$33) -> 5150 | AO33: =((Labor!$H$20/12)+(Labor!$H$21/12))*(1+$G$33) -> 5150 | AP33: =((Labor!$H$20/12)+(Labor!$H$21/12))*(1+$G$33) -> 5150 | ... AT33: =((Labor!$H$20/12)+(Labor!$H$21/12))*(1+$G$33) -> 5150 | AU33: =((Labor!$H$20/12)+(Labor!$H$21/12))*(1+$G$33)^2 -> 5304.5 | AV33: =((Labor!$H$20/12)+(Labor!$H$21/12))*(1+$G$33)^2 -> 5304.5 | AW33: =((Labor!$H$20/12)+(Labor!$H$21/12))*(1+$G$33)^2 -> 5304.5 | AX33: =((Labor!$H$20/12)+(Labor!$H$21/12))*(1+$G$33)^2 -> 5304.5 | AY33: =((Labor!$H$20/12)+(Labor!$H$21/12))*(1+$G$33)^2 -> 5304.5 | AZ33: =((Labor!$H$20/12)+(Labor!$H$21/12))*(1+$G$33)^2 -> 5304.5 | BA33: =((Labor!$H$20/12)+(Labor!$H$21/12))*(1+$G$33)^2 -> 5304.5 | BB33: =((Labor!$H$20/12)+(Labor!$H$21/12))*(1+$G$33)^2 -> 5304.5 | ... BF33: =((Labor!$H$20/12)+(Labor!$H$21/12))*(1+$G$33)^2 -> 5304.5 | BG33: =((Labor!$H$20/12)+(Labor!$H$21/12))*(1+$G$33)^3 -> 5463.635 | BH33: =((Labor!$H$20/12)+(Labor!$H$21/12))*(1+$G$33)^3 -> 5463.635 | BI33: =((Labor!$H$20/12)+(Labor!$H$21/12))*(1+$G$33)^3 -> 5463.635 | BJ33: =((Labor!$H$20/12)+(Labor!$H$21/12))*(1+$G$33)^3 -> 5463.635 | BK33: =((Labor!$H$20/12)+(Labor!$H$21/12))*(1+$G$33)^3 -> 5463.635 | BL33: =((Labor!$H$20/12)+(Labor!$H$21/12))*(1+$G$33)^3 -> 5463.635 | BM33: =((Labor!$H$20/12)+(Labor!$H$21/12))*(1+$G$33)^3 -> 5463.635 | BN33: =((Labor!$H$20/12)+(Labor!$H$21/12))*(1+$G$33)^3 -> 5463.635 | ... BR33: =((Labor!$H$20/12)+(Labor!$H$21/12))*(1+$G$33)^3 -> 5463.635 | BS33: =((Labor!$H$20/12)+(Labor!$H$21/12))*(1+$G$33)^4 -> 5627.544 | BT33: =((Labor!$H$20/12)+(Labor!$H$21/12))*(1+$G$33)^4 -> 5627.544 | BU33: =((Labor!$H$20/12)+(Labor!$H$21/12))*(1+$G$33)^4 -> 5627.544 | BV33: =((Labor!$H$20/12)+(Labor!$H$21/12))*(1+$G$33)^4 -> 5627.544 | BW33: =((Labor!$H$20/12)+(Labor!$H$21/12))*(1+$G$33)^4 -> 5627.544 | BX33: =((Labor!$H$20/12)+(Labor!$H$21/12))*(1+$G$33)^4 -> 5627.544 | BY33: =((Labor!$H$20/12)+(Labor!$H$21/12))*(1+$G$33)^4 -> 5627.544 | BZ33: =((Labor!$H$20/12)+(Labor!$H$21/12))*(1+$G$33)^4 -> 5627.544 | ... CD33: =((Labor!$H$20/12)+(Labor!$H$21/12))*(1+$G$33)^4 -> 5627.544 | CE33: =((Labor!$H$20/12)+(Labor!$H$21/12))*(1+$G$33)^5 -> 5796.3704 | CF33: =((Labor!$H$20/12)+(Labor!$H$21/12))*(1+$G$33)^5 -> 5796.3704 | CG33: =((Labor!$H$20/12)+(Labor!$H$21/12))*(1+$G$33)^5 -> 5796.3704 | CH33: =((Labor!$H$20/12)+(Labor!$H$21/12))*(1+$G$33)^5 -> 5796.3704 | CI33: =((Labor!$H$20/12)+(Labor!$H$21/12))*(1+$G$33)^5 -> 5796.3704 | CJ33: =((Labor!$H$20/12)+(Labor!$H$21/12))*(1+$G$33)^5 -> 5796.3704 | CK33: =((Labor!$H$20/12)+(Labor!$H$21/12))*(1+$G$33)^5 -> 5796.3704 | CL33: =((Labor!$H$20/12)+(Labor!$H$21/12))*(1+$G$33)^5 -> 5796.3704 | ... CP33: =((Labor!$H$20/12)+(Labor!$H$21/12))*(1+$G$33)^5 -> 5796.3704 | CQ33: =((Labor!$H$20/12)+(Labor!$H$21/12))*(1+$G$33)^6 -> 5970.2615 | CR33: =((Labor!$H$20/12)+(Labor!$H$21/12))*(1+$G$33)^6 -> 5970.2615 | CS33: =((Labor!$H$20/12)+(Labor!$H$21/12))*(1+$G$33)^6 -> 5970.2615 | CT33: =((Labor!$H$20/12)+(Labor!$H$21/12))*(1+$G$33)^6 -> 5970.2615 | CU33: =((Labor!$H$20/12)+(Labor!$H$21/12))*(1+$G$33)^6 -> 5970.2615 | CV33: =((Labor!$H$20/12)+(Labor!$H$21/12))*(1+$G$33)^6 -> 5970.2615 | CW33: =((Labor!$H$20/12)+(Labor!$H$21/12))*(1+$G$33)^6 -> 5970.2615 | CX33: =((Labor!$H$20/12)+(Labor!$H$21/12))*(1+$G$33)^6 -> 5970.2615 | ... DB33: =((Labor!$H$20/12)+(Labor!$H$21/12))*(1+$G$33)^6 -> 5970.2615 | DC33: =((Labor!$H$20/12)+(Labor!$H$21/12))*(1+$G$33)^7 -> 6149.3693 | DD33: =((Labor!$H$20/12)+(Labor!$H$21/12))*(1+$G$33)^7 -> 6149.3693 | DE33: =((Labor!$H$20/12)+(Labor!$H$21/12))*(1+$G$33)^7 -> 6149.3693 | DF33: =((Labor!$H$20/12)+(Labor!$H$21/12))*(1+$G$33)^7 -> 6149.3693 | DG33: =((Labor!$H$20/12)+(Labor!$H$21/12))*(1+$G$33)^7 -> 6149.3693 | DH33: =((Labor!$H$20/12)+(Labor!$H$21/12))*(1+$G$33)^7 -> 6149.3693 | DI33: =((Labor!$H$20/12)+(Labor!$H$21/12))*(1+$G$33)^7 -> 6149.3693 | DJ33: =((Labor!$H$20/12)+(Labor!$H$21/12))*(1+$G$33)^7 -> 6149.3693 | ... DN33: =((Labor!$H$20/12)+(Labor!$H$21/12))*(1+$G$33)^7 -> 6149.3693 | DP33: =SUM(J33:DN33) -> 533540.16
E34: ='Table 3.0'!E62 -> Payroll Taxes & Incentives
F35: ='Table 3.0'!F63 -> Payroll Taxes | G35: ='Table 3.0'!G63 -> 0.1 | H35: ='Table 3.0'!H63 -> of Salaries and Wages | W35: =$G$35*SUM(W31:W33) -> 1541.6667 | X35: =$G$35*SUM(X31:X33) -> 1541.6667 | Y35: =$G$35*SUM(Y31:Y33) -> 1541.6667 | Z35: =$G$35*SUM(Z31:Z33) -> 1541.6667 | AA35: =$G$35*SUM(AA31:AA33) -> 1541.6667 | AB35: =$G$35*SUM(AB31:AB33) -> 1541.6667 | AC35: =$G$35*SUM(AC31:AC33) -> 1541.6667 | AD35: =$G$35*SUM(AD31:AD33) -> 1541.6667 | ... DN35: =$G$35*SUM(DN31:DN33) -> 1896.0555 | DP35: =SUM(J35:DN35) -> 164508.22
F36: ='Table 3.0'!F64 -> Payroll Processing Fees | G36: ='Table 3.0'!G64 -> 0.01 | H36: ='Table 3.0'!H64 -> of Salaries and Wages | W36: =$G$36*SUM(W31:W33) -> 154.16667 | X36: =$G$36*SUM(X31:X33) -> 154.16667 | Y36: =$G$36*SUM(Y31:Y33) -> 154.16667 | Z36: =$G$36*SUM(Z31:Z33) -> 154.16667 | AA36: =$G$36*SUM(AA31:AA33) -> 154.16667 | AB36: =$G$36*SUM(AB31:AB33) -> 154.16667 | AC36: =$G$36*SUM(AC31:AC33) -> 154.16667 | AD36: =$G$36*SUM(AD31:AD33) -> 154.16667 | ... DN36: =$G$36*SUM(DN31:DN33) -> 189.60555 | DP36: =SUM(J36:DN36) -> 16450.822
F37: ='Table 3.0'!F65 -> Benefits | G37: ='Table 3.0'!G65 -> 0.01 | H37: ='Table 3.0'!H65 -> of Salaries and Wages | W37: =$G$37*SUM(W31:W33) -> 154.16667 | X37: =$G$37*SUM(X31:X33) -> 154.16667 | Y37: =$G$37*SUM(Y31:Y33) -> 154.16667 | Z37: =$G$37*SUM(Z31:Z33) -> 154.16667 | AA37: =$G$37*SUM(AA31:AA33) -> 154.16667 | AB37: =$G$37*SUM(AB31:AB33) -> 154.16667 | AC37: =$G$37*SUM(AC31:AC33) -> 154.16667 | AD37: =$G$37*SUM(AD31:AD33) -> 154.16667 | ... DN37: =$G$37*SUM(DN31:DN33) -> 189.60555 | DP37: =SUM(J37:DN37) -> 16450.822
D38: ='Table 3.0'!D66 -> Laundry Expenses
E39: ='Table 3.0'!E67 -> Laundry Machine Related Exp. | G39: ='Table 3.0'!G67 -> 0.03 | H39: ='Table 3.0'!H67 -> YoY Growth | W39: 250 | X39: =W39 -> 250 | Y39: =X39 -> 250 | Z39: =Y39 -> 250 | AA39: =Z39 -> 250 | AB39: =AA39 -> 250 | AC39: =AB39 -> 250 | AD39: =AC39 -> 250 | AE39: =AD39 -> 250 | ... AH39: =AG39 -> 250 | AI39: =$W$39*(1+$G$39) -> 257.5 | AJ39: =$W$39*(1+$G$39) -> 257.5 | AK39: =$W$39*(1+$G$39) -> 257.5 | AL39: =$W$39*(1+$G$39) -> 257.5 | AM39: =$W$39*(1+$G$39) -> 257.5 | AN39: =$W$39*(1+$G$39) -> 257.5 | AO39: =$W$39*(1+$G$39) -> 257.5 | AP39: =$W$39*(1+$G$39) -> 257.5 | ... AT39: =$W$39*(1+$G$39) -> 257.5 | AU39: =$W$39*(1+$G$39)^2 -> 265.225 | AV39: =$W$39*(1+$G$39)^2 -> 265.225 | AW39: =$W$39*(1+$G$39)^2 -> 265.225 | AX39: =$W$39*(1+$G$39)^2 -> 265.225 | AY39: =$W$39*(1+$G$39)^2 -> 265.225 | AZ39: =$W$39*(1+$G$39)^2 -> 265.225 | BA39: =$W$39*(1+$G$39)^2 -> 265.225 | BB39: =$W$39*(1+$G$39)^2 -> 265.225 | ... BF39: =$W$39*(1+$G$39)^2 -> 265.225 | BG39: =$W$39*(1+$G$39)^3 -> 273.18175 | BH39: =$W$39*(1+$G$39)^3 -> 273.18175 | BI39: =$W$39*(1+$G$39)^3 -> 273.18175 | BJ39: =$W$39*(1+$G$39)^3 -> 273.18175 | BK39: =$W$39*(1+$G$39)^3 -> 273.18175 | BL39: =$W$39*(1+$G$39)^3 -> 273.18175 | BM39: =$W$39*(1+$G$39)^3 -> 273.18175 | BN39: =$W$39*(1+$G$39)^3 -> 273.18175 | ... BR39: =$W$39*(1+$G$39)^3 -> 273.18175 | BS39: =$W$39*(1+$G$39)^4 -> 281.3772 | BT39: =$W$39*(1+$G$39)^4 -> 281.3772 | BU39: =$W$39*(1+$G$39)^4 -> 281.3772 | BV39: =$W$39*(1+$G$39)^4 -> 281.3772 | BW39: =$W$39*(1+$G$39)^4 -> 281.3772 | BX39: =$W$39*(1+$G$39)^4 -> 281.3772 | BY39: =$W$39*(1+$G$39)^4 -> 281.3772 | BZ39: =$W$39*(1+$G$39)^4 -> 281.3772 | ... CD39: =$W$39*(1+$G$39)^4 -> 281.3772 | CE39: =$W$39*(1+$G$39)^5 -> 289.81852 | CF39: =$W$39*(1+$G$39)^5 -> 289.81852 | CG39: =$W$39*(1+$G$39)^5 -> 289.81852 | CH39: =$W$39*(1+$G$39)^5 -> 289.81852 | CI39: =$W$39*(1+$G$39)^5 -> 289.81852 | CJ39: =$W$39*(1+$G$39)^5 -> 289.81852 | CK39: =$W$39*(1+$G$39)^5 -> 289.81852 | CL39: =$W$39*(1+$G$39)^5 -> 289.81852 | ... CP39: =$W$39*(1+$G$39)^5 -> 289.81852 | CQ39: =$W$39*(1+$G$39)^6 -> 298.51307 | CR39: =$W$39*(1+$G$39)^6 -> 298.51307 | CS39: =$W$39*(1+$G$39)^6 -> 298.51307 | CT39: =$W$39*(1+$G$39)^6 -> 298.51307 | CU39: =$W$39*(1+$G$39)^6 -> 298.51307 | CV39: =$W$39*(1+$G$39)^6 -> 298.51307 | CW39: =$W$39*(1+$G$39)^6 -> 298.51307 | CX39: =$W$39*(1+$G$39)^6 -> 298.51307 | ... DB39: =$W$39*(1+$G$39)^6 -> 298.51307 | DC39: =$W$39*(1+$G$39)^7 -> 307.46847 | DD39: =$W$39*(1+$G$39)^7 -> 307.46847 | DE39: =$W$39*(1+$G$39)^7 -> 307.46847 | DF39: =$W$39*(1+$G$39)^7 -> 307.46847 | DG39: =$W$39*(1+$G$39)^7 -> 307.46847 | DH39: =$W$39*(1+$G$39)^7 -> 307.46847 | DI39: =$W$39*(1+$G$39)^7 -> 307.46847 | DJ39: =$W$39*(1+$G$39)^7 -> 307.46847 | ... DN39: =$W$39*(1+$G$39)^7 -> 307.46847 | DP39: =SUM(J39:DN39) -> 26677.008
E40: ='Table 3.0'!E68 -> Laundry Vending Machine Supplies | G40: ='Table 3.0'!G68 -> 0.03 | H40: ='Table 3.0'!H68 -> YoY Growth | W40: 3500 | X40: =W40 -> 3500 | Y40: =X40 -> 3500 | Z40: =Y40 -> 3500 | AA40: =Z40 -> 3500 | AB40: =AA40 -> 3500 | AC40: =AB40 -> 3500 | AD40: =AC40 -> 3500 | AE40: =AD40 -> 3500 | ... AH40: =AG40 -> 3500 | AI40: =$W$40*(1+$G$40) -> 3605 | AJ40: =$W$40*(1+$G$40) -> 3605 | AK40: =$W$40*(1+$G$40) -> 3605 | AL40: =$W$40*(1+$G$40) -> 3605 | AM40: =$W$40*(1+$G$40) -> 3605 | AN40: =$W$40*(1+$G$40) -> 3605 | AO40: =$W$40*(1+$G$40) -> 3605 | AP40: =$W$40*(1+$G$40) -> 3605 | ... AT40: =$W$40*(1+$G$40) -> 3605 | AU40: =$W$40*(1+$G$40)^2 -> 3713.15 | AV40: =$W$40*(1+$G$40)^2 -> 3713.15 | AW40: =$W$40*(1+$G$40)^2 -> 3713.15 | AX40: =$W$40*(1+$G$40)^2 -> 3713.15 | AY40: =$W$40*(1+$G$40)^2 -> 3713.15 | AZ40: =$W$40*(1+$G$40)^2 -> 3713.15 | BA40: =$W$40*(1+$G$40)^2 -> 3713.15 | BB40: =$W$40*(1+$G$40)^2 -> 3713.15 | ... BF40: =$W$40*(1+$G$40)^2 -> 3713.15 | BG40: =$W$40*(1+$G$40)^3 -> 3824.5445 | BH40: =$W$40*(1+$G$40)^3 -> 3824.5445 | BI40: =$W$40*(1+$G$40)^3 -> 3824.5445 | BJ40: =$W$40*(1+$G$40)^3 -> 3824.5445 | BK40: =$W$40*(1+$G$40)^3 -> 3824.5445 | BL40: =$W$40*(1+$G$40)^3 -> 3824.5445 | BM40: =$W$40*(1+$G$40)^3 -> 3824.5445 | BN40: =$W$40*(1+$G$40)^3 -> 3824.5445 | ... BR40: =$W$40*(1+$G$40)^3 -> 3824.5445 | BS40: =$W$40*(1+$G$40)^4 -> 3939.2808 | BT40: =$W$40*(1+$G$40)^4 -> 3939.2808 | BU40: =$W$40*(1+$G$40)^4 -> 3939.2808 | BV40: =$W$40*(1+$G$40)^4 -> 3939.2808 | BW40: =$W$40*(1+$G$40)^4 -> 3939.2808 | BX40: =$W$40*(1+$G$40)^4 -> 3939.2808 | BY40: =$W$40*(1+$G$40)^4 -> 3939.2808 | BZ40: =$W$40*(1+$G$40)^4 -> 3939.2808 | ... CD40: =$W$40*(1+$G$40)^4 -> 3939.2808 | CE40: =$W$40*(1+$G$40)^5 -> 4057.4593 | CF40: =$W$40*(1+$G$40)^5 -> 4057.4593 | CG40: =$W$40*(1+$G$40)^5 -> 4057.4593 | CH40: =$W$40*(1+$G$40)^5 -> 4057.4593 | CI40: =$W$40*(1+$G$40)^5 -> 4057.4593 | CJ40: =$W$40*(1+$G$40)^5 -> 4057.4593 | CK40: =$W$40*(1+$G$40)^5 -> 4057.4593 | CL40: =$W$40*(1+$G$40)^5 -> 4057.4593 | ... CP40: =$W$40*(1+$G$40)^5 -> 4057.4593 | CQ40: =$W$40*(1+$G$40)^6 -> 4179.183 | CR40: =$W$40*(1+$G$40)^6 -> 4179.183 | CS40: =$W$40*(1+$G$40)^6 -> 4179.183 | CT40: =$W$40*(1+$G$40)^6 -> 4179.183 | CU40: =$W$40*(1+$G$40)^6 -> 4179.183 | CV40: =$W$40*(1+$G$40)^6 -> 4179.183 | CW40: =$W$40*(1+$G$40)^6 -> 4179.183 | CX40: =$W$40*(1+$G$40)^6 -> 4179.183 | ... DB40: =$W$40*(1+$G$40)^6 -> 4179.183 | DC40: =$W$40*(1+$G$40)^7 -> 4304.5585 | DD40: =$W$40*(1+$G$40)^7 -> 4304.5585 | DE40: =$W$40*(1+$G$40)^7 -> 4304.5585 | DF40: =$W$40*(1+$G$40)^7 -> 4304.5585 | DG40: =$W$40*(1+$G$40)^7 -> 4304.5585 | DH40: =$W$40*(1+$G$40)^7 -> 4304.5585 | DI40: =$W$40*(1+$G$40)^7 -> 4304.5585 | DJ40: =$W$40*(1+$G$40)^7 -> 4304.5585 | ... DN40: =$W$40*(1+$G$40)^7 -> 4304.5585 | DP40: =SUM(J40:DN40) -> 373478.11
D41: ='Table 3.0'!D69 -> Retail Expenses
E42: ='Table 3.0'!E70 -> Convenience Store/Vending Supplies | G42: ='Table 3.0'!G70 -> 0.03 | H42: ='Table 3.0'!H70 -> YoY Growth | W42: 3500 | X42: =W42 -> 3500 | Y42: =X42 -> 3500 | Z42: =Y42 -> 3500 | AA42: =Z42 -> 3500 | AB42: =AA42 -> 3500 | AC42: =AB42 -> 3500 | AD42: =AC42 -> 3500 | AE42: =AD42 -> 3500 | ... AH42: =AG42 -> 3500 | AI42: =$W$42*(1+$G$42) -> 3605 | AJ42: =$W$42*(1+$G$42) -> 3605 | AK42: =$W$42*(1+$G$42) -> 3605 | AL42: =$W$42*(1+$G$42) -> 3605 | AM42: =$W$42*(1+$G$42) -> 3605 | AN42: =$W$42*(1+$G$42) -> 3605 | AO42: =$W$42*(1+$G$42) -> 3605 | AP42: =$W$42*(1+$G$42) -> 3605 | ... AT42: =$W$42*(1+$G$42) -> 3605 | AU42: =$W$42*(1+$G$42)^2 -> 3713.15 | AV42: =$W$42*(1+$G$42)^2 -> 3713.15 | AW42: =$W$42*(1+$G$42)^2 -> 3713.15 | AX42: =$W$42*(1+$G$42)^2 -> 3713.15 | AY42: =$W$42*(1+$G$42)^2 -> 3713.15 | AZ42: =$W$42*(1+$G$42)^2 -> 3713.15 | BA42: =$W$42*(1+$G$42)^2 -> 3713.15 | BB42: =$W$42*(1+$G$42)^2 -> 3713.15 | ... BF42: =$W$42*(1+$G$42)^2 -> 3713.15 | BG42: =$W$42*(1+$G$42)^3 -> 3824.5445 | BH42: =$W$42*(1+$G$42)^3 -> 3824.5445 | BI42: =$W$42*(1+$G$42)^3 -> 3824.5445 | BJ42: =$W$42*(1+$G$42)^3 -> 3824.5445 | BK42: =$W$42*(1+$G$42)^3 -> 3824.5445 | BL42: =$W$42*(1+$G$42)^3 -> 3824.5445 | BM42: =$W$42*(1+$G$42)^3 -> 3824.5445 | BN42: =$W$42*(1+$G$42)^3 -> 3824.5445 | ... BR42: =$W$42*(1+$G$42)^3 -> 3824.5445 | BS42: =$W$42*(1+$G$42)^4 -> 3939.2808 | BT42: =$W$42*(1+$G$42)^4 -> 3939.2808 | BU42: =$W$42*(1+$G$42)^4 -> 3939.2808 | BV42: =$W$42*(1+$G$42)^4 -> 3939.2808 | BW42: =$W$42*(1+$G$42)^4 -> 3939.2808 | BX42: =$W$42*(1+$G$42)^4 -> 3939.2808 | BY42: =$W$42*(1+$G$42)^4 -> 3939.2808 | BZ42: =$W$42*(1+$G$42)^4 -> 3939.2808 | ... CD42: =$W$42*(1+$G$42)^4 -> 3939.2808 | CE42: =$W$42*(1+$G$42)^5 -> 4057.4593 | CF42: =$W$42*(1+$G$42)^5 -> 4057.4593 | CG42: =$W$42*(1+$G$42)^5 -> 4057.4593 | CH42: =$W$42*(1+$G$42)^5 -> 4057.4593 | CI42: =$W$42*(1+$G$42)^5 -> 4057.4593 | CJ42: =$W$42*(1+$G$42)^5 -> 4057.4593 | CK42: =$W$42*(1+$G$42)^5 -> 4057.4593 | CL42: =$W$42*(1+$G$42)^5 -> 4057.4593 | ... CP42: =$W$42*(1+$G$42)^5 -> 4057.4593 | CQ42: =$W$42*(1+$G$42)^6 -> 4179.183 | CR42: =$W$42*(1+$G$42)^6 -> 4179.183 | CS42: =$W$42*(1+$G$42)^6 -> 4179.183 | CT42: =$W$42*(1+$G$42)^6 -> 4179.183 | CU42: =$W$42*(1+$G$42)^6 -> 4179.183 | CV42: =$W$42*(1+$G$42)^6 -> 4179.183 | CW42: =$W$42*(1+$G$42)^6 -> 4179.183 | CX42: =$W$42*(1+$G$42)^6 -> 4179.183 | ... DB42: =$W$42*(1+$G$42)^6 -> 4179.183 | DC42: =$W$42*(1+$G$42)^7 -> 4304.5585 | DD42: =$W$42*(1+$G$42)^7 -> 4304.5585 | DE42: =$W$42*(1+$G$42)^7 -> 4304.5585 | DF42: =$W$42*(1+$G$42)^7 -> 4304.5585 | DG42: =$W$42*(1+$G$42)^7 -> 4304.5585 | DH42: =$W$42*(1+$G$42)^7 -> 4304.5585 | DI42: =$W$42*(1+$G$42)^7 -> 4304.5585 | DJ42: =$W$42*(1+$G$42)^7 -> 4304.5585 | ... DN42: =$W$42*(1+$G$42)^7 -> 4304.5585 | DP42: =SUM(J42:DN42) -> 373478.11
D43: ='Table 3.0'!D71 -> Total Departmental Expenses | K43: =SUM(K29:K42) -> 0 | L43: =SUM(L29:L42) -> 0 | M43: =SUM(M29:M42) -> 0 | N43: =SUM(N29:N42) -> 0 | O43: =SUM(O29:O42) -> 0 | P43: =SUM(P29:P42) -> 0 | Q43: =SUM(Q29:Q42) -> 0 | R43: =SUM(R29:R42) -> 0 | ... DN43: =SUM(DN29:DN42) -> 30152.408 | DP43: =SUM(J43:DN43) -> 2616125.3
C45: ='Table 3.0'!C73 -> UNDISTRIBUTED OPERATING EXPENSES
D46: ='Table 3.0'!D74 -> Administrative & General
E47: ='Table 3.0'!E75 -> Accounting | G47: ='Table 3.0'!G75 -> 0.03 | H47: ='Table 3.0'!H75 -> YoY Growth | W47: 250 | X47: =W47 -> 250 | Y47: =X47 -> 250 | Z47: =Y47 -> 250 | AA47: =Z47 -> 250 | AB47: =AA47 -> 250 | AC47: =AB47 -> 250 | AD47: =AC47 -> 250 | AE47: =AD47 -> 250 | ... AH47: =AG47 -> 250 | AI47: =$W$47*(1+$G$47) -> 257.5 | AJ47: =$W$47*(1+$G$47) -> 257.5 | AK47: =$W$47*(1+$G$47) -> 257.5 | AL47: =$W$47*(1+$G$47) -> 257.5 | AM47: =$W$47*(1+$G$47) -> 257.5 | AN47: =$W$47*(1+$G$47) -> 257.5 | AO47: =$W$47*(1+$G$47) -> 257.5 | AP47: =$W$47*(1+$G$47) -> 257.5 | ... AT47: =$W$47*(1+$G$47) -> 257.5 | AU47: =$W$47*(1+$G$47)^2 -> 265.225 | AV47: =$W$47*(1+$G$47)^2 -> 265.225 | AW47: =$W$47*(1+$G$47)^2 -> 265.225 | AX47: =$W$47*(1+$G$47)^2 -> 265.225 | AY47: =$W$47*(1+$G$47)^2 -> 265.225 | AZ47: =$W$47*(1+$G$47)^2 -> 265.225 | BA47: =$W$47*(1+$G$47)^2 -> 265.225 | BB47: =$W$47*(1+$G$47)^2 -> 265.225 | ... BF47: =$W$47*(1+$G$47)^2 -> 265.225 | BG47: =$W$47*(1+$G$47)^3 -> 273.18175 | BH47: =$W$47*(1+$G$47)^3 -> 273.18175 | BI47: =$W$47*(1+$G$47)^3 -> 273.18175 | BJ47: =$W$47*(1+$G$47)^3 -> 273.18175 | BK47: =$W$47*(1+$G$47)^3 -> 273.18175 | BL47: =$W$47*(1+$G$47)^3 -> 273.18175 | BM47: =$W$47*(1+$G$47)^3 -> 273.18175 | BN47: =$W$47*(1+$G$47)^3 -> 273.18175 | ... BR47: =$W$47*(1+$G$47)^3 -> 273.18175 | BS47: =$W$47*(1+$G$47)^4 -> 281.3772 | BT47: =$W$47*(1+$G$47)^4 -> 281.3772 | BU47: =$W$47*(1+$G$47)^4 -> 281.3772 | BV47: =$W$47*(1+$G$47)^4 -> 281.3772 | BW47: =$W$47*(1+$G$47)^4 -> 281.3772 | BX47: =$W$47*(1+$G$47)^4 -> 281.3772 | BY47: =$W$47*(1+$G$47)^4 -> 281.3772 | BZ47: =$W$47*(1+$G$47)^4 -> 281.3772 | ... CD47: =$W$47*(1+$G$47)^4 -> 281.3772 | CE47: =$W$47*(1+$G$47)^5 -> 289.81852 | CF47: =$W$47*(1+$G$47)^5 -> 289.81852 | CG47: =$W$47*(1+$G$47)^5 -> 289.81852 | CH47: =$W$47*(1+$G$47)^5 -> 289.81852 | CI47: =$W$47*(1+$G$47)^5 -> 289.81852 | CJ47: =$W$47*(1+$G$47)^5 -> 289.81852 | CK47: =$W$47*(1+$G$47)^5 -> 289.81852 | CL47: =$W$47*(1+$G$47)^5 -> 289.81852 | ... CP47: =$W$47*(1+$G$47)^5 -> 289.81852 | CQ47: =$W$47*(1+$G$47)^6 -> 298.51307 | CR47: =$W$47*(1+$G$47)^6 -> 298.51307 | CS47: =$W$47*(1+$G$47)^6 -> 298.51307 | CT47: =$W$47*(1+$G$47)^6 -> 298.51307 | CU47: =$W$47*(1+$G$47)^6 -> 298.51307 | CV47: =$W$47*(1+$G$47)^6 -> 298.51307 | CW47: =$W$47*(1+$G$47)^6 -> 298.51307 | CX47: =$W$47*(1+$G$47)^6 -> 298.51307 | ... DB47: =$W$47*(1+$G$47)^6 -> 298.51307 | DC47: =$W$47*(1+$G$47)^7 -> 307.46847 | DD47: =$W$47*(1+$G$47)^7 -> 307.46847 | DE47: =$W$47*(1+$G$47)^7 -> 307.46847 | DF47: =$W$47*(1+$G$47)^7 -> 307.46847 | DG47: =$W$47*(1+$G$47)^7 -> 307.46847 | DH47: =$W$47*(1+$G$47)^7 -> 307.46847 | DI47: =$W$47*(1+$G$47)^7 -> 307.46847 | DJ47: =$W$47*(1+$G$47)^7 -> 307.46847 | ... DN47: =$W$47*(1+$G$47)^7 -> 307.46847 | DP47: =SUM(J47:DN47) -> 26677.008
E48: ='Table 3.0'!E76 -> Legal | G48: ='Table 3.0'!G76 -> 0.03 | H48: ='Table 3.0'!H76 -> YoY Growth | W48: 250 | X48: =W48 -> 250 | Y48: =X48 -> 250 | Z48: =Y48 -> 250 | AA48: =Z48 -> 250 | AB48: =AA48 -> 250 | AC48: =AB48 -> 250 | AD48: =AC48 -> 250 | AE48: =AD48 -> 250 | ... AH48: =AG48 -> 250 | AI48: =$W$48*(1+$G$48) -> 257.5 | AJ48: =$W$48*(1+$G$48) -> 257.5 | AK48: =$W$48*(1+$G$48) -> 257.5 | AL48: =$W$48*(1+$G$48) -> 257.5 | AM48: =$W$48*(1+$G$48) -> 257.5 | AN48: =$W$48*(1+$G$48) -> 257.5 | AO48: =$W$48*(1+$G$48) -> 257.5 | AP48: =$W$48*(1+$G$48) -> 257.5 | ... AT48: =$W$48*(1+$G$48) -> 257.5 | AU48: =$W$48*(1+$G$48)^2 -> 265.225 | AV48: =$W$48*(1+$G$48)^2 -> 265.225 | AW48: =$W$48*(1+$G$48)^2 -> 265.225 | AX48: =$W$48*(1+$G$48)^2 -> 265.225 | AY48: =$W$48*(1+$G$48)^2 -> 265.225 | AZ48: =$W$48*(1+$G$48)^2 -> 265.225 | BA48: =$W$48*(1+$G$48)^2 -> 265.225 | BB48: =$W$48*(1+$G$48)^2 -> 265.225 | ... BF48: =$W$48*(1+$G$48)^2 -> 265.225 | BG48: =$W$48*(1+$G$48)^3 -> 273.18175 | BH48: =$W$48*(1+$G$48)^3 -> 273.18175 | BI48: =$W$48*(1+$G$48)^3 -> 273.18175 | BJ48: =$W$48*(1+$G$48)^3 -> 273.18175 | BK48: =$W$48*(1+$G$48)^3 -> 273.18175 | BL48: =$W$48*(1+$G$48)^3 -> 273.18175 | BM48: =$W$48*(1+$G$48)^3 -> 273.18175 | BN48: =$W$48*(1+$G$48)^3 -> 273.18175 | ... BR48: =$W$48*(1+$G$48)^3 -> 273.18175 | BS48: =$W$48*(1+$G$48)^4 -> 281.3772 | BT48: =$W$48*(1+$G$48)^4 -> 281.3772 | BU48: =$W$48*(1+$G$48)^4 -> 281.3772 | BV48: =$W$48*(1+$G$48)^4 -> 281.3772 | BW48: =$W$48*(1+$G$48)^4 -> 281.3772 | BX48: =$W$48*(1+$G$48)^4 -> 281.3772 | BY48: =$W$48*(1+$G$48)^4 -> 281.3772 | BZ48: =$W$48*(1+$G$48)^4 -> 281.3772 | ... CD48: =$W$48*(1+$G$48)^4 -> 281.3772 | CE48: =$W$48*(1+$G$48)^5 -> 289.81852 | CF48: =$W$48*(1+$G$48)^5 -> 289.81852 | CG48: =$W$48*(1+$G$48)^5 -> 289.81852 | CH48: =$W$48*(1+$G$48)^5 -> 289.81852 | CI48: =$W$48*(1+$G$48)^5 -> 289.81852 | CJ48: =$W$48*(1+$G$48)^5 -> 289.81852 | CK48: =$W$48*(1+$G$48)^5 -> 289.81852 | CL48: =$W$48*(1+$G$48)^5 -> 289.81852 | ... CP48: =$W$48*(1+$G$48)^5 -> 289.81852 | CQ48: =$W$48*(1+$G$48)^6 -> 298.51307 | CR48: =$W$48*(1+$G$48)^6 -> 298.51307 | CS48: =$W$48*(1+$G$48)^6 -> 298.51307 | CT48: =$W$48*(1+$G$48)^6 -> 298.51307 | CU48: =$W$48*(1+$G$48)^6 -> 298.51307 | CV48: =$W$48*(1+$G$48)^6 -> 298.51307 | CW48: =$W$48*(1+$G$48)^6 -> 298.51307 | CX48: =$W$48*(1+$G$48)^6 -> 298.51307 | ... DB48: =$W$48*(1+$G$48)^6 -> 298.51307 | DC48: =$W$48*(1+$G$48)^7 -> 307.46847 | DD48: =$W$48*(1+$G$48)^7 -> 307.46847 | DE48: =$W$48*(1+$G$48)^7 -> 307.46847 | DF48: =$W$48*(1+$G$48)^7 -> 307.46847 | DG48: =$W$48*(1+$G$48)^7 -> 307.46847 | DH48: =$W$48*(1+$G$48)^7 -> 307.46847 | DI48: =$W$48*(1+$G$48)^7 -> 307.46847 | DJ48: =$W$48*(1+$G$48)^7 -> 307.46847 | ... DN48: =$W$48*(1+$G$48)^7 -> 307.46847 | DP48: =SUM(J48:DN48) -> 26677.008
E49: ='Table 3.0'!E77 -> Misc. | G49: ='Table 3.0'!G77 -> 0.03 | H49: ='Table 3.0'!H77 -> YoY Growth | W49: 250 | X49: =W49 -> 250 | Y49: =X49 -> 250 | Z49: =Y49 -> 250 | AA49: =Z49 -> 250 | AB49: =AA49 -> 250 | AC49: =AB49 -> 250 | AD49: =AC49 -> 250 | AE49: =AD49 -> 250 | ... AH49: =AG49 -> 250 | AI49: =$W$49*(1+$G$49) -> 257.5 | AJ49: =$W$49*(1+$G$49) -> 257.5 | AK49: =$W$49*(1+$G$49) -> 257.5 | AL49: =$W$49*(1+$G$49) -> 257.5 | AM49: =$W$49*(1+$G$49) -> 257.5 | AN49: =$W$49*(1+$G$49) -> 257.5 | AO49: =$W$49*(1+$G$49) -> 257.5 | AP49: =$W$49*(1+$G$49) -> 257.5 | ... AT49: =$W$49*(1+$G$49) -> 257.5 | AU49: =$W$49*(1+$G$49)^2 -> 265.225 | AV49: =$W$49*(1+$G$49)^2 -> 265.225 | AW49: =$W$49*(1+$G$49)^2 -> 265.225 | AX49: =$W$49*(1+$G$49)^2 -> 265.225 | AY49: =$W$49*(1+$G$49)^2 -> 265.225 | AZ49: =$W$49*(1+$G$49)^2 -> 265.225 | BA49: =$W$49*(1+$G$49)^2 -> 265.225 | BB49: =$W$49*(1+$G$49)^2 -> 265.225 | ... BF49: =$W$49*(1+$G$49)^2 -> 265.225 | BG49: =$W$49*(1+$G$49)^3 -> 273.18175 | BH49: =$W$49*(1+$G$49)^3 -> 273.18175 | BI49: =$W$49*(1+$G$49)^3 -> 273.18175 | BJ49: =$W$49*(1+$G$49)^3 -> 273.18175 | BK49: =$W$49*(1+$G$49)^3 -> 273.18175 | BL49: =$W$49*(1+$G$49)^3 -> 273.18175 | BM49: =$W$49*(1+$G$49)^3 -> 273.18175 | BN49: =$W$49*(1+$G$49)^3 -> 273.18175 | ... BR49: =$W$49*(1+$G$49)^3 -> 273.18175 | BS49: =$W$49*(1+$G$49)^4 -> 281.3772 | BT49: =$W$49*(1+$G$49)^4 -> 281.3772 | BU49: =$W$49*(1+$G$49)^4 -> 281.3772 | BV49: =$W$49*(1+$G$49)^4 -> 281.3772 | BW49: =$W$49*(1+$G$49)^4 -> 281.3772 | BX49: =$W$49*(1+$G$49)^4 -> 281.3772 | BY49: =$W$49*(1+$G$49)^4 -> 281.3772 | BZ49: =$W$49*(1+$G$49)^4 -> 281.3772 | ... CD49: =$W$49*(1+$G$49)^4 -> 281.3772 | CE49: =$W$49*(1+$G$49)^5 -> 289.81852 | CF49: =$W$49*(1+$G$49)^5 -> 289.81852 | CG49: =$W$49*(1+$G$49)^5 -> 289.81852 | CH49: =$W$49*(1+$G$49)^5 -> 289.81852 | CI49: =$W$49*(1+$G$49)^5 -> 289.81852 | CJ49: =$W$49*(1+$G$49)^5 -> 289.81852 | CK49: =$W$49*(1+$G$49)^5 -> 289.81852 | CL49: =$W$49*(1+$G$49)^5 -> 289.81852 | ... CP49: =$W$49*(1+$G$49)^5 -> 289.81852 | CQ49: =$W$49*(1+$G$49)^6 -> 298.51307 | CR49: =$W$49*(1+$G$49)^6 -> 298.51307 | CS49: =$W$49*(1+$G$49)^6 -> 298.51307 | CT49: =$W$49*(1+$G$49)^6 -> 298.51307 | CU49: =$W$49*(1+$G$49)^6 -> 298.51307 | CV49: =$W$49*(1+$G$49)^6 -> 298.51307 | CW49: =$W$49*(1+$G$49)^6 -> 298.51307 | CX49: =$W$49*(1+$G$49)^6 -> 298.51307 | ... DB49: =$W$49*(1+$G$49)^6 -> 298.51307 | DC49: =$W$49*(1+$G$49)^7 -> 307.46847 | DD49: =$W$49*(1+$G$49)^7 -> 307.46847 | DE49: =$W$49*(1+$G$49)^7 -> 307.46847 | DF49: =$W$49*(1+$G$49)^7 -> 307.46847 | DG49: =$W$49*(1+$G$49)^7 -> 307.46847 | DH49: =$W$49*(1+$G$49)^7 -> 307.46847 | DI49: =$W$49*(1+$G$49)^7 -> 307.46847 | DJ49: =$W$49*(1+$G$49)^7 -> 307.46847 | ... DN49: =$W$49*(1+$G$49)^7 -> 307.46847 | DP49: =SUM(J49:DN49) -> 26677.008
E50: ='Table 3.0'!E78 -> Bank Fees | G50: ='Table 3.0'!G78 -> 0.03 | H50: ='Table 3.0'!H78 -> YoY Growth | W50: 500 | X50: =W50 -> 500 | Y50: =X50 -> 500 | Z50: =Y50 -> 500 | AA50: =Z50 -> 500 | AB50: =AA50 -> 500 | AC50: =AB50 -> 500 | AD50: =AC50 -> 500 | AE50: =AD50 -> 500 | ... AH50: =AG50 -> 500 | AI50: =$W$50*(1+$G$50) -> 515 | AJ50: =$W$50*(1+$G$50) -> 515 | AK50: =$W$50*(1+$G$50) -> 515 | AL50: =$W$50*(1+$G$50) -> 515 | AM50: =$W$50*(1+$G$50) -> 515 | AN50: =$W$50*(1+$G$50) -> 515 | AO50: =$W$50*(1+$G$50) -> 515 | AP50: =$W$50*(1+$G$50) -> 515 | ... AT50: =$W$50*(1+$G$50) -> 515 | AU50: =$W$50*(1+$G$50)^2 -> 530.45 | AV50: =$W$50*(1+$G$50)^2 -> 530.45 | AW50: =$W$50*(1+$G$50)^2 -> 530.45 | AX50: =$W$50*(1+$G$50)^2 -> 530.45 | AY50: =$W$50*(1+$G$50)^2 -> 530.45 | AZ50: =$W$50*(1+$G$50)^2 -> 530.45 | BA50: =$W$50*(1+$G$50)^2 -> 530.45 | BB50: =$W$50*(1+$G$50)^2 -> 530.45 | ... BF50: =$W$50*(1+$G$50)^2 -> 530.45 | BG50: =$W$50*(1+$G$50)^3 -> 546.3635 | BH50: =$W$50*(1+$G$50)^3 -> 546.3635 | BI50: =$W$50*(1+$G$50)^3 -> 546.3635 | BJ50: =$W$50*(1+$G$50)^3 -> 546.3635 | BK50: =$W$50*(1+$G$50)^3 -> 546.3635 | BL50: =$W$50*(1+$G$50)^3 -> 546.3635 | BM50: =$W$50*(1+$G$50)^3 -> 546.3635 | BN50: =$W$50*(1+$G$50)^3 -> 546.3635 | ... BR50: =$W$50*(1+$G$50)^3 -> 546.3635 | BS50: =$W$50*(1+$G$50)^4 -> 562.7544 | BT50: =$W$50*(1+$G$50)^4 -> 562.7544 | BU50: =$W$50*(1+$G$50)^4 -> 562.7544 | BV50: =$W$50*(1+$G$50)^4 -> 562.7544 | BW50: =$W$50*(1+$G$50)^4 -> 562.7544 | BX50: =$W$50*(1+$G$50)^4 -> 562.7544 | BY50: =$W$50*(1+$G$50)^4 -> 562.7544 | BZ50: =$W$50*(1+$G$50)^4 -> 562.7544 | ... CD50: =$W$50*(1+$G$50)^4 -> 562.7544 | CE50: =$W$50*(1+$G$50)^5 -> 579.63704 | CF50: =$W$50*(1+$G$50)^5 -> 579.63704 | CG50: =$W$50*(1+$G$50)^5 -> 579.63704 | CH50: =$W$50*(1+$G$50)^5 -> 579.63704 | CI50: =$W$50*(1+$G$50)^5 -> 579.63704 | CJ50: =$W$50*(1+$G$50)^5 -> 579.63704 | CK50: =$W$50*(1+$G$50)^5 -> 579.63704 | CL50: =$W$50*(1+$G$50)^5 -> 579.63704 | ... CP50: =$W$50*(1+$G$50)^5 -> 579.63704 | CQ50: =$W$50*(1+$G$50)^6 -> 597.02615 | CR50: =$W$50*(1+$G$50)^6 -> 597.02615 | CS50: =$W$50*(1+$G$50)^6 -> 597.02615 | CT50: =$W$50*(1+$G$50)^6 -> 597.02615 | CU50: =$W$50*(1+$G$50)^6 -> 597.02615 | CV50: =$W$50*(1+$G$50)^6 -> 597.02615 | CW50: =$W$50*(1+$G$50)^6 -> 597.02615 | CX50: =$W$50*(1+$G$50)^6 -> 597.02615 | ... DB50: =$W$50*(1+$G$50)^6 -> 597.02615 | DC50: =$W$50*(1+$G$50)^7 -> 614.93693 | DD50: =$W$50*(1+$G$50)^7 -> 614.93693 | DE50: =$W$50*(1+$G$50)^7 -> 614.93693 | DF50: =$W$50*(1+$G$50)^7 -> 614.93693 | DG50: =$W$50*(1+$G$50)^7 -> 614.93693 | DH50: =$W$50*(1+$G$50)^7 -> 614.93693 | DI50: =$W$50*(1+$G$50)^7 -> 614.93693 | DJ50: =$W$50*(1+$G$50)^7 -> 614.93693 | ... DN50: =$W$50*(1+$G$50)^7 -> 614.93693 | DP50: =SUM(J50:DN50) -> 53354.016
E51: ='Table 3.0'!E79 -> CC Processing | G51: ='Table 3.0'!G79 -> 0.03 | H51: ='Table 3.0'!H79 -> of Revenue | W51: =$G$51*W26 -> 1818.165 | X51: =$G$51*X26 -> 1890.105 | Y51: =$G$51*Y26 -> 1995.645 | Z51: =$G$51*Z26 -> 1995.645 | AA51: =$G$51*AA26 -> 1934.475 | AB51: =$G$51*AB26 -> 1906.905 | AC51: =$G$51*AC26 -> 1801.365 | AD51: =$G$51*AD26 -> 1729.425 | ... DN51: =$G$51*DN26 -> 2132.79 | DP51: =SUM(J51:DN51) -> 192879.48
D52: ='Table 3.0'!D80 -> Office & Software
E53: ='Table 3.0'!E81 -> Software Expense | G53: ='Table 3.0'!G81 -> 0.03 | H53: YoY Growth | W53: 210 | X53: =W53 -> 210 | Y53: =X53 -> 210 | Z53: =Y53 -> 210 | AA53: =Z53 -> 210 | AB53: =AA53 -> 210 | AC53: =AB53 -> 210 | AD53: =AC53 -> 210 | AE53: =AD53 -> 210 | ... AH53: =AG53 -> 210 | AI53: =$W$53*(1+$G$53) -> 216.3 | AJ53: =$W$53*(1+$G$53) -> 216.3 | AK53: =$W$53*(1+$G$53) -> 216.3 | AL53: =$W$53*(1+$G$53) -> 216.3 | AM53: =$W$53*(1+$G$53) -> 216.3 | AN53: =$W$53*(1+$G$53) -> 216.3 | AO53: =$W$53*(1+$G$53) -> 216.3 | AP53: =$W$53*(1+$G$53) -> 216.3 | ... AT53: =$W$53*(1+$G$53) -> 216.3 | AU53: =$W$53*(1+$G$53)^2 -> 222.789 | AV53: =$W$53*(1+$G$53)^2 -> 222.789 | AW53: =$W$53*(1+$G$53)^2 -> 222.789 | AX53: =$W$53*(1+$G$53)^2 -> 222.789 | AY53: =$W$53*(1+$G$53)^2 -> 222.789 | AZ53: =$W$53*(1+$G$53)^2 -> 222.789 | BA53: =$W$53*(1+$G$53)^2 -> 222.789 | BB53: =$W$53*(1+$G$53)^2 -> 222.789 | ... BF53: =$W$53*(1+$G$53)^2 -> 222.789 | BG53: =$W$53*(1+$G$53)^3 -> 229.47267 | BH53: =$W$53*(1+$G$53)^3 -> 229.47267 | BI53: =$W$53*(1+$G$53)^3 -> 229.47267 | BJ53: =$W$53*(1+$G$53)^3 -> 229.47267 | BK53: =$W$53*(1+$G$53)^3 -> 229.47267 | BL53: =$W$53*(1+$G$53)^3 -> 229.47267 | BM53: =$W$53*(1+$G$53)^3 -> 229.47267 | BN53: =$W$53*(1+$G$53)^3 -> 229.47267 | ... BR53: =$W$53*(1+$G$53)^3 -> 229.47267 | BS53: =$W$53*(1+$G$53)^4 -> 236.35685 | BT53: =$W$53*(1+$G$53)^4 -> 236.35685 | BU53: =$W$53*(1+$G$53)^4 -> 236.35685 | BV53: =$W$53*(1+$G$53)^4 -> 236.35685 | BW53: =$W$53*(1+$G$53)^4 -> 236.35685 | BX53: =$W$53*(1+$G$53)^4 -> 236.35685 | BY53: =$W$53*(1+$G$53)^4 -> 236.35685 | BZ53: =$W$53*(1+$G$53)^4 -> 236.35685 | ... CD53: =$W$53*(1+$G$53)^4 -> 236.35685 | CE53: =$W$53*(1+$G$53)^5 -> 243.44756 | CF53: =$W$53*(1+$G$53)^5 -> 243.44756 | CG53: =$W$53*(1+$G$53)^5 -> 243.44756 | CH53: =$W$53*(1+$G$53)^5 -> 243.44756 | CI53: =$W$53*(1+$G$53)^5 -> 243.44756 | CJ53: =$W$53*(1+$G$53)^5 -> 243.44756 | CK53: =$W$53*(1+$G$53)^5 -> 243.44756 | CL53: =$W$53*(1+$G$53)^5 -> 243.44756 | ... CP53: =$W$53*(1+$G$53)^5 -> 243.44756 | CQ53: =$W$53*(1+$G$53)^6 -> 250.75098 | CR53: =$W$53*(1+$G$53)^6 -> 250.75098 | CS53: =$W$53*(1+$G$53)^6 -> 250.75098 | CT53: =$W$53*(1+$G$53)^6 -> 250.75098 | CU53: =$W$53*(1+$G$53)^6 -> 250.75098 | CV53: =$W$53*(1+$G$53)^6 -> 250.75098 | CW53: =$W$53*(1+$G$53)^6 -> 250.75098 | CX53: =$W$53*(1+$G$53)^6 -> 250.75098 | ... DB53: =$W$53*(1+$G$53)^6 -> 250.75098 | DC53: =$W$53*(1+$G$53)^7 -> 258.27351 | DD53: =$W$53*(1+$G$53)^7 -> 258.27351 | DE53: =$W$53*(1+$G$53)^7 -> 258.27351 | DF53: =$W$53*(1+$G$53)^7 -> 258.27351 | DG53: =$W$53*(1+$G$53)^7 -> 258.27351 | DH53: =$W$53*(1+$G$53)^7 -> 258.27351 | DI53: =$W$53*(1+$G$53)^7 -> 258.27351 | DJ53: =$W$53*(1+$G$53)^7 -> 258.27351 | ... DN53: =$W$53*(1+$G$53)^7 -> 258.27351 | DP53: =SUM(J53:DN53) -> 22408.687
D54: ='Table 3.0'!D82 -> Sales & Marketing
E55: ='Table 3.0'!E83 -> Digital Marketing | G55: ='Table 3.0'!G83 -> 0.03 | H55: YoY Growth | T55: 5000 | U55: 250 | V55: =U55 -> 250 | W55: =V55 -> 250 | X55: =W55 -> 250 | Y55: =X55 -> 250 | Z55: =Y55 -> 250 | AA55: =Z55 -> 250 | AB55: =AA55 -> 250 | AC55: =AB55 -> 250 | ... AH55: =AG55 -> 250 | AI55: =$W$55*(1+$G$55) -> 257.5 | AJ55: =$W$55*(1+$G$55) -> 257.5 | AK55: =$W$55*(1+$G$55) -> 257.5 | AL55: =$W$55*(1+$G$55) -> 257.5 | AM55: =$W$55*(1+$G$55) -> 257.5 | AN55: =$W$55*(1+$G$55) -> 257.5 | AO55: =$W$55*(1+$G$55) -> 257.5 | AP55: =$W$55*(1+$G$55) -> 257.5 | ... AT55: =$W$55*(1+$G$55) -> 257.5 | AU55: =$W$55*(1+$G$55)^2 -> 265.225 | AV55: =$W$55*(1+$G$55)^2 -> 265.225 | AW55: =$W$55*(1+$G$55)^2 -> 265.225 | AX55: =$W$55*(1+$G$55)^2 -> 265.225 | AY55: =$W$55*(1+$G$55)^2 -> 265.225 | AZ55: =$W$55*(1+$G$55)^2 -> 265.225 | BA55: =$W$55*(1+$G$55)^2 -> 265.225 | BB55: =$W$55*(1+$G$55)^2 -> 265.225 | ... BF55: =$W$55*(1+$G$55)^2 -> 265.225 | BG55: =$W$55*(1+$G$55)^3 -> 273.18175 | BH55: =$W$55*(1+$G$55)^3 -> 273.18175 | BI55: =$W$55*(1+$G$55)^3 -> 273.18175 | BJ55: =$W$55*(1+$G$55)^3 -> 273.18175 | BK55: =$W$55*(1+$G$55)^3 -> 273.18175 | BL55: =$W$55*(1+$G$55)^3 -> 273.18175 | BM55: =$W$55*(1+$G$55)^3 -> 273.18175 | BN55: =$W$55*(1+$G$55)^3 -> 273.18175 | ... BR55: =$W$55*(1+$G$55)^3 -> 273.18175 | BS55: =$W$55*(1+$G$55)^4 -> 281.3772 | BT55: =$W$55*(1+$G$55)^4 -> 281.3772 | BU55: =$W$55*(1+$G$55)^4 -> 281.3772 | BV55: =$W$55*(1+$G$55)^4 -> 281.3772 | BW55: =$W$55*(1+$G$55)^4 -> 281.3772 | BX55: =$W$55*(1+$G$55)^4 -> 281.3772 | BY55: =$W$55*(1+$G$55)^4 -> 281.3772 | BZ55: =$W$55*(1+$G$55)^4 -> 281.3772 | ... CD55: =$W$55*(1+$G$55)^4 -> 281.3772 | CE55: =$W$55*(1+$G$55)^5 -> 289.81852 | CF55: =$W$55*(1+$G$55)^5 -> 289.81852 | CG55: =$W$55*(1+$G$55)^5 -> 289.81852 | CH55: =$W$55*(1+$G$55)^5 -> 289.81852 | CI55: =$W$55*(1+$G$55)^5 -> 289.81852 | CJ55: =$W$55*(1+$G$55)^5 -> 289.81852 | CK55: =$W$55*(1+$G$55)^5 -> 289.81852 | CL55: =$W$55*(1+$G$55)^5 -> 289.81852 | ... CP55: =$W$55*(1+$G$55)^5 -> 289.81852 | CQ55: =$W$55*(1+$G$55)^6 -> 298.51307 | CR55: =$W$55*(1+$G$55)^6 -> 298.51307 | CS55: =$W$55*(1+$G$55)^6 -> 298.51307 | CT55: =$W$55*(1+$G$55)^6 -> 298.51307 | CU55: =$W$55*(1+$G$55)^6 -> 298.51307 | CV55: =$W$55*(1+$G$55)^6 -> 298.51307 | CW55: =$W$55*(1+$G$55)^6 -> 298.51307 | CX55: =$W$55*(1+$G$55)^6 -> 298.51307 | ... DB55: =$W$55*(1+$G$55)^6 -> 298.51307 | DC55: =$W$55*(1+$G$55)^7 -> 307.46847 | DD55: =$W$55*(1+$G$55)^7 -> 307.46847 | DE55: =$W$55*(1+$G$55)^7 -> 307.46847 | DF55: =$W$55*(1+$G$55)^7 -> 307.46847 | DG55: =$W$55*(1+$G$55)^7 -> 307.46847 | DH55: =$W$55*(1+$G$55)^7 -> 307.46847 | DI55: =$W$55*(1+$G$55)^7 -> 307.46847 | DJ55: =$W$55*(1+$G$55)^7 -> 307.46847 | ... DN55: =$W$55*(1+$G$55)^7 -> 307.46847 | DP55: =SUM(J55:DN55) -> 32177.008
D56: ='Table 3.0'!D84 -> Property Operating & Maintenance
E57: ='Table 3.0'!E85 -> R&M Groundskeeping/Landscaping | G57: ='Table 3.0'!G85 -> 0.03 | H57: YoY Growth | W57: 2880 | X57: =W57 -> 2880 | Y57: =X57 -> 2880 | Z57: =Y57 -> 2880 | AA57: =Z57 -> 2880 | AB57: =AA57 -> 2880 | AC57: =AB57 -> 2880 | AD57: =AC57 -> 2880 | AE57: =AD57 -> 2880 | ... AH57: =AG57 -> 2880 | AI57: =$W$57*(1+$G$57) -> 2966.4 | AJ57: =$W$57*(1+$G$57) -> 2966.4 | AK57: =$W$57*(1+$G$57) -> 2966.4 | AL57: =$W$57*(1+$G$57) -> 2966.4 | AM57: =$W$57*(1+$G$57) -> 2966.4 | AN57: =$W$57*(1+$G$57) -> 2966.4 | AO57: =$W$57*(1+$G$57) -> 2966.4 | AP57: =$W$57*(1+$G$57) -> 2966.4 | ... AT57: =$W$57*(1+$G$57) -> 2966.4 | AU57: =$W$57*(1+$G$57)^2 -> 3055.392 | AV57: =$W$57*(1+$G$57)^2 -> 3055.392 | AW57: =$W$57*(1+$G$57)^2 -> 3055.392 | AX57: =$W$57*(1+$G$57)^2 -> 3055.392 | AY57: =$W$57*(1+$G$57)^2 -> 3055.392 | AZ57: =$W$57*(1+$G$57)^2 -> 3055.392 | BA57: =$W$57*(1+$G$57)^2 -> 3055.392 | BB57: =$W$57*(1+$G$57)^2 -> 3055.392 | ... BF57: =$W$57*(1+$G$57)^2 -> 3055.392 | BG57: =$W$57*(1+$G$57)^3 -> 3147.0538 | BH57: =$W$57*(1+$G$57)^3 -> 3147.0538 | BI57: =$W$57*(1+$G$57)^3 -> 3147.0538 | BJ57: =$W$57*(1+$G$57)^3 -> 3147.0538 | BK57: =$W$57*(1+$G$57)^3 -> 3147.0538 | BL57: =$W$57*(1+$G$57)^3 -> 3147.0538 | BM57: =$W$57*(1+$G$57)^3 -> 3147.0538 | BN57: =$W$57*(1+$G$57)^3 -> 3147.0538 | ... BR57: =$W$57*(1+$G$57)^3 -> 3147.0538 | BS57: =$W$57*(1+$G$57)^4 -> 3241.4654 | BT57: =$W$57*(1+$G$57)^4 -> 3241.4654 | BU57: =$W$57*(1+$G$57)^4 -> 3241.4654 | BV57: =$W$57*(1+$G$57)^4 -> 3241.4654 | BW57: =$W$57*(1+$G$57)^4 -> 3241.4654 | BX57: =$W$57*(1+$G$57)^4 -> 3241.4654 | BY57: =$W$57*(1+$G$57)^4 -> 3241.4654 | BZ57: =$W$57*(1+$G$57)^4 -> 3241.4654 | ... CD57: =$W$57*(1+$G$57)^4 -> 3241.4654 | CE57: =$W$57*(1+$G$57)^5 -> 3338.7093 | CF57: =$W$57*(1+$G$57)^5 -> 3338.7093 | CG57: =$W$57*(1+$G$57)^5 -> 3338.7093 | CH57: =$W$57*(1+$G$57)^5 -> 3338.7093 | CI57: =$W$57*(1+$G$57)^5 -> 3338.7093 | CJ57: =$W$57*(1+$G$57)^5 -> 3338.7093 | CK57: =$W$57*(1+$G$57)^5 -> 3338.7093 | CL57: =$W$57*(1+$G$57)^5 -> 3338.7093 | ... CP57: =$W$57*(1+$G$57)^5 -> 3338.7093 | CQ57: =$W$57*(1+$G$57)^6 -> 3438.8706 | CR57: =$W$57*(1+$G$57)^6 -> 3438.8706 | CS57: =$W$57*(1+$G$57)^6 -> 3438.8706 | CT57: =$W$57*(1+$G$57)^6 -> 3438.8706 | CU57: =$W$57*(1+$G$57)^6 -> 3438.8706 | CV57: =$W$57*(1+$G$57)^6 -> 3438.8706 | CW57: =$W$57*(1+$G$57)^6 -> 3438.8706 | CX57: =$W$57*(1+$G$57)^6 -> 3438.8706 | ... DB57: =$W$57*(1+$G$57)^6 -> 3438.8706 | DC57: =$W$57*(1+$G$57)^7 -> 3542.0367 | DD57: =$W$57*(1+$G$57)^7 -> 3542.0367 | DE57: =$W$57*(1+$G$57)^7 -> 3542.0367 | DF57: =$W$57*(1+$G$57)^7 -> 3542.0367 | DG57: =$W$57*(1+$G$57)^7 -> 3542.0367 | DH57: =$W$57*(1+$G$57)^7 -> 3542.0367 | DI57: =$W$57*(1+$G$57)^7 -> 3542.0367 | DJ57: =$W$57*(1+$G$57)^7 -> 3542.0367 | ... DN57: =$W$57*(1+$G$57)^7 -> 3542.0367 | DP57: =SUM(J57:DN57) -> 307319.13
E58: ='Table 3.0'!E86 -> R&M Pool | G58: ='Table 3.0'!G86 -> 0.03 | H58: YoY Growth | W58: 500 | X58: =W58 -> 500 | Y58: =X58 -> 500 | Z58: =Y58 -> 500 | AA58: =Z58 -> 500 | AB58: =AA58 -> 500 | AC58: =AB58 -> 500 | AD58: =AC58 -> 500 | AE58: =AD58 -> 500 | ... AH58: =AG58 -> 500 | AI58: =$W$58*(1+$G$58) -> 515 | AJ58: =$W$58*(1+$G$58) -> 515 | AK58: =$W$58*(1+$G$58) -> 515 | AL58: =$W$58*(1+$G$58) -> 515 | AM58: =$W$58*(1+$G$58) -> 515 | AN58: =$W$58*(1+$G$58) -> 515 | AO58: =$W$58*(1+$G$58) -> 515 | AP58: =$W$58*(1+$G$58) -> 515 | ... AT58: =$W$58*(1+$G$58) -> 515 | AU58: =$W$58*(1+$G$58)^2 -> 530.45 | AV58: =$W$58*(1+$G$58)^2 -> 530.45 | AW58: =$W$58*(1+$G$58)^2 -> 530.45 | AX58: =$W$58*(1+$G$58)^2 -> 530.45 | AY58: =$W$58*(1+$G$58)^2 -> 530.45 | AZ58: =$W$58*(1+$G$58)^2 -> 530.45 | BA58: =$W$58*(1+$G$58)^2 -> 530.45 | BB58: =$W$58*(1+$G$58)^2 -> 530.45 | ... BF58: =$W$58*(1+$G$58)^2 -> 530.45 | BG58: =$W$58*(1+$G$58)^3 -> 546.3635 | BH58: =$W$58*(1+$G$58)^3 -> 546.3635 | BI58: =$W$58*(1+$G$58)^3 -> 546.3635 | BJ58: =$W$58*(1+$G$58)^3 -> 546.3635 | BK58: =$W$58*(1+$G$58)^3 -> 546.3635 | BL58: =$W$58*(1+$G$58)^3 -> 546.3635 | BM58: =$W$58*(1+$G$58)^3 -> 546.3635 | BN58: =$W$58*(1+$G$58)^3 -> 546.3635 | ... BR58: =$W$58*(1+$G$58)^3 -> 546.3635 | BS58: =$W$58*(1+$G$58)^4 -> 562.7544 | BT58: =$W$58*(1+$G$58)^4 -> 562.7544 | BU58: =$W$58*(1+$G$58)^4 -> 562.7544 | BV58: =$W$58*(1+$G$58)^4 -> 562.7544 | BW58: =$W$58*(1+$G$58)^4 -> 562.7544 | BX58: =$W$58*(1+$G$58)^4 -> 562.7544 | BY58: =$W$58*(1+$G$58)^4 -> 562.7544 | BZ58: =$W$58*(1+$G$58)^4 -> 562.7544 | ... CD58: =$W$58*(1+$G$58)^4 -> 562.7544 | CE58: =$W$58*(1+$G$58)^5 -> 579.63704 | CF58: =$W$58*(1+$G$58)^5 -> 579.63704 | CG58: =$W$58*(1+$G$58)^5 -> 579.63704 | CH58: =$W$58*(1+$G$58)^5 -> 579.63704 | CI58: =$W$58*(1+$G$58)^5 -> 579.63704 | CJ58: =$W$58*(1+$G$58)^5 -> 579.63704 | CK58: =$W$58*(1+$G$58)^5 -> 579.63704 | CL58: =$W$58*(1+$G$58)^5 -> 579.63704 | ... CP58: =$W$58*(1+$G$58)^5 -> 579.63704 | CQ58: =$W$58*(1+$G$58)^6 -> 597.02615 | CR58: =$W$58*(1+$G$58)^6 -> 597.02615 | CS58: =$W$58*(1+$G$58)^6 -> 597.02615 | CT58: =$W$58*(1+$G$58)^6 -> 597.02615 | CU58: =$W$58*(1+$G$58)^6 -> 597.02615 | CV58: =$W$58*(1+$G$58)^6 -> 597.02615 | CW58: =$W$58*(1+$G$58)^6 -> 597.02615 | CX58: =$W$58*(1+$G$58)^6 -> 597.02615 | ... DB58: =$W$58*(1+$G$58)^6 -> 597.02615 | DC58: =$W$58*(1+$G$58)^7 -> 614.93693 | DD58: =$W$58*(1+$G$58)^7 -> 614.93693 | DE58: =$W$58*(1+$G$58)^7 -> 614.93693 | DF58: =$W$58*(1+$G$58)^7 -> 614.93693 | DG58: =$W$58*(1+$G$58)^7 -> 614.93693 | DH58: =$W$58*(1+$G$58)^7 -> 614.93693 | DI58: =$W$58*(1+$G$58)^7 -> 614.93693 | DJ58: =$W$58*(1+$G$58)^7 -> 614.93693 | ... DN58: =$W$58*(1+$G$58)^7 -> 614.93693 | DP58: =SUM(J58:DN58) -> 53354.016
E59: ='Table 3.0'!E87 -> R&M Plumbing & Septic | G59: ='Table 3.0'!G87 -> 0.03 | H59: YoY Growth | W59: 500 | X59: =W59 -> 500 | Y59: =X59 -> 500 | Z59: =Y59 -> 500 | AA59: =Z59 -> 500 | AB59: =AA59 -> 500 | AC59: =AB59 -> 500 | AD59: =AC59 -> 500 | AE59: =AD59 -> 500 | ... AH59: =AG59 -> 500 | AI59: =$W$59*(1+$G$59) -> 515 | AJ59: =$W$59*(1+$G$59) -> 515 | AK59: =$W$59*(1+$G$59) -> 515 | AL59: =$W$59*(1+$G$59) -> 515 | AM59: =$W$59*(1+$G$59) -> 515 | AN59: =$W$59*(1+$G$59) -> 515 | AO59: =$W$59*(1+$G$59) -> 515 | AP59: =$W$59*(1+$G$59) -> 515 | ... AT59: =$W$59*(1+$G$59) -> 515 | AU59: =$W$59*(1+$G$59)^2 -> 530.45 | AV59: =$W$59*(1+$G$59)^2 -> 530.45 | AW59: =$W$59*(1+$G$59)^2 -> 530.45 | AX59: =$W$59*(1+$G$59)^2 -> 530.45 | AY59: =$W$59*(1+$G$59)^2 -> 530.45 | AZ59: =$W$59*(1+$G$59)^2 -> 530.45 | BA59: =$W$59*(1+$G$59)^2 -> 530.45 | BB59: =$W$59*(1+$G$59)^2 -> 530.45 | ... BF59: =$W$59*(1+$G$59)^2 -> 530.45 | BG59: =$W$59*(1+$G$59)^3 -> 546.3635 | BH59: =$W$59*(1+$G$59)^3 -> 546.3635 | BI59: =$W$59*(1+$G$59)^3 -> 546.3635 | BJ59: =$W$59*(1+$G$59)^3 -> 546.3635 | BK59: =$W$59*(1+$G$59)^3 -> 546.3635 | BL59: =$W$59*(1+$G$59)^3 -> 546.3635 | BM59: =$W$59*(1+$G$59)^3 -> 546.3635 | BN59: =$W$59*(1+$G$59)^3 -> 546.3635 | ... BR59: =$W$59*(1+$G$59)^3 -> 546.3635 | BS59: =$W$59*(1+$G$59)^4 -> 562.7544 | BT59: =$W$59*(1+$G$59)^4 -> 562.7544 | BU59: =$W$59*(1+$G$59)^4 -> 562.7544 | BV59: =$W$59*(1+$G$59)^4 -> 562.7544 | BW59: =$W$59*(1+$G$59)^4 -> 562.7544 | BX59: =$W$59*(1+$G$59)^4 -> 562.7544 | BY59: =$W$59*(1+$G$59)^4 -> 562.7544 | BZ59: =$W$59*(1+$G$59)^4 -> 562.7544 | ... CD59: =$W$59*(1+$G$59)^4 -> 562.7544 | CE59: =$W$59*(1+$G$59)^5 -> 579.63704 | CF59: =$W$59*(1+$G$59)^5 -> 579.63704 | CG59: =$W$59*(1+$G$59)^5 -> 579.63704 | CH59: =$W$59*(1+$G$59)^5 -> 579.63704 | CI59: =$W$59*(1+$G$59)^5 -> 579.63704 | CJ59: =$W$59*(1+$G$59)^5 -> 579.63704 | CK59: =$W$59*(1+$G$59)^5 -> 579.63704 | CL59: =$W$59*(1+$G$59)^5 -> 579.63704 | ... CP59: =$W$59*(1+$G$59)^5 -> 579.63704 | CQ59: =$W$59*(1+$G$59)^6 -> 597.02615 | CR59: =$W$59*(1+$G$59)^6 -> 597.02615 | CS59: =$W$59*(1+$G$59)^6 -> 597.02615 | CT59: =$W$59*(1+$G$59)^6 -> 597.02615 | CU59: =$W$59*(1+$G$59)^6 -> 597.02615 | CV59: =$W$59*(1+$G$59)^6 -> 597.02615 | CW59: =$W$59*(1+$G$59)^6 -> 597.02615 | CX59: =$W$59*(1+$G$59)^6 -> 597.02615 | ... DB59: =$W$59*(1+$G$59)^6 -> 597.02615 | DC59: =$W$59*(1+$G$59)^7 -> 614.93693 | DD59: =$W$59*(1+$G$59)^7 -> 614.93693 | DE59: =$W$59*(1+$G$59)^7 -> 614.93693 | DF59: =$W$59*(1+$G$59)^7 -> 614.93693 | DG59: =$W$59*(1+$G$59)^7 -> 614.93693 | DH59: =$W$59*(1+$G$59)^7 -> 614.93693 | DI59: =$W$59*(1+$G$59)^7 -> 614.93693 | DJ59: =$W$59*(1+$G$59)^7 -> 614.93693 | ... DN59: =$W$59*(1+$G$59)^7 -> 614.93693 | DP59: =SUM(J59:DN59) -> 53354.016
E60: ='Table 3.0'!E88 -> R&M Tools & Supplies | G60: ='Table 3.0'!G88 -> 0.03 | H60: YoY Growth | W60: 500 | X60: =W60 -> 500 | Y60: =X60 -> 500 | Z60: =Y60 -> 500 | AA60: =Z60 -> 500 | AB60: =AA60 -> 500 | AC60: =AB60 -> 500 | AD60: =AC60 -> 500 | AE60: =AD60 -> 500 | ... AH60: =AG60 -> 500 | AI60: =$W$60*(1+$G$60) -> 515 | AJ60: =$W$60*(1+$G$60) -> 515 | AK60: =$W$60*(1+$G$60) -> 515 | AL60: =$W$60*(1+$G$60) -> 515 | AM60: =$W$60*(1+$G$60) -> 515 | AN60: =$W$60*(1+$G$60) -> 515 | AO60: =$W$60*(1+$G$60) -> 515 | AP60: =$W$60*(1+$G$60) -> 515 | ... AT60: =$W$60*(1+$G$60) -> 515 | AU60: =$W$60*(1+$G$60)^2 -> 530.45 | AV60: =$W$60*(1+$G$60)^2 -> 530.45 | AW60: =$W$60*(1+$G$60)^2 -> 530.45 | AX60: =$W$60*(1+$G$60)^2 -> 530.45 | AY60: =$W$60*(1+$G$60)^2 -> 530.45 | AZ60: =$W$60*(1+$G$60)^2 -> 530.45 | BA60: =$W$60*(1+$G$60)^2 -> 530.45 | BB60: =$W$60*(1+$G$60)^2 -> 530.45 | ... BF60: =$W$60*(1+$G$60)^2 -> 530.45 | BG60: =$W$60*(1+$G$60)^3 -> 546.3635 | BH60: =$W$60*(1+$G$60)^3 -> 546.3635 | BI60: =$W$60*(1+$G$60)^3 -> 546.3635 | BJ60: =$W$60*(1+$G$60)^3 -> 546.3635 | BK60: =$W$60*(1+$G$60)^3 -> 546.3635 | BL60: =$W$60*(1+$G$60)^3 -> 546.3635 | BM60: =$W$60*(1+$G$60)^3 -> 546.3635 | BN60: =$W$60*(1+$G$60)^3 -> 546.3635 | ... BR60: =$W$60*(1+$G$60)^3 -> 546.3635 | BS60: =$W$60*(1+$G$60)^4 -> 562.7544 | BT60: =$W$60*(1+$G$60)^4 -> 562.7544 | BU60: =$W$60*(1+$G$60)^4 -> 562.7544 | BV60: =$W$60*(1+$G$60)^4 -> 562.7544 | BW60: =$W$60*(1+$G$60)^4 -> 562.7544 | BX60: =$W$60*(1+$G$60)^4 -> 562.7544 | BY60: =$W$60*(1+$G$60)^4 -> 562.7544 | BZ60: =$W$60*(1+$G$60)^4 -> 562.7544 | ... CD60: =$W$60*(1+$G$60)^4 -> 562.7544 | CE60: =$W$60*(1+$G$60)^5 -> 579.63704 | CF60: =$W$60*(1+$G$60)^5 -> 579.63704 | CG60: =$W$60*(1+$G$60)^5 -> 579.63704 | CH60: =$W$60*(1+$G$60)^5 -> 579.63704 | CI60: =$W$60*(1+$G$60)^5 -> 579.63704 | CJ60: =$W$60*(1+$G$60)^5 -> 579.63704 | CK60: =$W$60*(1+$G$60)^5 -> 579.63704 | CL60: =$W$60*(1+$G$60)^5 -> 579.63704 | ... CP60: =$W$60*(1+$G$60)^5 -> 579.63704 | CQ60: =$W$60*(1+$G$60)^6 -> 597.02615 | CR60: =$W$60*(1+$G$60)^6 -> 597.02615 | CS60: =$W$60*(1+$G$60)^6 -> 597.02615 | CT60: =$W$60*(1+$G$60)^6 -> 597.02615 | CU60: =$W$60*(1+$G$60)^6 -> 597.02615 | CV60: =$W$60*(1+$G$60)^6 -> 597.02615 | CW60: =$W$60*(1+$G$60)^6 -> 597.02615 | CX60: =$W$60*(1+$G$60)^6 -> 597.02615 | ... DB60: =$W$60*(1+$G$60)^6 -> 597.02615 | DC60: =$W$60*(1+$G$60)^7 -> 614.93693 | DD60: =$W$60*(1+$G$60)^7 -> 614.93693 | DE60: =$W$60*(1+$G$60)^7 -> 614.93693 | DF60: =$W$60*(1+$G$60)^7 -> 614.93693 | DG60: =$W$60*(1+$G$60)^7 -> 614.93693 | DH60: =$W$60*(1+$G$60)^7 -> 614.93693 | DI60: =$W$60*(1+$G$60)^7 -> 614.93693 | DJ60: =$W$60*(1+$G$60)^7 -> 614.93693 | ... DN60: =$W$60*(1+$G$60)^7 -> 614.93693 | DP60: =SUM(J60:DN60) -> 53354.016
D61: ='Table 3.0'!D89 -> Utilities
E62: ='Table 3.0'!E90 -> Water | G62: ='Table 3.0'!G90 -> 0.03 | H62: YoY Growth | W62: 1150 | X62: =W62 -> 1150 | Y62: =X62 -> 1150 | Z62: =Y62 -> 1150 | AA62: =Z62 -> 1150 | AB62: =AA62 -> 1150 | AC62: =AB62 -> 1150 | AD62: =AC62 -> 1150 | AE62: =AD62 -> 1150 | ... AH62: =AG62 -> 1150 | AI62: =$W$62*(1+$G$62) -> 1184.5 | AJ62: =$W$62*(1+$G$62) -> 1184.5 | AK62: =$W$62*(1+$G$62) -> 1184.5 | AL62: =$W$62*(1+$G$62) -> 1184.5 | AM62: =$W$62*(1+$G$62) -> 1184.5 | AN62: =$W$62*(1+$G$62) -> 1184.5 | AO62: =$W$62*(1+$G$62) -> 1184.5 | AP62: =$W$62*(1+$G$62) -> 1184.5 | ... AT62: =$W$62*(1+$G$62) -> 1184.5 | AU62: =$W$62*(1+$G$62)^2 -> 1220.035 | AV62: =$W$62*(1+$G$62)^2 -> 1220.035 | AW62: =$W$62*(1+$G$62)^2 -> 1220.035 | AX62: =$W$62*(1+$G$62)^2 -> 1220.035 | AY62: =$W$62*(1+$G$62)^2 -> 1220.035 | AZ62: =$W$62*(1+$G$62)^2 -> 1220.035 | BA62: =$W$62*(1+$G$62)^2 -> 1220.035 | BB62: =$W$62*(1+$G$62)^2 -> 1220.035 | ... BF62: =$W$62*(1+$G$62)^2 -> 1220.035 | BG62: =$W$62*(1+$G$62)^3 -> 1256.6361 | BH62: =$W$62*(1+$G$62)^3 -> 1256.6361 | BI62: =$W$62*(1+$G$62)^3 -> 1256.6361 | BJ62: =$W$62*(1+$G$62)^3 -> 1256.6361 | BK62: =$W$62*(1+$G$62)^3 -> 1256.6361 | BL62: =$W$62*(1+$G$62)^3 -> 1256.6361 | BM62: =$W$62*(1+$G$62)^3 -> 1256.6361 | BN62: =$W$62*(1+$G$62)^3 -> 1256.6361 | ... BR62: =$W$62*(1+$G$62)^3 -> 1256.6361 | BS62: =$W$62*(1+$G$62)^4 -> 1294.3351 | BT62: =$W$62*(1+$G$62)^4 -> 1294.3351 | BU62: =$W$62*(1+$G$62)^4 -> 1294.3351 | BV62: =$W$62*(1+$G$62)^4 -> 1294.3351 | BW62: =$W$62*(1+$G$62)^4 -> 1294.3351 | BX62: =$W$62*(1+$G$62)^4 -> 1294.3351 | BY62: =$W$62*(1+$G$62)^4 -> 1294.3351 | BZ62: =$W$62*(1+$G$62)^4 -> 1294.3351 | ... CD62: =$W$62*(1+$G$62)^4 -> 1294.3351 | CE62: =$W$62*(1+$G$62)^5 -> 1333.1652 | CF62: =$W$62*(1+$G$62)^5 -> 1333.1652 | CG62: =$W$62*(1+$G$62)^5 -> 1333.1652 | CH62: =$W$62*(1+$G$62)^5 -> 1333.1652 | CI62: =$W$62*(1+$G$62)^5 -> 1333.1652 | CJ62: =$W$62*(1+$G$62)^5 -> 1333.1652 | CK62: =$W$62*(1+$G$62)^5 -> 1333.1652 | CL62: =$W$62*(1+$G$62)^5 -> 1333.1652 | ... CP62: =$W$62*(1+$G$62)^5 -> 1333.1652 | CQ62: =$W$62*(1+$G$62)^6 -> 1373.1601 | CR62: =$W$62*(1+$G$62)^6 -> 1373.1601 | CS62: =$W$62*(1+$G$62)^6 -> 1373.1601 | CT62: =$W$62*(1+$G$62)^6 -> 1373.1601 | CU62: =$W$62*(1+$G$62)^6 -> 1373.1601 | CV62: =$W$62*(1+$G$62)^6 -> 1373.1601 | CW62: =$W$62*(1+$G$62)^6 -> 1373.1601 | CX62: =$W$62*(1+$G$62)^6 -> 1373.1601 | ... DB62: =$W$62*(1+$G$62)^6 -> 1373.1601 | DC62: =$W$62*(1+$G$62)^7 -> 1414.3549 | DD62: =$W$62*(1+$G$62)^7 -> 1414.3549 | DE62: =$W$62*(1+$G$62)^7 -> 1414.3549 | DF62: =$W$62*(1+$G$62)^7 -> 1414.3549 | DG62: =$W$62*(1+$G$62)^7 -> 1414.3549 | DH62: =$W$62*(1+$G$62)^7 -> 1414.3549 | DI62: =$W$62*(1+$G$62)^7 -> 1414.3549 | DJ62: =$W$62*(1+$G$62)^7 -> 1414.3549 | ... DN62: =$W$62*(1+$G$62)^7 -> 1414.3549 | DP62: =SUM(J62:DN62) -> 122714.24
E63: ='Table 3.0'!E91 -> Telephone | G63: ='Table 3.0'!G91 -> 0.03 | H63: YoY Growth | W63: 250 | X63: =W63 -> 250 | Y63: =X63 -> 250 | Z63: =Y63 -> 250 | AA63: =Z63 -> 250 | AB63: =AA63 -> 250 | AC63: =AB63 -> 250 | AD63: =AC63 -> 250 | AE63: =AD63 -> 250 | ... AH63: =AG63 -> 250 | AI63: =$W$63*(1+$G$63) -> 257.5 | AJ63: =$W$63*(1+$G$63) -> 257.5 | AK63: =$W$63*(1+$G$63) -> 257.5 | AL63: =$W$63*(1+$G$63) -> 257.5 | AM63: =$W$63*(1+$G$63) -> 257.5 | AN63: =$W$63*(1+$G$63) -> 257.5 | AO63: =$W$63*(1+$G$63) -> 257.5 | AP63: =$W$63*(1+$G$63) -> 257.5 | ... AT63: =$W$63*(1+$G$63) -> 257.5 | AU63: =$W$63*(1+$G$63)^2 -> 265.225 | AV63: =$W$63*(1+$G$63)^2 -> 265.225 | AW63: =$W$63*(1+$G$63)^2 -> 265.225 | AX63: =$W$63*(1+$G$63)^2 -> 265.225 | AY63: =$W$63*(1+$G$63)^2 -> 265.225 | AZ63: =$W$63*(1+$G$63)^2 -> 265.225 | BA63: =$W$63*(1+$G$63)^2 -> 265.225 | BB63: =$W$63*(1+$G$63)^2 -> 265.225 | ... BF63: =$W$63*(1+$G$63)^2 -> 265.225 | BG63: =$W$63*(1+$G$63)^3 -> 273.18175 | BH63: =$W$63*(1+$G$63)^3 -> 273.18175 | BI63: =$W$63*(1+$G$63)^3 -> 273.18175 | BJ63: =$W$63*(1+$G$63)^3 -> 273.18175 | BK63: =$W$63*(1+$G$63)^3 -> 273.18175 | BL63: =$W$63*(1+$G$63)^3 -> 273.18175 | BM63: =$W$63*(1+$G$63)^3 -> 273.18175 | BN63: =$W$63*(1+$G$63)^3 -> 273.18175 | ... BR63: =$W$63*(1+$G$63)^3 -> 273.18175 | BS63: =$W$63*(1+$G$63)^4 -> 281.3772 | BT63: =$W$63*(1+$G$63)^4 -> 281.3772 | BU63: =$W$63*(1+$G$63)^4 -> 281.3772 | BV63: =$W$63*(1+$G$63)^4 -> 281.3772 | BW63: =$W$63*(1+$G$63)^4 -> 281.3772 | BX63: =$W$63*(1+$G$63)^4 -> 281.3772 | BY63: =$W$63*(1+$G$63)^4 -> 281.3772 | BZ63: =$W$63*(1+$G$63)^4 -> 281.3772 | ... CD63: =$W$63*(1+$G$63)^4 -> 281.3772 | CE63: =$W$63*(1+$G$63)^5 -> 289.81852 | CF63: =$W$63*(1+$G$63)^5 -> 289.81852 | CG63: =$W$63*(1+$G$63)^5 -> 289.81852 | CH63: =$W$63*(1+$G$63)^5 -> 289.81852 | CI63: =$W$63*(1+$G$63)^5 -> 289.81852 | CJ63: =$W$63*(1+$G$63)^5 -> 289.81852 | CK63: =$W$63*(1+$G$63)^5 -> 289.81852 | CL63: =$W$63*(1+$G$63)^5 -> 289.81852 | ... CP63: =$W$63*(1+$G$63)^5 -> 289.81852 | CQ63: =$W$63*(1+$G$63)^6 -> 298.51307 | CR63: =$W$63*(1+$G$63)^6 -> 298.51307 | CS63: =$W$63*(1+$G$63)^6 -> 298.51307 | CT63: =$W$63*(1+$G$63)^6 -> 298.51307 | CU63: =$W$63*(1+$G$63)^6 -> 298.51307 | CV63: =$W$63*(1+$G$63)^6 -> 298.51307 | CW63: =$W$63*(1+$G$63)^6 -> 298.51307 | CX63: =$W$63*(1+$G$63)^6 -> 298.51307 | ... DB63: =$W$63*(1+$G$63)^6 -> 298.51307 | DC63: =$W$63*(1+$G$63)^7 -> 307.46847 | DD63: =$W$63*(1+$G$63)^7 -> 307.46847 | DE63: =$W$63*(1+$G$63)^7 -> 307.46847 | DF63: =$W$63*(1+$G$63)^7 -> 307.46847 | DG63: =$W$63*(1+$G$63)^7 -> 307.46847 | DH63: =$W$63*(1+$G$63)^7 -> 307.46847 | DI63: =$W$63*(1+$G$63)^7 -> 307.46847 | DJ63: =$W$63*(1+$G$63)^7 -> 307.46847 | ... DN63: =$W$63*(1+$G$63)^7 -> 307.46847 | DP63: =SUM(J63:DN63) -> 26677.008
E64: ='Table 3.0'!E92 -> Cable/Internet | G64: ='Table 3.0'!G92 -> 0.03 | H64: YoY Growth | W64: 1200 | X64: =W64 -> 1200 | Y64: =X64 -> 1200 | Z64: =Y64 -> 1200 | AA64: =Z64 -> 1200 | AB64: =AA64 -> 1200 | AC64: =AB64 -> 1200 | AD64: =AC64 -> 1200 | AE64: =AD64 -> 1200 | ... AH64: =AG64 -> 1200 | AI64: =$W$64*(1+$G$64) -> 1236 | AJ64: =$W$64*(1+$G$64) -> 1236 | AK64: =$W$64*(1+$G$64) -> 1236 | AL64: =$W$64*(1+$G$64) -> 1236 | AM64: =$W$64*(1+$G$64) -> 1236 | AN64: =$W$64*(1+$G$64) -> 1236 | AO64: =$W$64*(1+$G$64) -> 1236 | AP64: =$W$64*(1+$G$64) -> 1236 | ... AT64: =$W$64*(1+$G$64) -> 1236 | AU64: =$W$64*(1+$G$64)^2 -> 1273.08 | AV64: =$W$64*(1+$G$64)^2 -> 1273.08 | AW64: =$W$64*(1+$G$64)^2 -> 1273.08 | AX64: =$W$64*(1+$G$64)^2 -> 1273.08 | AY64: =$W$64*(1+$G$64)^2 -> 1273.08 | AZ64: =$W$64*(1+$G$64)^2 -> 1273.08 | BA64: =$W$64*(1+$G$64)^2 -> 1273.08 | BB64: =$W$64*(1+$G$64)^2 -> 1273.08 | ... BF64: =$W$64*(1+$G$64)^2 -> 1273.08 | BG64: =$W$64*(1+$G$64)^3 -> 1311.2724 | BH64: =$W$64*(1+$G$64)^3 -> 1311.2724 | BI64: =$W$64*(1+$G$64)^3 -> 1311.2724 | BJ64: =$W$64*(1+$G$64)^3 -> 1311.2724 | BK64: =$W$64*(1+$G$64)^3 -> 1311.2724 | BL64: =$W$64*(1+$G$64)^3 -> 1311.2724 | BM64: =$W$64*(1+$G$64)^3 -> 1311.2724 | BN64: =$W$64*(1+$G$64)^3 -> 1311.2724 | ... BR64: =$W$64*(1+$G$64)^3 -> 1311.2724 | BS64: =$W$64*(1+$G$64)^4 -> 1350.6106 | BT64: =$W$64*(1+$G$64)^4 -> 1350.6106 | BU64: =$W$64*(1+$G$64)^4 -> 1350.6106 | BV64: =$W$64*(1+$G$64)^4 -> 1350.6106 | BW64: =$W$64*(1+$G$64)^4 -> 1350.6106 | BX64: =$W$64*(1+$G$64)^4 -> 1350.6106 | BY64: =$W$64*(1+$G$64)^4 -> 1350.6106 | BZ64: =$W$64*(1+$G$64)^4 -> 1350.6106 | ... CD64: =$W$64*(1+$G$64)^4 -> 1350.6106 | CE64: =$W$64*(1+$G$64)^5 -> 1391.1289 | CF64: =$W$64*(1+$G$64)^5 -> 1391.1289 | CG64: =$W$64*(1+$G$64)^5 -> 1391.1289 | CH64: =$W$64*(1+$G$64)^5 -> 1391.1289 | CI64: =$W$64*(1+$G$64)^5 -> 1391.1289 | CJ64: =$W$64*(1+$G$64)^5 -> 1391.1289 | CK64: =$W$64*(1+$G$64)^5 -> 1391.1289 | CL64: =$W$64*(1+$G$64)^5 -> 1391.1289 | ... CP64: =$W$64*(1+$G$64)^5 -> 1391.1289 | CQ64: =$W$64*(1+$G$64)^6 -> 1432.8628 | CR64: =$W$64*(1+$G$64)^6 -> 1432.8628 | CS64: =$W$64*(1+$G$64)^6 -> 1432.8628 | CT64: =$W$64*(1+$G$64)^6 -> 1432.8628 | CU64: =$W$64*(1+$G$64)^6 -> 1432.8628 | CV64: =$W$64*(1+$G$64)^6 -> 1432.8628 | CW64: =$W$64*(1+$G$64)^6 -> 1432.8628 | CX64: =$W$64*(1+$G$64)^6 -> 1432.8628 | ... DB64: =$W$64*(1+$G$64)^6 -> 1432.8628 | DC64: =$W$64*(1+$G$64)^7 -> 1475.8486 | DD64: =$W$64*(1+$G$64)^7 -> 1475.8486 | DE64: =$W$64*(1+$G$64)^7 -> 1475.8486 | DF64: =$W$64*(1+$G$64)^7 -> 1475.8486 | DG64: =$W$64*(1+$G$64)^7 -> 1475.8486 | DH64: =$W$64*(1+$G$64)^7 -> 1475.8486 | DI64: =$W$64*(1+$G$64)^7 -> 1475.8486 | DJ64: =$W$64*(1+$G$64)^7 -> 1475.8486 | ... DN64: =$W$64*(1+$G$64)^7 -> 1475.8486 | DP64: =SUM(J64:DN64) -> 128049.64
E65: ='Table 3.0'!E93 -> Electric | G65: ='Table 3.0'!G93 -> 0.03 | H65: YoY Growth | W65: 1500 | X65: =W65 -> 1500 | Y65: =X65 -> 1500 | Z65: =Y65 -> 1500 | AA65: =Z65 -> 1500 | AB65: =AA65 -> 1500 | AC65: =AB65 -> 1500 | AD65: =AC65 -> 1500 | AE65: =AD65 -> 1500 | ... AH65: =AG65 -> 1500 | AI65: =$W$65*(1+$G$65) -> 1545 | AJ65: =$W$65*(1+$G$65) -> 1545 | AK65: =$W$65*(1+$G$65) -> 1545 | AL65: =$W$65*(1+$G$65) -> 1545 | AM65: =$W$65*(1+$G$65) -> 1545 | AN65: =$W$65*(1+$G$65) -> 1545 | AO65: =$W$65*(1+$G$65) -> 1545 | AP65: =$W$65*(1+$G$65) -> 1545 | ... AT65: =$W$65*(1+$G$65) -> 1545 | AU65: =$W$65*(1+$G$65)^2 -> 1591.35 | AV65: =$W$65*(1+$G$65)^2 -> 1591.35 | AW65: =$W$65*(1+$G$65)^2 -> 1591.35 | AX65: =$W$65*(1+$G$65)^2 -> 1591.35 | AY65: =$W$65*(1+$G$65)^2 -> 1591.35 | AZ65: =$W$65*(1+$G$65)^2 -> 1591.35 | BA65: =$W$65*(1+$G$65)^2 -> 1591.35 | BB65: =$W$65*(1+$G$65)^2 -> 1591.35 | ... BF65: =$W$65*(1+$G$65)^2 -> 1591.35 | BG65: =$W$65*(1+$G$65)^3 -> 1639.0905 | BH65: =$W$65*(1+$G$65)^3 -> 1639.0905 | BI65: =$W$65*(1+$G$65)^3 -> 1639.0905 | BJ65: =$W$65*(1+$G$65)^3 -> 1639.0905 | BK65: =$W$65*(1+$G$65)^3 -> 1639.0905 | BL65: =$W$65*(1+$G$65)^3 -> 1639.0905 | BM65: =$W$65*(1+$G$65)^3 -> 1639.0905 | BN65: =$W$65*(1+$G$65)^3 -> 1639.0905 | ... BR65: =$W$65*(1+$G$65)^3 -> 1639.0905 | BS65: =$W$65*(1+$G$65)^4 -> 1688.2632 | BT65: =$W$65*(1+$G$65)^4 -> 1688.2632 | BU65: =$W$65*(1+$G$65)^4 -> 1688.2632 | BV65: =$W$65*(1+$G$65)^4 -> 1688.2632 | BW65: =$W$65*(1+$G$65)^4 -> 1688.2632 | BX65: =$W$65*(1+$G$65)^4 -> 1688.2632 | BY65: =$W$65*(1+$G$65)^4 -> 1688.2632 | BZ65: =$W$65*(1+$G$65)^4 -> 1688.2632 | ... CD65: =$W$65*(1+$G$65)^4 -> 1688.2632 | CE65: =$W$65*(1+$G$65)^5 -> 1738.9111 | CF65: =$W$65*(1+$G$65)^5 -> 1738.9111 | CG65: =$W$65*(1+$G$65)^5 -> 1738.9111 | CH65: =$W$65*(1+$G$65)^5 -> 1738.9111 | CI65: =$W$65*(1+$G$65)^5 -> 1738.9111 | CJ65: =$W$65*(1+$G$65)^5 -> 1738.9111 | CK65: =$W$65*(1+$G$65)^5 -> 1738.9111 | CL65: =$W$65*(1+$G$65)^5 -> 1738.9111 | ... CP65: =$W$65*(1+$G$65)^5 -> 1738.9111 | CQ65: =$W$65*(1+$G$65)^6 -> 1791.0784 | CR65: =$W$65*(1+$G$65)^6 -> 1791.0784 | CS65: =$W$65*(1+$G$65)^6 -> 1791.0784 | CT65: =$W$65*(1+$G$65)^6 -> 1791.0784 | CU65: =$W$65*(1+$G$65)^6 -> 1791.0784 | CV65: =$W$65*(1+$G$65)^6 -> 1791.0784 | CW65: =$W$65*(1+$G$65)^6 -> 1791.0784 | CX65: =$W$65*(1+$G$65)^6 -> 1791.0784 | ... DB65: =$W$65*(1+$G$65)^6 -> 1791.0784 | DC65: =$W$65*(1+$G$65)^7 -> 1844.8108 | DD65: =$W$65*(1+$G$65)^7 -> 1844.8108 | DE65: =$W$65*(1+$G$65)^7 -> 1844.8108 | DF65: =$W$65*(1+$G$65)^7 -> 1844.8108 | DG65: =$W$65*(1+$G$65)^7 -> 1844.8108 | DH65: =$W$65*(1+$G$65)^7 -> 1844.8108 | DI65: =$W$65*(1+$G$65)^7 -> 1844.8108 | DJ65: =$W$65*(1+$G$65)^7 -> 1844.8108 | ... DN65: =$W$65*(1+$G$65)^7 -> 1844.8108 | DP65: =SUM(J65:DN65) -> 160062.05
E66: ='Table 3.0'!E94 -> Gas | G66: ='Table 3.0'!G94 -> 0.03 | H66: YoY Growth | W66: 1000 | X66: =W66 -> 1000 | Y66: =X66 -> 1000 | Z66: =Y66 -> 1000 | AA66: =Z66 -> 1000 | AB66: =AA66 -> 1000 | AC66: =AB66 -> 1000 | AD66: =AC66 -> 1000 | AE66: =AD66 -> 1000 | ... AH66: =AG66 -> 1000 | AI66: =$W$66*(1+$G$66) -> 1030 | AJ66: =$W$66*(1+$G$66) -> 1030 | AK66: =$W$66*(1+$G$66) -> 1030 | AL66: =$W$66*(1+$G$66) -> 1030 | AM66: =$W$66*(1+$G$66) -> 1030 | AN66: =$W$66*(1+$G$66) -> 1030 | AO66: =$W$66*(1+$G$66) -> 1030 | AP66: =$W$66*(1+$G$66) -> 1030 | ... AT66: =$W$66*(1+$G$66) -> 1030 | AU66: =$W$66*(1+$G$66)^2 -> 1060.9 | AV66: =$W$66*(1+$G$66)^2 -> 1060.9 | AW66: =$W$66*(1+$G$66)^2 -> 1060.9 | AX66: =$W$66*(1+$G$66)^2 -> 1060.9 | AY66: =$W$66*(1+$G$66)^2 -> 1060.9 | AZ66: =$W$66*(1+$G$66)^2 -> 1060.9 | BA66: =$W$66*(1+$G$66)^2 -> 1060.9 | BB66: =$W$66*(1+$G$66)^2 -> 1060.9 | ... BF66: =$W$66*(1+$G$66)^2 -> 1060.9 | BG66: =$W$66*(1+$G$66)^3 -> 1092.727 | BH66: =$W$66*(1+$G$66)^3 -> 1092.727 | BI66: =$W$66*(1+$G$66)^3 -> 1092.727 | BJ66: =$W$66*(1+$G$66)^3 -> 1092.727 | BK66: =$W$66*(1+$G$66)^3 -> 1092.727 | BL66: =$W$66*(1+$G$66)^3 -> 1092.727 | BM66: =$W$66*(1+$G$66)^3 -> 1092.727 | BN66: =$W$66*(1+$G$66)^3 -> 1092.727 | ... BR66: =$W$66*(1+$G$66)^3 -> 1092.727 | BS66: =$W$66*(1+$G$66)^4 -> 1125.5088 | BT66: =$W$66*(1+$G$66)^4 -> 1125.5088 | BU66: =$W$66*(1+$G$66)^4 -> 1125.5088 | BV66: =$W$66*(1+$G$66)^4 -> 1125.5088 | BW66: =$W$66*(1+$G$66)^4 -> 1125.5088 | BX66: =$W$66*(1+$G$66)^4 -> 1125.5088 | BY66: =$W$66*(1+$G$66)^4 -> 1125.5088 | BZ66: =$W$66*(1+$G$66)^4 -> 1125.5088 | ... CD66: =$W$66*(1+$G$66)^4 -> 1125.5088 | CE66: =$W$66*(1+$G$66)^5 -> 1159.2741 | CF66: =$W$66*(1+$G$66)^5 -> 1159.2741 | CG66: =$W$66*(1+$G$66)^5 -> 1159.2741 | CH66: =$W$66*(1+$G$66)^5 -> 1159.2741 | CI66: =$W$66*(1+$G$66)^5 -> 1159.2741 | CJ66: =$W$66*(1+$G$66)^5 -> 1159.2741 | CK66: =$W$66*(1+$G$66)^5 -> 1159.2741 | CL66: =$W$66*(1+$G$66)^5 -> 1159.2741 | ... CP66: =$W$66*(1+$G$66)^5 -> 1159.2741 | CQ66: =$W$66*(1+$G$66)^6 -> 1194.0523 | CR66: =$W$66*(1+$G$66)^6 -> 1194.0523 | CS66: =$W$66*(1+$G$66)^6 -> 1194.0523 | CT66: =$W$66*(1+$G$66)^6 -> 1194.0523 | CU66: =$W$66*(1+$G$66)^6 -> 1194.0523 | CV66: =$W$66*(1+$G$66)^6 -> 1194.0523 | CW66: =$W$66*(1+$G$66)^6 -> 1194.0523 | CX66: =$W$66*(1+$G$66)^6 -> 1194.0523 | ... DB66: =$W$66*(1+$G$66)^6 -> 1194.0523 | DC66: =$W$66*(1+$G$66)^7 -> 1229.8739 | DD66: =$W$66*(1+$G$66)^7 -> 1229.8739 | DE66: =$W$66*(1+$G$66)^7 -> 1229.8739 | DF66: =$W$66*(1+$G$66)^7 -> 1229.8739 | DG66: =$W$66*(1+$G$66)^7 -> 1229.8739 | DH66: =$W$66*(1+$G$66)^7 -> 1229.8739 | DI66: =$W$66*(1+$G$66)^7 -> 1229.8739 | DJ66: =$W$66*(1+$G$66)^7 -> 1229.8739 | ... DN66: =$W$66*(1+$G$66)^7 -> 1229.8739 | DP66: =SUM(J66:DN66) -> 106708.03
E67: ='Table 3.0'!E95 -> Pest Control | G67: ='Table 3.0'!G95 -> 0.03 | H67: YoY Growth | W67: 500 | X67: =W67 -> 500 | Y67: =X67 -> 500 | Z67: =Y67 -> 500 | AA67: =Z67 -> 500 | AB67: =AA67 -> 500 | AC67: =AB67 -> 500 | AD67: =AC67 -> 500 | AE67: =AD67 -> 500 | ... AH67: =AG67 -> 500 | AI67: =$W$67*(1+$G$67) -> 515 | AJ67: =$W$67*(1+$G$67) -> 515 | AK67: =$W$67*(1+$G$67) -> 515 | AL67: =$W$67*(1+$G$67) -> 515 | AM67: =$W$67*(1+$G$67) -> 515 | AN67: =$W$67*(1+$G$67) -> 515 | AO67: =$W$67*(1+$G$67) -> 515 | AP67: =$W$67*(1+$G$67) -> 515 | ... AT67: =$W$67*(1+$G$67) -> 515 | AU67: =$W$67*(1+$G$67)^2 -> 530.45 | AV67: =$W$67*(1+$G$67)^2 -> 530.45 | AW67: =$W$67*(1+$G$67)^2 -> 530.45 | AX67: =$W$67*(1+$G$67)^2 -> 530.45 | AY67: =$W$67*(1+$G$67)^2 -> 530.45 | AZ67: =$W$67*(1+$G$67)^2 -> 530.45 | BA67: =$W$67*(1+$G$67)^2 -> 530.45 | BB67: =$W$67*(1+$G$67)^2 -> 530.45 | ... BF67: =$W$67*(1+$G$67)^2 -> 530.45 | BG67: =$W$67*(1+$G$67)^3 -> 546.3635 | BH67: =$W$67*(1+$G$67)^3 -> 546.3635 | BI67: =$W$67*(1+$G$67)^3 -> 546.3635 | BJ67: =$W$67*(1+$G$67)^3 -> 546.3635 | BK67: =$W$67*(1+$G$67)^3 -> 546.3635 | BL67: =$W$67*(1+$G$67)^3 -> 546.3635 | BM67: =$W$67*(1+$G$67)^3 -> 546.3635 | BN67: =$W$67*(1+$G$67)^3 -> 546.3635 | ... BR67: =$W$67*(1+$G$67)^3 -> 546.3635 | BS67: =$W$67*(1+$G$67)^4 -> 562.7544 | BT67: =$W$67*(1+$G$67)^4 -> 562.7544 | BU67: =$W$67*(1+$G$67)^4 -> 562.7544 | BV67: =$W$67*(1+$G$67)^4 -> 562.7544 | BW67: =$W$67*(1+$G$67)^4 -> 562.7544 | BX67: =$W$67*(1+$G$67)^4 -> 562.7544 | BY67: =$W$67*(1+$G$67)^4 -> 562.7544 | BZ67: =$W$67*(1+$G$67)^4 -> 562.7544 | ... CD67: =$W$67*(1+$G$67)^4 -> 562.7544 | CE67: =$W$67*(1+$G$67)^5 -> 579.63704 | CF67: =$W$67*(1+$G$67)^5 -> 579.63704 | CG67: =$W$67*(1+$G$67)^5 -> 579.63704 | CH67: =$W$67*(1+$G$67)^5 -> 579.63704 | CI67: =$W$67*(1+$G$67)^5 -> 579.63704 | CJ67: =$W$67*(1+$G$67)^5 -> 579.63704 | CK67: =$W$67*(1+$G$67)^5 -> 579.63704 | CL67: =$W$67*(1+$G$67)^5 -> 579.63704 | ... CP67: =$W$67*(1+$G$67)^5 -> 579.63704 | CQ67: =$W$67*(1+$G$67)^6 -> 597.02615 | CR67: =$W$67*(1+$G$67)^6 -> 597.02615 | CS67: =$W$67*(1+$G$67)^6 -> 597.02615 | CT67: =$W$67*(1+$G$67)^6 -> 597.02615 | CU67: =$W$67*(1+$G$67)^6 -> 597.02615 | CV67: =$W$67*(1+$G$67)^6 -> 597.02615 | CW67: =$W$67*(1+$G$67)^6 -> 597.02615 | CX67: =$W$67*(1+$G$67)^6 -> 597.02615 | ... DB67: =$W$67*(1+$G$67)^6 -> 597.02615 | DC67: =$W$67*(1+$G$67)^7 -> 614.93693 | DD67: =$W$67*(1+$G$67)^7 -> 614.93693 | DE67: =$W$67*(1+$G$67)^7 -> 614.93693 | DF67: =$W$67*(1+$G$67)^7 -> 614.93693 | DG67: =$W$67*(1+$G$67)^7 -> 614.93693 | DH67: =$W$67*(1+$G$67)^7 -> 614.93693 | DI67: =$W$67*(1+$G$67)^7 -> 614.93693 | DJ67: =$W$67*(1+$G$67)^7 -> 614.93693 | ... DN67: =$W$67*(1+$G$67)^7 -> 614.93693 | DP67: =SUM(J67:DN67) -> 53354.016
E68: ='Table 3.0'!E96 -> Fire Prevention | G68: ='Table 3.0'!G96 -> 0.03 | H68: YoY Growth | W68: 250 | X68: =W68 -> 250 | Y68: =X68 -> 250 | Z68: =Y68 -> 250 | AA68: =Z68 -> 250 | AB68: =AA68 -> 250 | AC68: =AB68 -> 250 | AD68: =AC68 -> 250 | AE68: =AD68 -> 250 | ... AH68: =AG68 -> 250 | AI68: =$W$68*(1+$G$68) -> 257.5 | AJ68: =$W$68*(1+$G$68) -> 257.5 | AK68: =$W$68*(1+$G$68) -> 257.5 | AL68: =$W$68*(1+$G$68) -> 257.5 | AM68: =$W$68*(1+$G$68) -> 257.5 | AN68: =$W$68*(1+$G$68) -> 257.5 | AO68: =$W$68*(1+$G$68) -> 257.5 | AP68: =$W$68*(1+$G$68) -> 257.5 | ... AT68: =$W$68*(1+$G$68) -> 257.5 | AU68: =$W$68*(1+$G$68)^2 -> 265.225 | AV68: =$W$68*(1+$G$68)^2 -> 265.225 | AW68: =$W$68*(1+$G$68)^2 -> 265.225 | AX68: =$W$68*(1+$G$68)^2 -> 265.225 | AY68: =$W$68*(1+$G$68)^2 -> 265.225 | AZ68: =$W$68*(1+$G$68)^2 -> 265.225 | BA68: =$W$68*(1+$G$68)^2 -> 265.225 | BB68: =$W$68*(1+$G$68)^2 -> 265.225 | ... BF68: =$W$68*(1+$G$68)^2 -> 265.225 | BG68: =$W$68*(1+$G$68)^3 -> 273.18175 | BH68: =$W$68*(1+$G$68)^3 -> 273.18175 | BI68: =$W$68*(1+$G$68)^3 -> 273.18175 | BJ68: =$W$68*(1+$G$68)^3 -> 273.18175 | BK68: =$W$68*(1+$G$68)^3 -> 273.18175 | BL68: =$W$68*(1+$G$68)^3 -> 273.18175 | BM68: =$W$68*(1+$G$68)^3 -> 273.18175 | BN68: =$W$68*(1+$G$68)^3 -> 273.18175 | ... BR68: =$W$68*(1+$G$68)^3 -> 273.18175 | BS68: =$W$68*(1+$G$68)^4 -> 281.3772 | BT68: =$W$68*(1+$G$68)^4 -> 281.3772 | BU68: =$W$68*(1+$G$68)^4 -> 281.3772 | BV68: =$W$68*(1+$G$68)^4 -> 281.3772 | BW68: =$W$68*(1+$G$68)^4 -> 281.3772 | BX68: =$W$68*(1+$G$68)^4 -> 281.3772 | BY68: =$W$68*(1+$G$68)^4 -> 281.3772 | BZ68: =$W$68*(1+$G$68)^4 -> 281.3772 | ... CD68: =$W$68*(1+$G$68)^4 -> 281.3772 | CE68: =$W$68*(1+$G$68)^5 -> 289.81852 | CF68: =$W$68*(1+$G$68)^5 -> 289.81852 | CG68: =$W$68*(1+$G$68)^5 -> 289.81852 | CH68: =$W$68*(1+$G$68)^5 -> 289.81852 | CI68: =$W$68*(1+$G$68)^5 -> 289.81852 | CJ68: =$W$68*(1+$G$68)^5 -> 289.81852 | CK68: =$W$68*(1+$G$68)^5 -> 289.81852 | CL68: =$W$68*(1+$G$68)^5 -> 289.81852 | ... CP68: =$W$68*(1+$G$68)^5 -> 289.81852 | CQ68: =$W$68*(1+$G$68)^6 -> 298.51307 | CR68: =$W$68*(1+$G$68)^6 -> 298.51307 | CS68: =$W$68*(1+$G$68)^6 -> 298.51307 | CT68: =$W$68*(1+$G$68)^6 -> 298.51307 | CU68: =$W$68*(1+$G$68)^6 -> 298.51307 | CV68: =$W$68*(1+$G$68)^6 -> 298.51307 | CW68: =$W$68*(1+$G$68)^6 -> 298.51307 | CX68: =$W$68*(1+$G$68)^6 -> 298.51307 | ... DB68: =$W$68*(1+$G$68)^6 -> 298.51307 | DC68: =$W$68*(1+$G$68)^7 -> 307.46847 | DD68: =$W$68*(1+$G$68)^7 -> 307.46847 | DE68: =$W$68*(1+$G$68)^7 -> 307.46847 | DF68: =$W$68*(1+$G$68)^7 -> 307.46847 | DG68: =$W$68*(1+$G$68)^7 -> 307.46847 | DH68: =$W$68*(1+$G$68)^7 -> 307.46847 | DI68: =$W$68*(1+$G$68)^7 -> 307.46847 | DJ68: =$W$68*(1+$G$68)^7 -> 307.46847 | ... DN68: =$W$68*(1+$G$68)^7 -> 307.46847 | DP68: =SUM(J68:DN68) -> 26677.008
E69: ='Table 3.0'!E97 -> Waste Disposal | G69: ='Table 3.0'!G97 -> 0.03 | H69: YoY Growth | W69: 250 | X69: =W69 -> 250 | Y69: =X69 -> 250 | Z69: =Y69 -> 250 | AA69: =Z69 -> 250 | AB69: =AA69 -> 250 | AC69: =AB69 -> 250 | AD69: =AC69 -> 250 | AE69: =AD69 -> 250 | ... AH69: =AG69 -> 250 | AI69: =$W$69*(1+$G$69) -> 257.5 | AJ69: =$W$69*(1+$G$69) -> 257.5 | AK69: =$W$69*(1+$G$69) -> 257.5 | AL69: =$W$69*(1+$G$69) -> 257.5 | AM69: =$W$69*(1+$G$69) -> 257.5 | AN69: =$W$69*(1+$G$69) -> 257.5 | AO69: =$W$69*(1+$G$69) -> 257.5 | AP69: =$W$69*(1+$G$69) -> 257.5 | ... AT69: =$W$69*(1+$G$69) -> 257.5 | AU69: =$W$69*(1+$G$69)^2 -> 265.225 | AV69: =$W$69*(1+$G$69)^2 -> 265.225 | AW69: =$W$69*(1+$G$69)^2 -> 265.225 | AX69: =$W$69*(1+$G$69)^2 -> 265.225 | AY69: =$W$69*(1+$G$69)^2 -> 265.225 | AZ69: =$W$69*(1+$G$69)^2 -> 265.225 | BA69: =$W$69*(1+$G$69)^2 -> 265.225 | BB69: =$W$69*(1+$G$69)^2 -> 265.225 | ... BF69: =$W$69*(1+$G$69)^2 -> 265.225 | BG69: =$W$69*(1+$G$69)^3 -> 273.18175 | BH69: =$W$69*(1+$G$69)^3 -> 273.18175 | BI69: =$W$69*(1+$G$69)^3 -> 273.18175 | BJ69: =$W$69*(1+$G$69)^3 -> 273.18175 | BK69: =$W$69*(1+$G$69)^3 -> 273.18175 | BL69: =$W$69*(1+$G$69)^3 -> 273.18175 | BM69: =$W$69*(1+$G$69)^3 -> 273.18175 | BN69: =$W$69*(1+$G$69)^3 -> 273.18175 | ... BR69: =$W$69*(1+$G$69)^3 -> 273.18175 | BS69: =$W$69*(1+$G$69)^4 -> 281.3772 | BT69: =$W$69*(1+$G$69)^4 -> 281.3772 | BU69: =$W$69*(1+$G$69)^4 -> 281.3772 | BV69: =$W$69*(1+$G$69)^4 -> 281.3772 | BW69: =$W$69*(1+$G$69)^4 -> 281.3772 | BX69: =$W$69*(1+$G$69)^4 -> 281.3772 | BY69: =$W$69*(1+$G$69)^4 -> 281.3772 | BZ69: =$W$69*(1+$G$69)^4 -> 281.3772 | ... CD69: =$W$69*(1+$G$69)^4 -> 281.3772 | CE69: =$W$69*(1+$G$69)^5 -> 289.81852 | CF69: =$W$69*(1+$G$69)^5 -> 289.81852 | CG69: =$W$69*(1+$G$69)^5 -> 289.81852 | CH69: =$W$69*(1+$G$69)^5 -> 289.81852 | CI69: =$W$69*(1+$G$69)^5 -> 289.81852 | CJ69: =$W$69*(1+$G$69)^5 -> 289.81852 | CK69: =$W$69*(1+$G$69)^5 -> 289.81852 | CL69: =$W$69*(1+$G$69)^5 -> 289.81852 | ... CP69: =$W$69*(1+$G$69)^5 -> 289.81852 | CQ69: =$W$69*(1+$G$69)^6 -> 298.51307 | CR69: =$W$69*(1+$G$69)^6 -> 298.51307 | CS69: =$W$69*(1+$G$69)^6 -> 298.51307 | CT69: =$W$69*(1+$G$69)^6 -> 298.51307 | CU69: =$W$69*(1+$G$69)^6 -> 298.51307 | CV69: =$W$69*(1+$G$69)^6 -> 298.51307 | CW69: =$W$69*(1+$G$69)^6 -> 298.51307 | CX69: =$W$69*(1+$G$69)^6 -> 298.51307 | ... DB69: =$W$69*(1+$G$69)^6 -> 298.51307 | DC69: =$W$69*(1+$G$69)^7 -> 307.46847 | DD69: =$W$69*(1+$G$69)^7 -> 307.46847 | DE69: =$W$69*(1+$G$69)^7 -> 307.46847 | DF69: =$W$69*(1+$G$69)^7 -> 307.46847 | DG69: =$W$69*(1+$G$69)^7 -> 307.46847 | DH69: =$W$69*(1+$G$69)^7 -> 307.46847 | DI69: =$W$69*(1+$G$69)^7 -> 307.46847 | DJ69: =$W$69*(1+$G$69)^7 -> 307.46847 | ... DN69: =$W$69*(1+$G$69)^7 -> 307.46847 | DP69: =SUM(J69:DN69) -> 26677.008
D70: ='Table 3.0'!D98 -> Property Taxes | G70: ='Table 3.0'!G98 -> 0.12 | H70: YoY Growth | T70: 40000 | W70: 0 | X70: =W70 -> 0 | Y70: =X70 -> 0 | Z70: =Y70 -> 0 | AA70: =Z70 -> 0 | AB70: =AA70 -> 0 | AC70: =AB70 -> 0 | AD70: =AC70 -> 0 | AE70: =T70*(1+$G$70) -> 44800 | AF70: 0 | AG70: =AF70 -> 0 | AH70: =AG70 -> 0 | AQ70: =AE70*(1+$G$70) -> 50176 | BC70: =AQ70*(1+$G$70) -> 56197.12 | BO70: =BC70*(1+$G$70) -> 62940.774 | CA70: =BO70*(1+$G$70) -> 70493.667 | CM70: =CA70*(1+$G$70) -> 78952.907 | CY70: =CM70*(1+$G$70) -> 88427.256 | DK70: =CY70*(1+$G$70) -> 99038.527 | DP70: =SUM(J70:DN70) -> 591026.25
D71: ='Table 3.0'!D99 -> Insurance
E72: ='Table 3.0'!E100 -> General Liability | G72: ='Table 3.0'!G100 -> 0.1 | H72: YoY Growth | T72: 5300 | AE72: =T72*(1+$G$72) -> 5830 | AQ72: =AE72*(1+$G$72) -> 6413 | BC72: =AQ72*(1+$G$72) -> 7054.3 | BO72: =BC72*(1+$G$72) -> 7759.73 | CA72: =BO72*(1+$G$72) -> 8535.703 | CM72: =CA72*(1+$G$72) -> 9389.2733 | CY72: =CM72*(1+$G$72) -> 10328.201 | DK72: =CY72*(1+$G$72) -> 11361.021 | DP72: =SUM(J72:DN72) -> 71971.228
E73: ='Table 3.0'!E101 -> Builders Risk | G73: ='Table 3.0'!G101 -> 0 | H73: YoY Growth | T73: 3000 | DP73: =SUM(J73:DN73) -> 3000
E74: ='Table 3.0'!E102 -> Other | G74: ='Table 3.0'!G102 -> 0 | H74: YoY Growth | T74: 0 | AE74: =T74*(1+$G$74) -> 0 | AQ74: =AE74*(1+$G$72) -> 0 | BC74: =AQ74*(1+$G$72) -> 0 | BO74: =BC74*(1+$G$72) -> 0 | CA74: =BO74*(1+$G$72) -> 0 | CM74: =CA74*(1+$G$72) -> 0 | CY74: =CM74*(1+$G$72) -> 0 | DK74: =CY74*(1+$G$72) -> 0 | DP74: =SUM(J74:DN74) -> 0
D75: ='Table 3.0'!D103 -> Total Undistributed Expenses | K75: =SUM(K46:K74) -> 0 | L75: =SUM(L46:L74) -> 0 | M75: =SUM(M46:M74) -> 0 | N75: =SUM(N46:N74) -> 0 | O75: =SUM(O46:O74) -> 0 | P75: =SUM(P46:P74) -> 0 | Q75: =SUM(Q46:Q74) -> 0 | R75: =SUM(R46:R74) -> 0 | ... DN75: =SUM(DN46:DN74) -> 17124.952 | DP75: =SUM(J75:DN75) -> 2165147.9
C77: ='Table 3.0'!C105 -> TOTAL OPERATING EXPENSES | K77: =K43+K75 -> 0 | L77: =L43+L75 -> 0 | M77: =M43+M75 -> 0 | N77: =N43+N75 -> 0 | O77: =O43+O75 -> 0 | P77: =P43+P75 -> 0 | Q77: =Q43+Q75 -> 0 | R77: =R43+R75 -> 0 | ... DN77: =DN43+DN75 -> 47277.36
C79: ='Table 3.0'!C107 -> NET OPERATING INCOME (NOI) | K79: =K26-K77 -> 0 | L79: =L26-L77 -> 0 | M79: =M26-M77 -> 0 | N79: =N26-N77 -> 0 | O79: =O26-O77 -> 0 | P79: =P26-P77 -> 0 | Q79: =Q26-Q77 -> 0 | R79: =R26-R77 -> 0 | ... DN79: =DN26-DN77 -> 23815.64 | DP79: =SUM(J79:DJ79) -> 1675289.8
C81: ='Table 3.0'!C109 -> NON-OPERATING EXPENSES
D82: ='Table 3.0'!D110 -> Debt Service - Interest
E83: ='Table 3.0'!E111 -> Acquisition Loan (Int. Rate) | G83: ='Table 3.0'!G111 -> 0.095 | K83: ='Table 3.0'!$M$22/12*Balances!I8 -> 9302.0833 | L83: ='Table 3.0'!$M$22/12*Balances!J8 -> 9302.0833 | M83: ='Table 3.0'!$M$22/12*Balances!K8 -> 9302.0833 | N83: ='Table 3.0'!$M$22/12*Balances!L8 -> 9302.0833 | O83: ='Table 3.0'!$M$22/12*Balances!M8 -> 9302.0833 | P83: ='Table 3.0'!$M$22/12*Balances!N8 -> 9302.0833 | Q83: ='Table 3.0'!$M$22/12*Balances!O8 -> 9302.0833 | R83: ='Table 3.0'!$M$22/12*Balances!P8 -> 9302.0833 | ... DN83: ='Table 3.0'!$M$22/12*Balances!DL8 -> 7427.8124 | DP83: =SUM(J83:DJ83) -> 818334.4
E84: ='Table 3.0'!E112 -> Seller Carryback (Int. Rate) | G84: ='Table 3.0'!G112 -> N/A | K84: ='Table 3.0'!$M$23/12*Balances!I15 -> 0 | L84: ='Table 3.0'!$M$23/12*Balances!J15 -> 0 | M84: ='Table 3.0'!$M$23/12*Balances!K15 -> 0 | N84: ='Table 3.0'!$M$23/12*Balances!L15 -> 0 | O84: ='Table 3.0'!$M$23/12*Balances!M15 -> 0 | P84: ='Table 3.0'!$M$23/12*Balances!N15 -> 0 | Q84: ='Table 3.0'!$M$23/12*Balances!O15 -> 0 | R84: ='Table 3.0'!$M$23/12*Balances!P15 -> 0 | ... DN84: ='Table 3.0'!$M$23/12*Balances!DL15 -> 0 | DP84: =SUM(J84:DJ84) -> 0
E85: ='Table 3.0'!E113 -> Construction Loan (Int. Rate) | G85: ='Table 3.0'!G113 -> 0.095 | K85: ='Table 3.0'!$M$24/12*Balances!I22 -> 0 | L85: ='Table 3.0'!$M$24/12*Balances!J22 -> 0 | M85: ='Table 3.0'!$M$24/12*Balances!K22 -> 0 | N85: ='Table 3.0'!$M$24/12*Balances!L22 -> 0 | O85: ='Table 3.0'!$M$24/12*Balances!M22 -> 0 | P85: ='Table 3.0'!$M$24/12*Balances!N22 -> 641.46705 | Q85: ='Table 3.0'!$M$24/12*Balances!O22 -> 3586.9583 | R85: ='Table 3.0'!$M$24/12*Balances!P22 -> 6122.758 | ... DN85: ='Table 3.0'!$M$24/12*Balances!DL22 -> 4415.0092 | DP85: =SUM(J85:DJ85) -> 378979.51
E86: ='Table 3.0'!E114 -> Permanent Loan (Int. Rate) | G86: ='Table 3.0'!G114 -> 0.06 | K86: ='Table 3.0'!$M$28/12*Balances!I29 -> 0 | L86: ='Table 3.0'!$M$28/12*Balances!J29 -> 0 | M86: ='Table 3.0'!$M$28/12*Balances!K29 -> 0 | N86: ='Table 3.0'!$M$28/12*Balances!L29 -> 0 | O86: ='Table 3.0'!$M$28/12*Balances!M29 -> 0 | P86: ='Table 3.0'!$M$28/12*Balances!N29 -> 0 | Q86: ='Table 3.0'!$M$28/12*Balances!O29 -> 0 | R86: ='Table 3.0'!$M$28/12*Balances!P29 -> 0 | ... DN86: ='Table 3.0'!$M$28/12*Balances!DL29 -> 9958.6089 | DP86: =SUM(J86:DJ86) -> 895614.45
D87: ='Table 3.0'!D115 -> Total Debt Service | K87: =SUM(K83:K86) -> 9302.0833 | L87: =SUM(L83:L86) -> 9302.0833 | M87: =SUM(M83:M86) -> 9302.0833 | N87: =SUM(N83:N86) -> 9302.0833 | O87: =SUM(O83:O86) -> 9302.0833 | P87: =SUM(P83:P86) -> 9943.5504 | Q87: =SUM(Q83:Q86) -> 12889.042 | R87: =SUM(R83:R86) -> 15424.841 | ... DJ87: =SUM(DJ83:DJ86) -> 20897.198 | DP87: =SUM(J87:DJ87) -> 2092928.4
D89: ='Table 3.0'!D117 -> Refinance Points & Fees | K89: =IF(K119>0,(('Table 3.0'!$Q$28*Monthly!K119)+'Table 3.0'!$R$28),0) -> 0 | L89: =IF(L119>0,(('Table 3.0'!$Q$28*Monthly!L119)+'Table 3.0'!$R$28),0) -> 0 | M89: =IF(M119>0,(('Table 3.0'!$Q$28*Monthly!M119)+'Table 3.0'!$R$28),0) -> 0 | N89: =IF(N119>0,(('Table 3.0'!$Q$28*Monthly!N119)+'Table 3.0'!$R$28),0) -> 0 | O89: =IF(O119>0,(('Table 3.0'!$Q$28*Monthly!O119)+'Table 3.0'!$R$28),0) -> 0 | P89: =IF(P119>0,(('Table 3.0'!$Q$28*Monthly!P119)+'Table 3.0'!$R$28),0) -> 0 | Q89: =IF(Q119>0,(('Table 3.0'!$Q$28*Monthly!Q119)+'Table 3.0'!$R$28),0) -> 0 | R89: =IF(R119>0,(('Table 3.0'!$Q$28*Monthly!R119)+'Table 3.0'!$R$28),0) -> 0 | ... DN89: =IF(DN119>0,(('Table 3.0'!$Q$28*Monthly!DN119)+'Table 3.0'!$R$28),0) -> 0 | DP89: =SUM(J89:DJ89) -> 36290
D90: ='Table 3.0'!D118 -> Other | K90: =J90 -> 0 | L90: =K90 -> 0 | M90: =L90 -> 0 | N90: =M90 -> 0 | O90: =N90 -> 0 | P90: =O90 -> 0 | Q90: =P90 -> 0 | R90: =Q90 -> 0 | ... DN90: =DM90 -> 0 | DP90: =SUM(J90:DJ90) -> 0
C91: ='Table 3.0'!C119 -> TOTAL NON-OPERATING EXPENSE | K91: =SUM(K87:K90) -> 9302.0833 | L91: =SUM(L87:L90) -> 9302.0833 | M91: =SUM(M87:M90) -> 9302.0833 | N91: =SUM(N87:N90) -> 9302.0833 | O91: =SUM(O87:O90) -> 9302.0833 | P91: =SUM(P87:P90) -> 9943.5504 | Q91: =SUM(Q87:Q90) -> 12889.042 | R91: =SUM(R87:R90) -> 15424.841 | ... DN91: =SUM(DN87:DN90) -> 0 | DP91: =SUM(J91:DJ91) -> 2129218.4
C93: ='Table 3.0'!C121 -> NET INCOME | K93: =K79-K91 -> -9302.0833 | L93: =L79-L91 -> -9302.0833 | M93: =M79-M91 -> -9302.0833 | N93: =N79-N91 -> -9302.0833 | O93: =O79-O91 -> -9302.0833 | P93: =P79-P91 -> -9943.5504 | Q93: =Q79-Q91 -> -12889.042 | R93: =R79-R91 -> -15424.841 | ... DN93: =DN79-DN91 -> 23815.64 | DP93: =SUM(J93:DJ93) -> -453928.55
C95: ='Table 3.0'!C123 -> DEVELOPMENT COSTS
D96: ='Table 3.0'!D124 -> Hard Costs
E97: ='Table 3.0'!E125 -> Unit Construction | K97: ='Cost Curves'!K11 -> 0 | L97: ='Cost Curves'!L11 -> 0 | M97: ='Cost Curves'!M11 -> 0 | N97: ='Cost Curves'!N11 -> 0 | O97: ='Cost Curves'!O11 -> 0 | P97: ='Cost Curves'!P11 -> 0 | Q97: ='Cost Curves'!Q11 -> 0 | R97: ='Cost Curves'!R11 -> 0 | ... DN97: ='Cost Curves'!DN11 -> 0 | DP97: =SUM(J97:DN97) -> 0
E98: ='Table 3.0'!E126 -> Site Work | K98: ='Cost Curves'!K17 -> 68450 | L98: ='Cost Curves'!L17 -> 136900 | M98: ='Cost Curves'!M17 -> 136900 | N98: ='Cost Curves'!N17 -> 205350 | O98: ='Cost Curves'!O17 -> 136900 | P98: ='Cost Curves'!P17 -> 273800 | Q98: ='Cost Curves'!Q17 -> 205350 | R98: ='Cost Curves'!R17 -> 205350 | ... DN98: ='Cost Curves'!DN17 -> 0 | DP98: =SUM(J98:DN98) -> 1369000
E99: ='Table 3.0'!E127 -> Contractor Fee & Overhead (% of HC, $ Amt. (Mo.)) | K99: 10000 | L99: 10000 | M99: 10000 | N99: 10000 | O99: 10000 | P99: 10000 | Q99: 10000 | R99: 10000 | S99: 10000 | T99: 10000 | U99: 10000 | V99: 10000 | W99: 0 | X99: =W99 -> 0 | Y99: =X99 -> 0 | Z99: =Y99 -> 0 | AA99: =Z99 -> 0 | AB99: =AA99 -> 0 | AC99: =AB99 -> 0 | AD99: =AC99 -> 0 | AE99: =AD99 -> 0 | ... AK99: =AJ99 -> 0 | AL99: 0 | AM99: 0 | AN99: 0 | AO99: 0 | AP99: 0 | AQ99: 0 | AR99: 0 | AS99: 0 | AT99: 0 | AU99: 0 | AV99: 0 | AW99: 0 | AX99: 0 | AY99: 0 | AZ99: 0 | BA99: 0 | BB99: 0 | BC99: 0 | BD99: 0 | BE99: 0 | BF99: 0 | BG99: 0 | BH99: 0 | BI99: 0 | BJ99: 0 | BK99: 0 | BL99: 0 | BM99: 0 | BN99: 0 | BO99: 0 | BP99: 0 | BQ99: 0 | BR99: 0 | BS99: 0 | BT99: 0 | BU99: 0 | BV99: 0 | BW99: 0 | BX99: 0 | BY99: 0 | BZ99: 0 | CA99: 0 | CB99: 0 | CC99: 0 | CD99: 0 | CE99: 0 | CF99: 0 | CG99: 0 | CH99: 0 | CI99: 0 | CJ99: 0 | CK99: 0 | CL99: 0 | CM99: 0 | CN99: 0 | CO99: 0 | CP99: 0 | CQ99: 0 | CR99: 0 | CS99: 0 | CT99: 0 | CU99: 0 | CV99: 0 | CW99: 0 | CX99: 0 | CY99: 0 | CZ99: 0 | DA99: 0 | DB99: 0 | DC99: 0 | DD99: 0 | DE99: 0 | DF99: 0 | DG99: 0 | DH99: 0 | DI99: 0 | DJ99: 0 | DK99: 0 | DL99: 0 | DM99: 0 | DN99: 0 | DP99: =SUM(J99:DN99) -> 120000
E100: Contractor Fee Equalization (Min $ per Mo.) | H100: ='Table 3.0'!H128 -> 0 | K100: =Worksheet!U43 -> 0 | L100: =Worksheet!V43 -> 0 | M100: =Worksheet!W43 -> 0 | N100: =Worksheet!X43 -> 0 | O100: =Worksheet!Y43 -> 0 | P100: =Worksheet!Z43 -> 0 | Q100: =Worksheet!AA43 -> 0 | R100: =Worksheet!AB43 -> 0 | ... CL100: =Worksheet!CV43 -> 0 | CM100: =Worksheet!DI43 -> 0 | CN100: =Worksheet!DJ43 -> 0 | CO100: =Worksheet!DK43 -> 0 | CP100: =Worksheet!DL43 -> 0 | CQ100: =Worksheet!DM43 -> 0 | CR100: =Worksheet!DN43 -> 0 | CS100: =Worksheet!DO43 -> 0 | CT100: =Worksheet!DP43 -> 0 | ... DN100: =Worksheet!EJ43 -> 0 | DP100: =SUM(J100:DN100) -> 0
E101: ='Table 3.0'!E129 -> Amenities | K101: ='Cost Curves'!K26 -> 125500 | L101: ='Cost Curves'!L26 -> 42670 | M101: ='Cost Curves'!M26 -> 30120 | N101: ='Cost Curves'!N26 -> 25100 | O101: ='Cost Curves'!O26 -> 47690 | P101: ='Cost Curves'!P26 -> 20080 | Q101: ='Cost Curves'!Q26 -> 37650 | R101: ='Cost Curves'!R26 -> 20080 | ... DN101: ='Cost Curves'!DN26 -> 0 | DP101: =SUM(J101:DN101) -> 631000
E102: ='Table 3.0'!E130 -> FF&E | K102: ='Cost Curves'!K32 -> 0 | L102: ='Cost Curves'!L32 -> 0 | M102: ='Cost Curves'!M32 -> 0 | N102: ='Cost Curves'!N32 -> 0 | O102: ='Cost Curves'!O32 -> 33300 | P102: ='Cost Curves'!P32 -> 33300 | Q102: ='Cost Curves'!Q32 -> 33300 | R102: ='Cost Curves'!R32 -> 33300 | ... DN102: ='Cost Curves'!DN32 -> 0 | DP102: =SUM(J102:DN102) -> 222000
E103: ='Table 3.0'!E131 -> Temporary Utility Costs | K103: =IF(K97+K98+K101+K102>0,250,0) -> 250 | L103: =IF(L97+L98+L101+L102>0,250,0) -> 250 | M103: =IF(M97+M98+M101+M102>0,250,0) -> 250 | N103: =IF(N97+N98+N101+N102>0,250,0) -> 250 | O103: =IF(O97+O98+O101+O102>0,250,0) -> 250 | P103: =IF(P97+P98+P101+P102>0,250,0) -> 250 | Q103: =IF(Q97+Q98+Q101+Q102>0,250,0) -> 250 | R103: =IF(R97+R98+R101+R102>0,250,0) -> 250 | ... DN103: =IF(DN97+DN98+DN101+DN102>0,250,0) -> 0 | DP103: =SUM(J103:DN103) -> 3000
E104: ='Table 3.0'!E132 -> Temporary Portable Toilet Rental | K104: =IF(K97+K98+K101+K102>0,150,0) -> 150 | L104: =IF(L97+L98+L101+L102>0,150,0) -> 150 | M104: =IF(M97+M98+M101+M102>0,150,0) -> 150 | N104: =IF(N97+N98+N101+N102>0,150,0) -> 150 | O104: =IF(O97+O98+O101+O102>0,150,0) -> 150 | P104: =IF(P97+P98+P101+P102>0,150,0) -> 150 | Q104: =IF(Q97+Q98+Q101+Q102>0,150,0) -> 150 | R104: =IF(R97+R98+R101+R102>0,150,0) -> 150 | ... DN104: =IF(DN97+DN98+DN101+DN102>0,150,0) -> 0 | DP104: =SUM(J104:DN104) -> 1800
E105: ='Table 3.0'!E133 -> Contingency (% of HC & SC) | G105: ='Table 3.0'!G133 -> 0.075 | K105: =$G$105*(K97+K98+K101+K102+K108) -> 20148.75 | L105: =$G$105*(L97+L98+L101+L102+L108) -> 17202.75 | M105: =$G$105*(M97+M98+M101+M102+M108) -> 13460.25 | N105: =$G$105*(N97+N98+N101+N102+N108) -> 18217.5 | O105: =$G$105*(O97+O98+O101+O102+O108) -> 16341.75 | P105: =$G$105*(P97+P98+P101+P102+P108) -> 24538.5 | Q105: =$G$105*(Q97+Q98+Q101+Q102+Q108) -> 20722.5 | R105: =$G$105*(R97+R98+R101+R102+R108) -> 45549.75 | ... DN105: =$G$105*(DN97+DN98+DN101+DN102+DN108) -> 0 | DP105: =SUM(J105:DN105) -> 204000
D106: ='Table 3.0'!D134 -> Total Hard Cost | K106: =SUM(K97:K105) -> 224498.75 | L106: =SUM(L97:L105) -> 207172.75 | M106: =SUM(M97:M105) -> 190880.25 | N106: =SUM(N97:N105) -> 259067.5 | O106: =SUM(O97:O105) -> 244631.75 | P106: =SUM(P97:P105) -> 362118.5 | Q106: =SUM(Q97:Q105) -> 307422.5 | R106: =SUM(R97:R105) -> 314679.75 | ... DN106: =SUM(DN97:DN105) -> 0 | DP106: =SUM(J106:DO106) -> 2550800
D108: ='Table 3.0'!D136 -> Soft Costs | K108: ='Cost Curves'!K38 -> 74700 | L108: ='Cost Curves'!L38 -> 49800 | M108: ='Cost Curves'!M38 -> 12450 | N108: ='Cost Curves'!N38 -> 12450 | O108: ='Cost Curves'!O38 -> 0 | P108: ='Cost Curves'!P38 -> 0 | Q108: ='Cost Curves'!Q38 -> 0 | R108: ='Cost Curves'!R38 -> 348600 | ... DN108: ='Cost Curves'!DN38 -> 0 | DP108: =SUM(J108:DJ108) -> 498000
C110: ='Table 3.0'!C138 -> TOTAL DEVELOPMENT COSTS | K110: =K106+K108 -> 299198.75 | L110: =L106+L108 -> 256972.75 | M110: =M106+M108 -> 203330.25 | N110: =N106+N108 -> 271517.5 | O110: =O106+O108 -> 244631.75 | P110: =P106+P108 -> 362118.5 | Q110: =Q106+Q108 -> 307422.5 | R110: =R106+R108 -> 663279.75 | ... DN110: =DN106+DN108 -> 0 | DP110: =SUM(J110:DJ110) -> 3048800
D112: ='Table 3.0'!D140 -> Principal Payments - Perm. Loan | K112: =J112 -> 0 | L112: =K112 -> 0 | M112: =L112 -> 0 | N112: =M112 -> 0 | O112: =N112 -> 0 | P112: =O112 -> 0 | Q112: =P112 -> 0 | R112: =Q112 -> 0 | ... AH112: =AG112 -> 0 | AI112: ='Perm Loan'!E15 -> 2359.3474 | AJ112: ='Perm Loan'!F15 -> 2371.1442 | AK112: ='Perm Loan'!G15 -> 2382.9999 | AL112: ='Perm Loan'!H15 -> 2394.9149 | AM112: ='Perm Loan'!I15 -> 2406.8895 | AN112: ='Perm Loan'!J15 -> 2418.9239 | AO112: ='Perm Loan'!K15 -> 2431.0185 | AP112: ='Perm Loan'!L15 -> 2443.1736 | ... DN112: ='Perm Loan'!CJ15 -> 3358.3932 | DP112: =SUM(J112:DJ112) -> 228302.97
C114: ='Table 3.0'!C142 -> NET CASH FLOW | K114: =K93-K110-K112 -> -308500.83 | L114: =L93-L110-L112 -> -266274.83 | M114: =M93-M110-M112 -> -212632.33 | N114: =N93-N110-N112 -> -280819.58 | O114: =O93-O110-O112 -> -253933.83 | P114: =P93-P110-P112 -> -372062.05 | Q114: =Q93-Q110-Q112 -> -320311.54 | R114: =R93-R110-R112 -> -678704.59 | ... DN114: =DN93-DN110-DN112 -> 20457.247
C116: ='Table 3.0'!C144 -> CASH FLOW FROM OPERATING & DEVELOPMENT ACTIVITIES | K116: =K114 -> -308500.83 | L116: =L114 -> -266274.83 | M116: =M114 -> -212632.33 | N116: =N114 -> -280819.58 | O116: =O114 -> -253933.83 | P116: =P114 -> -372062.05 | Q116: =Q114 -> -320311.54 | R116: =R114 -> -678704.59 | ... DN116: =DN114 -> 20457.247 | DP116: =SUM(J116:DJ116) -> -3731031.5
D117: ='Table 3.0'!D145 -> Allocation of Working Capital | K117: =ABS(K116) -> 308500.83 | L117: =Balances!J44 -> 266274.83 | M117: =Balances!K44 -> 212632.33 | N117: =Balances!L44 -> 280819.58 | O117: =Balances!M44 -> 172906.42 | P117: =Balances!N44 -> 0 | Q117: =Balances!O44 -> 0 | R117: =Balances!P44 -> 0 | S117: =Balances!Q44 -> 0 | ... DN117: =Balances!DL44 -> 0 | DP117: =SUM(J117:DJ117) -> 1081134
D118: ='Table 3.0'!D146 -> Construction Loan Draw | K118: =IF((K116+K117)>0,0,IF(SUM(K116:K117)=0,0,IF(AND(SUM(K116:K117)<0,'Table 3.0'!$K$24-Balances!I22>-SUM(K116:K117)),-SUM(K116:K117),'Table 3.0'!$K$24-Balances!I22))) -> 0 | L118: =IF((L116+L117)>0,0,IF(SUM(L116:L117)=0,0,IF(AND(SUM(L116:L117)<0,'Table 3.0'!$K$24-Balances!J22>-SUM(L116:L117)),-SUM(L116:L117),'Table 3.0'!$K$24-Balances!J22))) -> 0 | M118: =IF((M116+M117)>0,0,IF(SUM(M116:M117)=0,0,IF(AND(SUM(M116:M117)<0,'Table 3.0'!$K$24-Balances!K22>-SUM(M116:M117)),-SUM(M116:M117),'Table 3.0'!$K$24-Balances!K22))) -> 0 | N118: =IF((N116+N117)>0,0,IF(SUM(N116:N117)=0,0,IF(AND(SUM(N116:N117)<0,'Table 3.0'!$K$24-Balances!L22>-SUM(N116:N117)),-SUM(N116:N117),'Table 3.0'!$K$24-Balances!L22))) -> 0 | O118: =IF((O116+O117)>0,0,IF(SUM(O116:O117)=0,0,IF(AND(SUM(O116:O117)<0,'Table 3.0'!$K$24-Balances!M22>-SUM(O116:O117)),-SUM(O116:O117),'Table 3.0'!$K$24-Balances!M22))) -> 81027.417 | P118: =IF((P116+P117)>0,0,IF(SUM(P116:P117)=0,0,IF(AND(SUM(P116:P117)<0,'Table 3.0'!$K$24-Balances!N22>-SUM(P116:P117)),-SUM(P116:P117),'Table 3.0'!$K$24-Balances!N22))) -> 372062.05 | Q118: =IF((Q116+Q117)>0,0,IF(SUM(Q116:Q117)=0,0,IF(AND(SUM(Q116:Q117)<0,'Table 3.0'!$K$24-Balances!O22>-SUM(Q116:Q117)),-SUM(Q116:Q117),'Table 3.0'!$K$24-Balances!O22))) -> 320311.54 | R118: =IF((R116+R117)>0,0,IF(SUM(R116:R117)=0,0,IF(AND(SUM(R116:R117)<0,'Table 3.0'!$K$24-Balances!P22>-SUM(R116:R117)),-SUM(R116:R117),'Table 3.0'!$K$24-Balances!P22))) -> 678704.59 | ... DN118: =IF((DN116+DN117)>0,0,IF(SUM(DN116:DN117)=0,0,IF(AND(SUM(DN116:DN117)<0,'Table 3.0'!$K$24-Balances!DL22>-SUM(DN116:DN117)),-SUM(DN116:DN117),'Table 3.0'!$K$24-Balances!DL22))) -> 0 | DP118: =SUM(J118:DJ118) -> 2889638.8
D119: ='Table 3.0'!D147 -> Refinance Proceeds - Perm. Loan | K119: 0 | L119: 0 | M119: 0 | N119: 0 | O119: 0 | P119: 0 | Q119: 0 | R119: 0 | S119: 0 | T119: 0 | U119: 0 | V119: 0 | W119: 0 | X119: 0 | Y119: 0 | Z119: 0 | AA119: 0 | AB119: 0 | AC119: 0 | AD119: 0 | AE119: 0 | AF119: 0 | AG119: 0 | AH119: ='Perm Loan'!D13 -> 2370000 | AI119: ='Perm Loan'!E13 -> 0 | AJ119: ='Perm Loan'!F13 -> 0 | AK119: ='Perm Loan'!G13 -> 0 | AL119: ='Perm Loan'!H13 -> 0 | AM119: ='Perm Loan'!I13 -> 0 | AN119: ='Perm Loan'!J13 -> 0 | AO119: ='Perm Loan'!K13 -> 0 | ... DN119: ='Perm Loan'!CJ13 -> 0
...

Sheet Labor
B3: Employee | C3: Salary | D3: Hourly Rate
B4: Community Manager | C4: 65000
B5: Maintenance | C5: 60000
B6: Convenience Store Employee #1 | D6: 20
B7: Convenience Store Employee #2 | D7: =D6 -> 20
C10: 0.25 | D10: 0.29166667 | E10: 0.33333333 | F10: 0.375 | G10: 0.41666667 | H10: 0.45833333 | I10: 0.5 | J10: 0.54166667 | K10: 0.58333333 | L10: 0.625 | M10: 0.66666667 | N10: 0.70833333 | O10: 0.75 | P10: 0.79166667 | Q10: 0.83333333 | R10: 0.875 | S10: 0.91666667 | T10: 0.95833333 | U10: 1 | V10: 1.0416667 | W10: 1.0833333 | X10: 1.125 | Y10: 1.1666667 | Z10: 1.2083333
B11: =B4 -> Community Manager | F11: 1 | G11: 1 | H11: 1 | I11: 1 | K11: 1 | L11: 1 | M11: 1 | N11: 1
B12: =B5 -> Maintenance | E12: 1 | F12: 1 | G12: 1 | H12: 1 | K12: 1 | L12: 1 | M12: 1 | N12: 1 | O12: 1 | P12: 1
B13: =B6 -> Convenience Store Employee #1 | E13: 1 | F13: 1 | G13: 1 | H13: 1 | J13: 1 | K13: 1 | L13: 1 | M13: 1
B14: =B7 -> Convenience Store Employee #2 | M14: 1 | N14: 1 | O14: 1 | P14: 1
C17: # Hours | D17: # Days | E17: # Weeks | F17: Total Hours | G17: Hourly Rate | H17: Annual Cost
B18: =B4 -> Community Manager | C18: =COUNT(C11:Z11) -> 8 | D18: 5 | E18: 50 | F18: =C18*D18*E18 -> 2000 | H18: =C4 -> 65000
B19: =B5 -> Maintenance | C19: =COUNT(C12:Z12) -> 10 | D19: =D18 -> 5 | E19: =E18 -> 50 | F19: =C19*D19*E19 -> 2500 | H19: =C5 -> 60000
B20: =B6 -> Convenience Store Employee #1 | C20: =COUNT(C13:Z13) -> 8 | D20: =D19 -> 5 | E20: =E19 -> 50 | F20: =C20*D20*E20 -> 2000 | G20: =D6 -> 20 | H20: =G20*E20*D20*C20 -> 40000
B21: =B7 -> Convenience Store Employee #2 | C21: =COUNT(C14:Z14) -> 4 | D21: =D20 -> 5 | E21: =E20 -> 50 | F21: =C21*D21*E21 -> 1000 | G21: =D7 -> 20 | H21: =G21*E21*D21*C21 -> 20000
G23: Total Annual Labor Cost: | H23: =SUM(H18:H21) -> 185000
G24: Monthly Labor Cost: | H24: =H23/12 -> 15416.667

Sheet Cost Curves
J2: CFO | K2: =Monthly!K3 -> Year 1 | W2: =Monthly!W3 -> Year 2 | AI2: =Monthly!AI3 -> Year 3 | AU2: =Monthly!AU3 -> Year 4 | BG2: =Monthly!BG3 -> Year 5 | BS2: =Monthly!BS3 -> Year 6 | CE2: =Monthly!CE3 -> Year 7 | CQ2: =Monthly!CQ3 -> Year 8 | DC2: =Monthly!DC3 -> Year 9
G3: Total | J3: =Monthly!J4 -> 45383 | K3: =Monthly!K4 -> 45413 | L3: =Monthly!L4 -> 45444 | M3: =Monthly!M4 -> 45474 | N3: =Monthly!N4 -> 45505 | O3: =Monthly!O4 -> 45536 | P3: =Monthly!P4 -> 45566 | Q3: =Monthly!Q4 -> 45597 | ... DN3: =Monthly!DN4 -> 48670 | DP3: Total
C5: DEVELOPMENT COSTS
D6: Hard Costs - Buildings | E6: # of Units | F6: Cost to Complete
D7: RV Pads | E7: ='Table 3.0'!K7 -> 72 | F7: 0 | G7: =SUM(K7:DN7) -> 0 | I7: Cost Curve | DP7: =SUM(K7:DN7) -> 0
D8: Total | E8: =SUM(E7:E7) -> 72 | F8: =F7 -> 0
D11: Total Hard Costs - Buildings | I11: =SUM(I10:I10) -> 0 | K11: =SUM(K10:K10) -> 0 | L11: =SUM(L10:L10) -> 0 | M11: =SUM(M10:M10) -> 0 | N11: =SUM(N10:N10) -> 0 | O11: =SUM(O10:O10) -> 0 | P11: =SUM(P10:P10) -> 0 | Q11: =SUM(Q10:Q10) -> 0 | R11: =SUM(R10:R10) -> 0 | ... BE11: =SUM(BE10:BE10) -> 0 | DP11: =SUM(DP10:DP10) -> 0
D13: Hard Costs - Site | F13: Cost to Complete
D14: Entire Site | F14: =Infrastructure!D35 -> 1369000 | G14: =SUM(K14:DN14) -> 1 | I14: Cost Curve | K14: 0.05 | L14: 0.1 | M14: 0.1 | N14: 0.15 | O14: 0.1 | P14: 0.2 | Q14: 0.15 | R14: 0.15 | DP14: =SUM(K14:DN14) -> 1
I15: Cumm. | K15: =K17/$F$14 -> 0.05 | L15: =SUM(K17:L17)/$F$14 -> 0.15 | M15: =SUM(K17:M17)/$F$14 -> 0.25 | N15: =SUM(K17:N17)/$F$14 -> 0.4 | O15: =SUM(K17:O17)/$F$14 -> 0.5 | P15: =SUM(K17:P17)/$F$14 -> 0.7 | Q15: =SUM(K17:Q17)/$F$14 -> 0.85 | R15: =SUM(K17:R17)/$F$14 -> 1
C17: Total Hard Costs - Site | I17: =SUM(K17:DN17) -> 1369000 | K17: =K14*$F$14 -> 68450 | L17: =L14*$F$14 -> 136900 | M17: =M14*$F$14 -> 136900 | N17: =N14*$F$14 -> 205350 | O17: =O14*$F$14 -> 136900 | P17: =P14*$F$14 -> 273800 | Q17: =Q14*$F$14 -> 205350 | R17: =R14*$F$14 -> 205350 | ... DN17: =DN14*$F$14 -> 0 | DP17: =SUM(K17:DN17) -> 1369000
D19: Hard Costs - Amenities | F19: Cost to Complete
D20: Phase I | F20: =IF('Table 3.0'!L6="y",ROUND(Amenities!N15,-3),0) -> 502000 | G20: =SUM(K20:DN20) -> 1 | I20: Cost Curve | K20: 0.25 | L20: 0.085 | M20: 0.06 | N20: 0.05 | O20: 0.095 | P20: 0.04 | Q20: 0.075 | R20: 0.04 | S20: 0.09 | T20: 0.07 | U20: 0.07 | V20: 0.075 | DP20: =SUM(K20:DN20) -> 1
D21: Phase II | F21: =IF('Table 3.0'!L6="y",ROUND(Amenities!O15,-3),0) -> 129000 | G21: =SUM(K21:DN21) -> 1 | I21: Cost Curve | U21: 0.5 | V21: 0.5 | DP21: =SUM(K21:DN21) -> 1
F22: =SUM(F20:F21) -> 631000 | I22: Cumm. | K22: =K26/$F$22 -> 0.19889065 | L22: =SUM(K26:L26)/$F$22 -> 0.26651347 | M22: =SUM(K26:M26)/$F$22 -> 0.31424723 | N22: =SUM(K26:N26)/$F$22 -> 0.35402536 | O22: =SUM(K26:O26)/$F$22 -> 0.4296038 | P22: =SUM(K26:P26)/$F$22 -> 0.46142631 | Q22: =SUM(K26:Q26)/$F$22 -> 0.5210935 | R22: =SUM(K26:R26)/$F$22 -> 0.55291601 | S22: =SUM(K26:S26)/$F$22 -> 0.62451664 | T22: =SUM(K26:T26)/$F$22 -> 0.68020602 | U22: =SUM(K26:U26)/$F$22 -> 0.8381141 | V22: =SUM(K26:V26)/$F$22 -> 1
G24: Phase I | I24: =SUM(K24:DN24) -> 502000 | K24: =$F$20*K20 -> 125500 | L24: =$F$20*L20 -> 42670 | M24: =$F$20*M20 -> 30120 | N24: =$F$20*N20 -> 25100 | O24: =$F$20*O20 -> 47690 | P24: =$F$20*P20 -> 20080 | Q24: =$F$20*Q20 -> 37650 | R24: =$F$20*R20 -> 20080 | ... BE24: =$F$20*BE20 -> 0 | DP24: =SUM(K24:DN24) -> 502000
G25: Phase II | I25: =SUM(K25:DN25) -> 129000 | K25: =$F$21*K21 -> 0 | L25: =$F$21*L21 -> 0 | M25: =$F$21*M21 -> 0 | N25: =$F$21*N21 -> 0 | O25: =$F$21*O21 -> 0 | P25: =$F$21*P21 -> 0 | Q25: =$F$21*Q21 -> 0 | R25: =$F$21*R21 -> 0 | ... BE25: =$F$21*BE21 -> 0 | DP25: =SUM(K25:DN25) -> 129000
C26: Total Hard Costs - Amenities | I26: =SUM(I24:I25) -> 631000 | K26: =SUM(K24:K25) -> 125500 | L26: =SUM(L24:L25) -> 42670 | M26: =SUM(M24:M25) -> 30120 | N26: =SUM(N24:N25) -> 25100 | O26: =SUM(O24:O25) -> 47690 | P26: =SUM(P24:P25) -> 20080 | Q26: =SUM(Q24:Q25) -> 37650 | R26: =SUM(R24:R25) -> 20080 | ... BE26: =SUM(BE24:BE25) -> 0 | DP26: =SUM(K26:DN26) -> 631000
D28: Hard Costs - FF&E | F28: Cost to Complete
D29: Entire Site | F29: ='FF&E'!L49 -> 222000 | G29: =SUM(K29:DN29) -> 1 | I29: Cost Curve | O29: 0.15 | P29: 0.15 | Q29: 0.15 | R29: 0.15 | S29: 0.15 | T29: 0.15 | U29: 0.1 | DP29: =SUM(K29:DN29) -> 1
I30: Cumm. | O30: =SUM(K32:O32)/$F$29 -> 0.15 | P30: =SUM(K32:P32)/$F$29 -> 0.3 | Q30: =SUM(K32:Q32)/$F$29 -> 0.45 | R30: =SUM(K32:R32)/$F$29 -> 0.6 | S30: =SUM(K32:S32)/$F$29 -> 0.75 | T30: =SUM(K32:T32)/$F$29 -> 0.9 | U30: =SUM(K32:U32)/$F$29 -> 1
C32: Total Hard Costs - FF&E | I32: =SUM(K32:DN32) -> 222000 | K32: =K29*$F$29 -> 0 | L32: =L29*$F$29 -> 0 | M32: =M29*$F$29 -> 0 | N32: =N29*$F$29 -> 0 | O32: =O29*$F$29 -> 33300 | P32: =P29*$F$29 -> 33300 | Q32: =Q29*$F$29 -> 33300 | R32: =R29*$F$29 -> 33300 | ... BE32: =BE29*$F$29 -> 0 | DP32: =SUM(K32:DN32) -> 222000
D34: Soft Costs | E34: # of Units | F34: Cost to Complete
D35: Entire Site | F35: ='Soft Costs'!J83 -> 498000 | G35: =SUM(K35:DN35) -> 1 | I35: Cost Curve | K35: 0.15 | L35: 0.1 | M35: 0.025 | N35: 0.025 | R35: 0.7 | DP35: =SUM(K35:DN35) -> 1
I36: Cumm. | K36: =K38/$F$35 -> 0.15 | L36: =SUM(K38:L38)/$F$35 -> 0.25 | M36: =SUM(K38:M38)/$F$35 -> 0.275 | N36: =SUM(K38:N38)/$F$35 -> 0.3 | O36: =SUM(K38:O38)/$F$35 -> 0.3 | P36: =SUM(K38:P38)/$F$35 -> 0.3 | Q36: =SUM(K38:Q38)/$F$35 -> 0.3 | R36: =SUM(K38:R38)/$F$35 -> 1
C38: Total Soft Costs | I38: =SUM(K38:DN38) -> 498000 | K38: =K35*$F$35 -> 74700 | L38: =L35*$F$35 -> 49800 | M38: =M35*$F$35 -> 12450 | N38: =N35*$F$35 -> 12450 | O38: =O35*$F$35 -> 0 | P38: =P35*$F$35 -> 0 | Q38: =Q35*$F$35 -> 0 | R38: =R35*$F$35 -> 348600 | ... DN38: =DN35*$F$35 -> 0 | DP38: =SUM(K38:DN38) -> 498000

Sheet Infrastructure
B2: Infrastructure Costs
B3: LAYOUT & EXCAVATION | D3: =SUM(C4:C12) -> 762150
B4: Dumpster & Labor | C4: 8000
B5: Construction of site work + ribbon curb | C5: 106250
B6: Site Work + labor & tree removal+ silt fence | C6: 45000
B7: Utility Connections 850 x $45/ft $2950/transformer/2 | C7: 65000
B8: Asphalt & Chipseal + Equipment Rental | C8: 250000
B9: Layout & Excavation & Roadbase/Sand | C9: 26000
B10: Running Electric cable to RV sites | C10: 108900
B11: Water Hydrant line | C11: 45000
B12: Water lines 4000ft x $27 plus labor | C12: 108000
B13: CONCRETE & MASONRY | D13: =SUM(C14:C16) -> 290750
B14: Concrete slabs for RV sites plus labor $1200 x 75 | C14: 90000
B15: Construction of RV sites | C15: 180000 | F15: Alt.: $480,000 in concrete
B16: Rebar for ribbon curb | C16: 20750
B17: OUTSIDE WORK 1 | D17: =SUM(C18:C18) -> 25000
B18: Landscape and Skirting | C18: 25000
B19: OUTSIDE WORK 2 | D19: =SUM(C20:C22) -> 287306
B20: Fire hydrants | C20: 7306
B21: Septic Drip | C21: 95000 | F21: might not need it. Engineers are working to confirm
B22: Septic System for RV Sites | C22: 185000
B23: INTERIOR FINISH (PART II) | D23: =SUM(C24:C24) -> 0
B24: Extras | C24: 0
B25: UTILITY BUILDOUT | D25: =C26 -> 3500
B26: Wifi/Internet - Spectrum | C26: 3500 | F26: still need to finalize this number
B27: ADMIN | D27: =SUM(C28:C30) -> 0
B28: Extras | C28: 0
B29: Overhead & management | C29: 0
B30: Managers Residence | C30: 0
B32: Contingency | C32: See Monthly
B34: TOTAL | D34: =SUM(D3:D33) -> 1368706
B35: ROUNDED | D35: =ROUND(D34,-3) -> 1369000
C37: # of Units
B38: $ per Unit | C38: ='Table 3.0'!K7 -> 72 | D38: =D35/C38 -> 19013.889

Sheet Soft Costs
B2: 1000 Series - Soft/Indirect Costs and Preliminaries
G5: # Units | H5: Unit Type | I5: Cost/Unit | J5: Est. Budget
C7: 1000 Permits / Fees
D8: 1010 | E8: Building Permits | G8: 1 | H8: U | I8: 0 | J8: =G8*I8 -> 0
D9: 1020 | E9: HOA Review Fees
D10: 1030 | E10: Permit Specialist
D11: 1040 | E11: Development & Septic Fees | G11: 1 | H11: U | I11: 25000 | J11: =G11*I11 -> 25000
D12: 1050 | E12: Utility Connection/Tap Fees
D13: 1060 | E13: Storm Water Prevention Plan | G13: 1 | H13: U | I13: 12000 | J13: =G13*I13 -> 12000
D14: 1061 | E14: Water Impact Fee - Crystal Clear | G14: 1 | H14: U | I14: 325000 | J14: =G14*I14 -> 325000
D15: 1062 | E15: TCEQ | G15: 1 | H15: U | I15: 6500 | K15: application fee
C17: 1100 Architectural / Engineering
